Workbook

Sheet Lisez-moi
A1: Chiffrage de l'espace Retraites
A2: La grande transmission : https://bonquentin-collab.github.io/Create-Website/
A4: Contenu
A5: Paramètres : données communes à toutes les réformes (CSG, TVA, emploi, salaires, pensions, composition des revenus), avec leurs sources.
A6: Une feuille par réforme de Retraites › Simuler : TVA sociale, CSG des retraités, Retraites sans impôts, Gel des hautes pensions, Plafond des pensions. Chaque feuille reprend les curseurs du site (cellules jaunes).
A7: Niveaux de vie : effet de chaque réforme sur le niveau de vie médian des actifs et des retraités, et cumul des réformes choisies (Oui/Non).
A8: Rendement : pensions reçues pour 100 000 € cotisés pour une génération, calé sur le TRI du COR (calcul trimestre par trimestre).
A9: Sources : références de chaque donnée.
A10: Vérification
A11: Avec les réglages par défaut du site, chaque résultat est identique à celui du site (écart inférieur à 0,01 Md€ ou à 1 €).
A12: Limites
A13: Ordres de grandeur, sans effets de comportement. Les hypothèses du site (assiettes de CSG par taux, distribution des pensions portée à 2026, composition des revenus) sont décrites à côté de chaque valeur.
... A20: Fond vert pâle : résultat principal

Sheet Paramètres
A1: Paramètres communs
A2: Données sourcées ; modifiables (texte bleu).
A4: Paramètre | B4: Valeur | C4: Source
A5: Personnes en emploi | B5: 30400000 | C5: Insee, Emploi, chômage, revenus du travail, édition 2025 : 30,4 millions de personnes en emploi fin 2024
A6: Masse salariale brute (Md€) | B6: 1108.5 | C6: Insee, Comptes de la Nation 2024, tableau 6.205 (salaires et traitements bruts, total branches)
A7: Ratio salaire net / brut | B7: 0.78 | C7: Hypothèse du simulateur : environ 22 % de cotisations et contributions salariales
A8: Taux de CSG sur les revenus d'activité | B8: 0.092 | C8: Code de la sécurité sociale, art. L136-8
A9: Assiette de la CSG d'activité (part du brut) | B9: 0.9825 | C9: 98,25 % du salaire brut
A10: Valeur d'un point de CSG sur les revenus d'activité (Md€) | B10: 12 | C10: CCSS, rapport de mai 2026, tableau 1 (recettes 2025) ; valeur du point : calcul du simulateur
A11: CSG des retraités : Exonéré | B11: 0 | C11: Code de la sécurité sociale, art. L136-8 ; seuils 2025 : service-public.gouv.fr
A12: CSG des retraités : Taux réduit, 3,8 % | B12: 0.038 | C12: Code de la sécurité sociale, art. L136-8 ; seuils 2025 : service-public.gouv.fr
A13: CSG des retraités : Taux médian, 6,6 % | B13: 0.066 | C13: Code de la sécurité sociale, art. L136-8 ; seuils 2025 : service-public.gouv.fr
A14: CSG des retraités : Taux normal, 8,3 % | B14: 0.083 | C14: Code de la sécurité sociale, art. L136-8 ; seuils 2025 : service-public.gouv.fr
A15: Assiette des pensions au taux normal (Md€, calibrée sur les recettes de CSG) | B15: 225 | C15: Estimation du site, calibrée sur les recettes de CSG 2025 (CCSS, mai 2026)
A16: Assiette des pensions au taux median (Md€, calibrée sur les recettes de CSG) | B16: 87 | C16: Estimation du site, calibrée sur les recettes de CSG 2025 (CCSS, mai 2026)
... A30: Pension moyenne nette de droit direct (€/mois) | B30: 1541 | C30: DREES, édition 2025, pension moyenne de droit direct nette, fin 2023

Sheet TVA sociale
A1: TVA sociale : une hausse de TVA dont toute la recette baisse la CSG des actifs
A4: Hausse de la TVA (points) | B4: 2
A5: Taux concernés | B5: Taux normal
A6: Part de la hausse répercutée dans les prix | B6: 1
A7: Salaire net mensuel (€) | B7: 2100
A8: Pension nette mensuelle (€) | B8: 1541
A10: Recettes (Md€) | B10: =$B$4*IF($B$5="Taux normal",Paramètres!$B$22,Paramètres!$B$23) -> 15
A11: Baisse de CSG des actifs (points) | B11: =MIN(Paramètres!$B$8*100,B10/Paramètres!$B$10) -> 1.25
A12: Hausse des prix (part du revenu) | B12: =$B$4*IF($B$5="Taux normal",Paramètres!$B$24,Paramètres!$B$25)*$B$6 -> 0.0064963504
A13: Actif : gain sur la paie (€/mois) | B13: =($B$7/Paramètres!$B$7)*Paramètres!$B$9*(B11/100) -> 33.064904
A14: Actif : hausse des prix (€/mois) | B14: =$B$7*B12 -> 13.642336
A15: Actif : solde (€/mois) | B15: =B13-B14 -> 19.422568
A16: Retraité : perte la première année (€/mois) | B16: =$B$8*B12 -> 10.010876
A17: Effet sur le niveau de vie des actifs | B17: =Paramètres!$B$27*(Paramètres!$B$9*B11/100/Paramètres!$B$7)-B12 -> 0.0067453564
A18: Effet sur le niveau de vie des retraités | B18: =-B12 -> -0.0064963504

Sheet CSG retraités
A1: CSG des retraités alignée sur celle des actifs (9,2 %), recette reversée aux actifs
A4: Retraités concernés | B4: Taux normal seulement
A5: Votre pension brute mensuelle (€) | B5: 1800
A6: Votre taux de CSG actuel | B6: normal
A7: Salaire net mensuel d'un actif (€) | B7: 2100
A9: Taux | B9: Taux actuel | C9: Assiette (Md€) | D9: Concerné | E9: Nouveau taux | F9: Recette (Md€)
A10: exonere | B10: =Paramètres!$B$11 -> 0 | C10: =0 -> 0 | D10: =IF($B$4="Taux normal seulement",IF(A10="normal",1,0),IF(A10="exonere",0,1)) -> 0 | E10: =IF(D10=1,Paramètres!$B$8,B10) -> 0 | F10: =D10*C10*(Paramètres!$B$8-B10) -> 0
A11: reduit | B11: =Paramètres!$B$12 -> 0.038 | C11: =Paramètres!$B$17 -> 27 | D11: =IF($B$4="Taux normal seulement",IF(A11="normal",1,0),IF(A11="exonere",0,1)) -> 0 | E11: =IF(D11=1,Paramètres!$B$8,B11) -> 0.038 | F11: =D11*C11*(Paramètres!$B$8-B11) -> 0
A12: median | B12: =Paramètres!$B$13 -> 0.066 | C12: =Paramètres!$B$16 -> 87 | D12: =IF($B$4="Taux normal seulement",IF(A12="normal",1,0),IF(A12="exonere",0,1)) -> 0 | E12: =IF(D12=1,Paramètres!$B$8,B12) -> 0.066 | F12: =D12*C12*(Paramètres!$B$8-B12) -> 0
A13: normal | B13: =Paramètres!$B$14 -> 0.083 | C13: =Paramètres!$B$15 -> 225 | D13: =IF($B$4="Taux normal seulement",IF(A13="normal",1,0),IF(A13="exonere",0,1)) -> 1 | E13: =IF(D13=1,Paramètres!$B$8,B13) -> 0.092 | F13: =D13*C13*(Paramètres!$B$8-B13) -> 2.025
A15: Recettes (Md€) | B15: =SUM(F10:F13) -> 2.025
A16: Baisse de CSG des actifs (points) | B16: =B15/Paramètres!$B$10 -> 0.16875
A17: Gain d'un actif (€/mois) | B17: =($B$7/Paramètres!$B$7)*Paramètres!$B$9*(B16/100) -> 4.463762
A18: Perte de votre pension (€/mois) | B18: =$B$5*MAX(0,INDEX(E10:E13,MATCH($B$6,A10:A13,0))-INDEX(B10:B13,MATCH($B$6,A10:A13,0))) -> 16.2
A19: Effet sur le niveau de vie des actifs | B19: =Paramètres!$B$27*(Paramètres!$B$9*B16/100/Paramètres!$B$7) -> 0.0017876304
A20: Effet sur le niveau de vie des retraités | B20: =-Paramètres!$B$26*B15/Paramètres!$B$28 -> -0.003938625

Sheet Sans impôts
A1: Retraites financées par leurs seules ressources « logiques »
A2: Gardée = 1 : la ressource continue de financer les retraites. Les ressources « fixes » sont toujours gardées.
A4: Part du trou comblée par une baisse des pensions (le reste : hausse des cotisations) | B4: 0.5
A5: Pension nette mensuelle (€) | B5: 1541
A6: Salaire net mensuel (€) | B6: 2100
A7: Argent public libéré reversé aux actifs (Md€ par an) | B7: 0
A9: Ressource (COR 2026, tableau 2.2) | B9: Montant (Md€) | C9: Fixe | D9: Gardée (1/0) | E9: Retirée (Md€)
A10: Cotisations des salariés, des employeurs et des indépendants | B10: 277 | C10: 1 | D10: =1 -> 1 | E10: =IF(OR(C10=1,D10=1),0,B10) -> 0
A11: État employeur : la part équivalente à une cotisation normale | B11: 21 | C11: 0 | D11: 1 | E11: =IF(OR(C11=1,D11=1),0,B11) -> 0
A12: État employeur : le complément qui équilibre le régime des fonctionnaires | B12: 28.3 | C12: 0 | D12: 0 | E12: =IF(OR(C12=1,D12=1),0,B12) -> 28.3
A13: Subventions d'équilibre aux régimes spéciaux (SNCF, RATP, mines, marins…) | B13: 7.7 | C13: 0 | D13: 0 | E13: =IF(OR(C13=1,D13=1),0,B13) -> 7.7
A14: CSG affectée aux retraites | B14: 21.9 | C14: 0 | D14: 0 | E14: =IF(OR(C14=1,D14=1),0,B14) -> 21.9
A15: Forfait social et taxe sur les salaires | B15: 17.9 | C15: 0 | D15: 1 | E15: =IF(OR(C15=1,D15=1),0,B15) -> 0
A16: TVA et taxes sur la consommation | B16: 17.4 | C16: 0 | D16: 0 | E16: =IF(OR(C16=1,D16=1),0,B16) -> 17.4
A17: Autres impôts et taxes affectés | B17: 7.4 | C17: 0 | D17: 0 | E17: =IF(OR(C17=1,D17=1),0,B17) -> 7.4
A18: Transferts de la branche famille (trimestres des parents au foyer) | B18: 11.2 | C18: 0 | D18: 1 | E18: =IF(OR(C18=1,D18=1),0,B18) -> 0
A19: Transferts de l'assurance chômage (trimestres de chômage) | B19: 3.9 | C19: 0 | D19: 1 | E19: =IF(OR(C19=1,D19=1),0,B19) -> 0
A20: Autres transferts | B20: 1.3 | C20: 0 | D20: 0 | E20: =IF(OR(C20=1,D20=1),0,B20) -> 1.3
A21: Produits financiers et autres produits | B21: 7 | C21: 1 | D21: =1 -> 1 | E21: =IF(OR(C21=1,D21=1),0,B21) -> 0
A23: Ressources retirées : le trou à combler (Md€) | B23: =SUM(E10:E21) -> 84
A24: Comblé par la baisse des pensions (Md€) | B24: =B23*$B$4 -> 42
A25: Comblé par la hausse des cotisations (Md€) | B25: =B23-B24 -> 42
A26: Baisse des pensions | B26: =B24/Paramètres!$B$29 -> 0.09947892
A27: Hausse des cotisations (points de salaire brut) | B27: =B25/Paramètres!$B$6 -> 0.037889039
A28: Pension après (€/mois) | B28: =$B$5*(1-B26) -> 1387.703
A29: Perte sur le salaire (€/mois) | B29: =$B$6/Paramètres!$B$7*B27 -> 102.00895
A30: Effet sur le niveau de vie des actifs | B30: =Paramètres!$B$27*(-B27/Paramètres!$B$7+$B$7/(Paramètres!$B$6*Paramètres!$B$7)) -> -0.040852156
A31: Effet sur le niveau de vie des retraités | B31: =-Paramètres!$B$26*B26 -> -0.0773946

Sheet Gel
A1: Gel de la revalorisation des pensions au-delà d'un seuil
A2: Calé sur l'IPP (2026) : pension de base = deux tiers, économie nette des finances publiques, taux d'annuité.
A4: Seuil de pension totale brute (€/mois) | B4: 2000
A5: Revalorisation non versée | B5: 0.009
A6: Ce qui n'est pas revalorisé | B6: Toute la pension
A7: Part de la pension venant des régimes de base | B7: 0.67
A8: Appliquer aussi aux futurs retraités (taux d'annuité) | B8: Non
A9: Votre pension brute mensuelle totale (€) | B9: 2500
A10: Salaire net d'un actif (€/mois) | B10: 2100
A12: Retraités de droit direct | B12: 17300000 | C12: Drees, effectifs de retraités fin 2024 (17,3 millions de retraités de droit direct, dont 16,4 en France)
A13: Passage des euros 2020 aux pensions 2026 | B13: 1.19 | C13: Estimation du site (COR, figure 3.25 ; revalorisations 2025-2026)
A14: Pension moyenne de la tranche ouverte « 4 500 € et plus » (€ 2020) | B14: 6000 | C14: Estimation du site, cohérente avec la pension moyenne totale fin 2020
A15: Économie nette / économie des régimes (finances publiques) | B15: 0.78 | C15: IPP, Perspectives budgétaires 2027, chapitre 3 : sous-indexation des retraites (Aubert, Tô, Tochev, 2026) : « environ 20 % à 25 % » de moins
A16: Sortie annuelle des retraités actuels (décès) | B16: 0.03 | C16: Insee Première n° 2087, Bilan démographique 2025
A17: Horizon (années après 2026) | B17: 10 | C17: 2036
A18: Taux plein | B18: 0.5 | C18: Régime général
A19: Trimestres requis | B19: 172 | C19: Générations nées à partir de 1965
A20: Prélèvements sur une pension au taux normal (CSG, CRDS, Casa) | B20: 0.091 | C20: 8,3 % + 0,5 % + 0,3 %
A21: Taux d'épargne des ménages de 70 ans ou plus | B21: 0.218 | C21: Insee Première n° 1815, 2020 (enquête Budget de famille 2017)
A23: Résultats
A24: Part des retraités au-dessus du seuil | B24: =G97 -> 0.4125395
A25: Retraités concernés | B25: =G97*$B$12 -> 7136933.3
A26: Économie des régimes, première année (Md€) | B26: =$B$12*12*IF($B$6="Toute la pension",H97,I97)*$B$7*$B$5/1000000000 -> 1.5677174
A27: Gain net pour les finances publiques (Md€) | B27: =B26*$B$15 -> 1.2228196
A28: Économie la dernière année de l'horizon (Md€) | B28: =IF($B$8="Oui",B26,B26*(1-$B$16)^$B$17) -> 1.1560726
A29: Cumul sur l'horizon, première année comprise (Md€) | B29: =IF($B$8="Oui",B26*($B$17+1),B26*(1-(1-$B$16)^($B$17+1))/$B$16) -> 14.877565
A30: Votre perte (€ brut par mois) | B30: =IF($B$9<=$B$4,0,IF($B$6="Toute la pension",$B$9,$B$9-$B$4)*$B$7*$B$5) -> 15.075
A31: Valeur d'un trimestre aujourd'hui (part du salaire de référence) | B31: =$B$18/$B$19 -> 0.0029069767
A32: Valeur d'un trimestre pour un futur retraité concerné | B32: =IF($B$6="Toute la pension",B31*(1-$B$5),IF($B$9>$B$4,B31*(1-$B$5*($B$9-$B$4)/$B$9),"sous le seuil")) -> 0.002880814
A33: Baisse de CSG des actifs (points) | B33: =B26/Paramètres!$B$10 -> 0.13064312
A34: Gain d'un actif (€/mois) | B34: =($B$10/Paramètres!$B$7)*Paramètres!$B$9*(B33/100) -> 3.4557617
A35: Votre perte nette (€/mois) | B35: =B30*(1-$B$20) -> 13.703175
A36: Épargne mensuelle à cette pension (€) | B36: =$B$9*(1-$B$20)*$B$21 -> 495.405
A37: La perte en part de cette épargne | B37: =IF(B36>0,B35/B36,0) -> 0.02766055
A38: Effet sur le niveau de vie des actifs | B38: =Paramètres!$B$27*(Paramètres!$B$9*B33/100/Paramètres!$B$7) -> 0.0013839503
A39: Effet sur le niveau de vie des retraités | B39: =-Paramètres!$B$26*B26/Paramètres!$B$28 -> -0.0030492103
A40: Masse totale des pensions (Md€, contrôle) | B40: =$B$12*12*F97/1000000000 -> 402.23086
A49: Distribution des pensions totales brutes (Drees, EIR 2020, tableau 5), portée à 2026
A50: De (€ 2020) | B50: À (€ 2020) | C50: Part (%) | D50: De (€ 2026) | E50: À (€ 2026) | F50: Contribution à la moyenne | G50: Part au-dessus du seuil | H50: Masse au-dessus | I50: Masse au-delà du seuil
A51: 0 | B51: 100 | C51: 2.43 | D51: =A51*$B$13 -> 0 | E51: =B51*$B$13 -> 119 | F51: =C51/100*(D51+E51)/2 -> 1.44585 | G51: =IF(E51<=$B$4,0,(C51/100*(E51-MAX(D51,$B$4))/(E51-D51))) -> 0 | H51: =IF(E51<=$B$4,0,(C51/100*(E51-MAX(D51,$B$4))/(E51-D51))*(MAX(D51,$B$4)+E51)/2) -> 0 | I51: =IF(E51<=$B$4,0,(C51/100*(E51-MAX(D51,$B$4))/(E51-D51))*(MAX(D51,$B$4)+E51)/2-(C51/100*(E51-MAX(D51,$B$4))/(E51-D51))*$B$4) -> 0
A52: 100 | B52: 200 | C52: 2.46 | D52: =A52*$B$13 -> 119 | E52: =B52*$B$13 -> 238 | F52: =C52/100*(D52+E52)/2 -> 4.3911 | G52: =IF(E52<=$B$4,0,(C52/100*(E52-MAX(D52,$B$4))/(E52-D52))) -> 0 | H52: =IF(E52<=$B$4,0,(C52/100*(E52-MAX(D52,$B$4))/(E52-D52))*(MAX(D52,$B$4)+E52)/2) -> 0 | I52: =IF(E52<=$B$4,0,(C52/100*(E52-MAX(D52,$B$4))/(E52-D52))*(MAX(D52,$B$4)+E52)/2-(C52/100*(E52-MAX(D52,$B$4))/(E52-D52))*$B$4) -> 0
A53: 200 | B53: 300 | C53: 2.35 | D53: =A53*$B$13 -> 238 | E53: =B53*$B$13 -> 357 | F53: =C53/100*(D53+E53)/2 -> 6.99125 | G53: =IF(E53<=$B$4,0,(C53/100*(E53-MAX(D53,$B$4))/(E53-D53))) -> 0 | H53: =IF(E53<=$B$4,0,(C53/100*(E53-MAX(D53,$B$4))/(E53-D53))*(MAX(D53,$B$4)+E53)/2) -> 0 | I53: =IF(E53<=$B$4,0,(C53/100*(E53-MAX(D53,$B$4))/(E53-D53))*(MAX(D53,$B$4)+E53)/2-(C53/100*(E53-MAX(D53,$B$4))/(E53-D53))*$B$4) -> 0
A54: 300 | B54: 400 | C54: 2.17 | D54: =A54*$B$13 -> 357 | E54: =B54*$B$13 -> 476 | F54: =C54/100*(D54+E54)/2 -> 9.03805 | G54: =IF(E54<=$B$4,0,(C54/100*(E54-MAX(D54,$B$4))/(E54-D54))) -> 0 | H54: =IF(E54<=$B$4,0,(C54/100*(E54-MAX(D54,$B$4))/(E54-D54))*(MAX(D54,$B$4)+E54)/2) -> 0 | I54: =IF(E54<=$B$4,0,(C54/100*(E54-MAX(D54,$B$4))/(E54-D54))*(MAX(D54,$B$4)+E54)/2-(C54/100*(E54-MAX(D54,$B$4))/(E54-D54))*$B$4) -> 0
A55: 400 | B55: 500 | C55: 2 | D55: =A55*$B$13 -> 476 | E55: =B55*$B$13 -> 595 | F55: =C55/100*(D55+E55)/2 -> 10.71 | G55: =IF(E55<=$B$4,0,(C55/100*(E55-MAX(D55,$B$4))/(E55-D55))) -> 0 | H55: =IF(E55<=$B$4,0,(C55/100*(E55-MAX(D55,$B$4))/(E55-D55))*(MAX(D55,$B$4)+E55)/2) -> 0 | I55: =IF(E55<=$B$4,0,(C55/100*(E55-MAX(D55,$B$4))/(E55-D55))*(MAX(D55,$B$4)+E55)/2-(C55/100*(E55-MAX(D55,$B$4))/(E55-D55))*$B$4) -> 0
A56: 500 | B56: 600 | C56: 2.06 | D56: =A56*$B$13 -> 595 | E56: =B56*$B$13 -> 714 | F56: =C56/100*(D56+E56)/2 -> 13.4827 | G56: =IF(E56<=$B$4,0,(C56/100*(E56-MAX(D56,$B$4))/(E56-D56))) -> 0 | H56: =IF(E56<=$B$4,0,(C56/100*(E56-MAX(D56,$B$4))/(E56-D56))*(MAX(D56,$B$4)+E56)/2) -> 0 | I56: =IF(E56<=$B$4,0,(C56/100*(E56-MAX(D56,$B$4))/(E56-D56))*(MAX(D56,$B$4)+E56)/2-(C56/100*(E56-MAX(D56,$B$4))/(E56-D56))*$B$4) -> 0
A57: 600 | B57: 700 | C57: 2.28 | D57: =A57*$B$13 -> 714 | E57: =B57*$B$13 -> 833 | F57: =C57/100*(D57+E57)/2 -> 17.6358 | G57: =IF(E57<=$B$4,0,(C57/100*(E57-MAX(D57,$B$4))/(E57-D57))) -> 0 | H57: =IF(E57<=$B$4,0,(C57/100*(E57-MAX(D57,$B$4))/(E57-D57))*(MAX(D57,$B$4)+E57)/2) -> 0 | I57: =IF(E57<=$B$4,0,(C57/100*(E57-MAX(D57,$B$4))/(E57-D57))*(MAX(D57,$B$4)+E57)/2-(C57/100*(E57-MAX(D57,$B$4))/(E57-D57))*$B$4) -> 0
A58: 700 | B58: 800 | C58: 2.94 | D58: =A58*$B$13 -> 833 | E58: =B58*$B$13 -> 952 | F58: =C58/100*(D58+E58)/2 -> 26.2395 | G58: =IF(E58<=$B$4,0,(C58/100*(E58-MAX(D58,$B$4))/(E58-D58))) -> 0 | H58: =IF(E58<=$B$4,0,(C58/100*(E58-MAX(D58,$B$4))/(E58-D58))*(MAX(D58,$B$4)+E58)/2) -> 0 | I58: =IF(E58<=$B$4,0,(C58/100*(E58-MAX(D58,$B$4))/(E58-D58))*(MAX(D58,$B$4)+E58)/2-(C58/100*(E58-MAX(D58,$B$4))/(E58-D58))*$B$4) -> 0
A59: 800 | B59: 900 | C59: 4.36 | D59: =A59*$B$13 -> 952 | E59: =B59*$B$13 -> 1071 | F59: =C59/100*(D59+E59)/2 -> 44.1014 | G59: =IF(E59<=$B$4,0,(C59/100*(E59-MAX(D59,$B$4))/(E59-D59))) -> 0 | H59: =IF(E59<=$B$4,0,(C59/100*(E59-MAX(D59,$B$4))/(E59-D59))*(MAX(D59,$B$4)+E59)/2) -> 0 | I59: =IF(E59<=$B$4,0,(C59/100*(E59-MAX(D59,$B$4))/(E59-D59))*(MAX(D59,$B$4)+E59)/2-(C59/100*(E59-MAX(D59,$B$4))/(E59-D59))*$B$4) -> 0
A60: 900 | B60: 1000 | C60: 4.44 | D60: =A60*$B$13 -> 1071 | E60: =B60*$B$13 -> 1190 | F60: =C60/100*(D60+E60)/2 -> 50.1942 | G60: =IF(E60<=$B$4,0,(C60/100*(E60-MAX(D60,$B$4))/(E60-D60))) -> 0 | H60: =IF(E60<=$B$4,0,(C60/100*(E60-MAX(D60,$B$4))/(E60-D60))*(MAX(D60,$B$4)+E60)/2) -> 0 | I60: =IF(E60<=$B$4,0,(C60/100*(E60-MAX(D60,$B$4))/(E60-D60))*(MAX(D60,$B$4)+E60)/2-(C60/100*(E60-MAX(D60,$B$4))/(E60-D60))*$B$4) -> 0
A61: 1000 | B61: 1100 | C61: 4.2 | D61: =A61*$B$13 -> 1190 | E61: =B61*$B$13 -> 1309 | F61: =C61/100*(D61+E61)/2 -> 52.479 | G61: =IF(E61<=$B$4,0,(C61/100*(E61-MAX(D61,$B$4))/(E61-D61))) -> 0 | H61: =IF(E61<=$B$4,0,(C61/100*(E61-MAX(D61,$B$4))/(E61-D61))*(MAX(D61,$B$4)+E61)/2) -> 0 | I61: =IF(E61<=$B$4,0,(C61/100*(E61-MAX(D61,$B$4))/(E61-D61))*(MAX(D61,$B$4)+E61)/2-(C61/100*(E61-MAX(D61,$B$4))/(E61-D61))*$B$4) -> 0
A62: 1100 | B62: 1200 | C62: 4.4 | D62: =A62*$B$13 -> 1309 | E62: =B62*$B$13 -> 1428 | F62: =C62/100*(D62+E62)/2 -> 60.214 | G62: =IF(E62<=$B$4,0,(C62/100*(E62-MAX(D62,$B$4))/(E62-D62))) -> 0 | H62: =IF(E62<=$B$4,0,(C62/100*(E62-MAX(D62,$B$4))/(E62-D62))*(MAX(D62,$B$4)+E62)/2) -> 0 | I62: =IF(E62<=$B$4,0,(C62/100*(E62-MAX(D62,$B$4))/(E62-D62))*(MAX(D62,$B$4)+E62)/2-(C62/100*(E62-MAX(D62,$B$4))/(E62-D62))*$B$4) -> 0
... A95: 4400 | B95: 4500 | C95: 0.18 | D95: =A95*$B$13 -> 5236 | E95: =B95*$B$13 -> 5355 | F95: =C95/100*(D95+E95)/2 -> 9.5319 | G95: =IF(E95<=$B$4,0,(C95/100*(E95-MAX(D95,$B$4))/(E95-D95))) -> 0.0018 | H95: =IF(E95<=$B$4,0,(C95/100*(E95-MAX(D95,$B$4))/(E95-D95))*(MAX(D95,$B$4)+E95)/2) -> 9.5319 | I95: =IF(E95<=$B$4,0,(C95/100*(E95-MAX(D95,$B$4))/(E95-D95))*(MAX(D95,$B$4)+E95)/2-(C95/100*(E95-MAX(D95,$B$4))/(E95-D95))*$B$4) -> 5.9319
A96: 4500 | B96: et plus | C96: 1.82 | D96: =A96*$B$13 -> 5355 | E96: =$B$14*$B$13 -> 7140 | F96: =C96/100*E96 -> 129.948 | G96: =IF(E96>$B$4,C96/100,0) -> 0.0182 | H96: =IF(E96>$B$4,C96/100*E96,0) -> 129.948 | I96: =IF(E96>$B$4,C96/100*(E96-$B$4),0) -> 93.548
A97: Total (par retraité, €/mois) | F97: =SUM(F51:F96) -> 1937.5283 | G97: =SUM(G51:G96) -> 0.4125395 | H97: =SUM(H51:H96) -> 1252.3425 | I97: =SUM(I51:I96) -> 427.2635

Sheet Plafond
A1: Plafond des pensions : aucune pension totale au-delà d'un montant choisi
A4: Plafond de la pension totale brute (€/mois) | B4: 4000
A5: Votre pension brute mensuelle (€) | B5: 5000
A6: Part de l'économie versée aux actifs (salaires) | B6: 0
A8: Retraités, facteur 2020 → 2026 et tranche ouverte : repris de la feuille Gel.
A10: Résultats
A11: Part des retraités au-dessus du plafond | B11: =G77 -> 0.054403361
A12: Retraités concernés | B12: =G77*Gel!$B$12 -> 941178.15
A13: Économie annuelle (Md€) | B13: =Gel!$B$12*12*I77/1000000000 -> 15.904792
A14: En part de l'ensemble des pensions | B14: =B13/(Gel!$B$12*12*F77/1000000000) -> 0.03954145
A15: Gain net pour les finances publiques (Md€) | B15: =B13*Gel!$B$15 -> 12.405738
A16: Votre perte (€ brut par mois) | B16: =MAX(0,$B$5-$B$4) -> 1000
A17: Effet sur le niveau de vie des actifs | B17: =Paramètres!$B$27*(B13*$B$6/(Paramètres!$B$6*Paramètres!$B$7)) -> 0
A18: Effet sur le niveau de vie des retraités | B18: =-Paramètres!$B$26*B13/Paramètres!$B$28 -> -0.03093482
A29: Distribution des pensions (même source que la feuille Gel)
A30: De (€ 2020) | B30: À (€ 2020) | C30: Part (%) | D30: De (€ 2026) | E30: À (€ 2026) | F30: Contribution à la moyenne | G30: Part au-dessus du seuil | H30: Masse au-dessus | I30: Masse au-delà du seuil
A31: 0 | B31: 100 | C31: 2.43 | D31: =A31*Gel!$B$13 -> 0 | E31: =B31*Gel!$B$13 -> 119 | F31: =C31/100*(D31+E31)/2 -> 1.44585 | G31: =IF(E31<=$B$4,0,(C31/100*(E31-MAX(D31,$B$4))/(E31-D31))) -> 0 | H31: =IF(E31<=$B$4,0,(C31/100*(E31-MAX(D31,$B$4))/(E31-D31))*(MAX(D31,$B$4)+E31)/2) -> 0 | I31: =IF(E31<=$B$4,0,(C31/100*(E31-MAX(D31,$B$4))/(E31-D31))*(MAX(D31,$B$4)+E31)/2-(C31/100*(E31-MAX(D31,$B$4))/(E31-D31))*$B$4) -> 0
A32: 100 | B32: 200 | C32: 2.46 | D32: =A32*Gel!$B$13 -> 119 | E32: =B32*Gel!$B$13 -> 238 | F32: =C32/100*(D32+E32)/2 -> 4.3911 | G32: =IF(E32<=$B$4,0,(C32/100*(E32-MAX(D32,$B$4))/(E32-D32))) -> 0 | H32: =IF(E32<=$B$4,0,(C32/100*(E32-MAX(D32,$B$4))/(E32-D32))*(MAX(D32,$B$4)+E32)/2) -> 0 | I32: =IF(E32<=$B$4,0,(C32/100*(E32-MAX(D32,$B$4))/(E32-D32))*(MAX(D32,$B$4)+E32)/2-(C32/100*(E32-MAX(D32,$B$4))/(E32-D32))*$B$4) -> 0
A33: 200 | B33: 300 | C33: 2.35 | D33: =A33*Gel!$B$13 -> 238 | E33: =B33*Gel!$B$13 -> 357 | F33: =C33/100*(D33+E33)/2 -> 6.99125 | G33: =IF(E33<=$B$4,0,(C33/100*(E33-MAX(D33,$B$4))/(E33-D33))) -> 0 | H33: =IF(E33<=$B$4,0,(C33/100*(E33-MAX(D33,$B$4))/(E33-D33))*(MAX(D33,$B$4)+E33)/2) -> 0 | I33: =IF(E33<=$B$4,0,(C33/100*(E33-MAX(D33,$B$4))/(E33-D33))*(MAX(D33,$B$4)+E33)/2-(C33/100*(E33-MAX(D33,$B$4))/(E33-D33))*$B$4) -> 0
A34: 300 | B34: 400 | C34: 2.17 | D34: =A34*Gel!$B$13 -> 357 | E34: =B34*Gel!$B$13 -> 476 | F34: =C34/100*(D34+E34)/2 -> 9.03805 | G34: =IF(E34<=$B$4,0,(C34/100*(E34-MAX(D34,$B$4))/(E34-D34))) -> 0 | H34: =IF(E34<=$B$4,0,(C34/100*(E34-MAX(D34,$B$4))/(E34-D34))*(MAX(D34,$B$4)+E34)/2) -> 0 | I34: =IF(E34<=$B$4,0,(C34/100*(E34-MAX(D34,$B$4))/(E34-D34))*(MAX(D34,$B$4)+E34)/2-(C34/100*(E34-MAX(D34,$B$4))/(E34-D34))*$B$4) -> 0
A35: 400 | B35: 500 | C35: 2 | D35: =A35*Gel!$B$13 -> 476 | E35: =B35*Gel!$B$13 -> 595 | F35: =C35/100*(D35+E35)/2 -> 10.71 | G35: =IF(E35<=$B$4,0,(C35/100*(E35-MAX(D35,$B$4))/(E35-D35))) -> 0 | H35: =IF(E35<=$B$4,0,(C35/100*(E35-MAX(D35,$B$4))/(E35-D35))*(MAX(D35,$B$4)+E35)/2) -> 0 | I35: =IF(E35<=$B$4,0,(C35/100*(E35-MAX(D35,$B$4))/(E35-D35))*(MAX(D35,$B$4)+E35)/2-(C35/100*(E35-MAX(D35,$B$4))/(E35-D35))*$B$4) -> 0
A36: 500 | B36: 600 | C36: 2.06 | D36: =A36*Gel!$B$13 -> 595 | E36: =B36*Gel!$B$13 -> 714 | F36: =C36/100*(D36+E36)/2 -> 13.4827 | G36: =IF(E36<=$B$4,0,(C36/100*(E36-MAX(D36,$B$4))/(E36-D36))) -> 0 | H36: =IF(E36<=$B$4,0,(C36/100*(E36-MAX(D36,$B$4))/(E36-D36))*(MAX(D36,$B$4)+E36)/2) -> 0 | I36: =IF(E36<=$B$4,0,(C36/100*(E36-MAX(D36,$B$4))/(E36-D36))*(MAX(D36,$B$4)+E36)/2-(C36/100*(E36-MAX(D36,$B$4))/(E36-D36))*$B$4) -> 0
A37: 600 | B37: 700 | C37: 2.28 | D37: =A37*Gel!$B$13 -> 714 | E37: =B37*Gel!$B$13 -> 833 | F37: =C37/100*(D37+E37)/2 -> 17.6358 | G37: =IF(E37<=$B$4,0,(C37/100*(E37-MAX(D37,$B$4))/(E37-D37))) -> 0 | H37: =IF(E37<=$B$4,0,(C37/100*(E37-MAX(D37,$B$4))/(E37-D37))*(MAX(D37,$B$4)+E37)/2) -> 0 | I37: =IF(E37<=$B$4,0,(C37/100*(E37-MAX(D37,$B$4))/(E37-D37))*(MAX(D37,$B$4)+E37)/2-(C37/100*(E37-MAX(D37,$B$4))/(E37-D37))*$B$4) -> 0
A38: 700 | B38: 800 | C38: 2.94 | D38: =A38*Gel!$B$13 -> 833 | E38: =B38*Gel!$B$13 -> 952 | F38: =C38/100*(D38+E38)/2 -> 26.2395 | G38: =IF(E38<=$B$4,0,(C38/100*(E38-MAX(D38,$B$4))/(E38-D38))) -> 0 | H38: =IF(E38<=$B$4,0,(C38/100*(E38-MAX(D38,$B$4))/(E38-D38))*(MAX(D38,$B$4)+E38)/2) -> 0 | I38: =IF(E38<=$B$4,0,(C38/100*(E38-MAX(D38,$B$4))/(E38-D38))*(MAX(D38,$B$4)+E38)/2-(C38/100*(E38-MAX(D38,$B$4))/(E38-D38))*$B$4) -> 0
A39: 800 | B39: 900 | C39: 4.36 | D39: =A39*Gel!$B$13 -> 952 | E39: =B39*Gel!$B$13 -> 1071 | F39: =C39/100*(D39+E39)/2 -> 44.1014 | G39: =IF(E39<=$B$4,0,(C39/100*(E39-MAX(D39,$B$4))/(E39-D39))) -> 0 | H39: =IF(E39<=$B$4,0,(C39/100*(E39-MAX(D39,$B$4))/(E39-D39))*(MAX(D39,$B$4)+E39)/2) -> 0 | I39: =IF(E39<=$B$4,0,(C39/100*(E39-MAX(D39,$B$4))/(E39-D39))*(MAX(D39,$B$4)+E39)/2-(C39/100*(E39-MAX(D39,$B$4))/(E39-D39))*$B$4) -> 0
A40: 900 | B40: 1000 | C40: 4.44 | D40: =A40*Gel!$B$13 -> 1071 | E40: =B40*Gel!$B$13 -> 1190 | F40: =C40/100*(D40+E40)/2 -> 50.1942 | G40: =IF(E40<=$B$4,0,(C40/100*(E40-MAX(D40,$B$4))/(E40-D40))) -> 0 | H40: =IF(E40<=$B$4,0,(C40/100*(E40-MAX(D40,$B$4))/(E40-D40))*(MAX(D40,$B$4)+E40)/2) -> 0 | I40: =IF(E40<=$B$4,0,(C40/100*(E40-MAX(D40,$B$4))/(E40-D40))*(MAX(D40,$B$4)+E40)/2-(C40/100*(E40-MAX(D40,$B$4))/(E40-D40))*$B$4) -> 0
A41: 1000 | B41: 1100 | C41: 4.2 | D41: =A41*Gel!$B$13 -> 1190 | E41: =B41*Gel!$B$13 -> 1309 | F41: =C41/100*(D41+E41)/2 -> 52.479 | G41: =IF(E41<=$B$4,0,(C41/100*(E41-MAX(D41,$B$4))/(E41-D41))) -> 0 | H41: =IF(E41<=$B$4,0,(C41/100*(E41-MAX(D41,$B$4))/(E41-D41))*(MAX(D41,$B$4)+E41)/2) -> 0 | I41: =IF(E41<=$B$4,0,(C41/100*(E41-MAX(D41,$B$4))/(E41-D41))*(MAX(D41,$B$4)+E41)/2-(C41/100*(E41-MAX(D41,$B$4))/(E41-D41))*$B$4) -> 0
A42: 1100 | B42: 1200 | C42: 4.4 | D42: =A42*Gel!$B$13 -> 1309 | E42: =B42*Gel!$B$13 -> 1428 | F42: =C42/100*(D42+E42)/2 -> 60.214 | G42: =IF(E42<=$B$4,0,(C42/100*(E42-MAX(D42,$B$4))/(E42-D42))) -> 0 | H42: =IF(E42<=$B$4,0,(C42/100*(E42-MAX(D42,$B$4))/(E42-D42))*(MAX(D42,$B$4)+E42)/2) -> 0 | I42: =IF(E42<=$B$4,0,(C42/100*(E42-MAX(D42,$B$4))/(E42-D42))*(MAX(D42,$B$4)+E42)/2-(C42/100*(E42-MAX(D42,$B$4))/(E42-D42))*$B$4) -> 0
... A75: 4400 | B75: 4500 | C75: 0.18 | D75: =A75*Gel!$B$13 -> 5236 | E75: =B75*Gel!$B$13 -> 5355 | F75: =C75/100*(D75+E75)/2 -> 9.5319 | G75: =IF(E75<=$B$4,0,(C75/100*(E75-MAX(D75,$B$4))/(E75-D75))) -> 0.0018 | H75: =IF(E75<=$B$4,0,(C75/100*(E75-MAX(D75,$B$4))/(E75-D75))*(MAX(D75,$B$4)+E75)/2) -> 9.5319 | I75: =IF(E75<=$B$4,0,(C75/100*(E75-MAX(D75,$B$4))/(E75-D75))*(MAX(D75,$B$4)+E75)/2-(C75/100*(E75-MAX(D75,$B$4))/(E75-D75))*$B$4) -> 2.3319
A76: 4500 | B76: et plus | C76: 1.82 | D76: =A76*Gel!$B$13 -> 5355 | E76: =Gel!$B$14*Gel!$B$13 -> 7140 | F76: =C76/100*E76 -> 129.948 | G76: =IF(E76>$B$4,C76/100,0) -> 0.0182 | H76: =IF(E76>$B$4,C76/100*E76,0) -> 129.948 | I76: =IF(E76>$B$4,C76/100*(E76-$B$4),0) -> 57.148
A77: Total (par retraité, €/mois) | F77: =SUM(F31:F76) -> 1937.5283 | G77: =SUM(G31:G76) -> 0.054403361 | H77: =SUM(H31:H76) -> 294.22612 | I77: =SUM(I31:I76) -> 76.612677

Sheet Niveaux de vie
A1: Retraités et actifs : niveau de vie médian, et effet des réformes choisies
A2: Effets cumulés multiplicativement ; hypothèse : l'effet « actifs » s'applique aux personnes en emploi, l'effet « retraités » aux retraités.
A4: Réforme | B4: Inclure | C4: Effet actifs | D4: Effet retraités | E4: Facteur actifs | F4: Facteur retraités
A5: TVA sociale | B5: Oui | C5: ='TVA sociale'!B17 -> 0.0067453564 | D5: ='TVA sociale'!B18 -> -0.0064963504 | E5: =IF(B5="Oui",1+C5,1) -> 1.0067454 | F5: =IF(B5="Oui",1+D5,1) -> 0.99350365
A6: CSG des retraités | B6: Oui | C6: ='CSG retraités'!B19 -> 0.0017876304 | D6: ='CSG retraités'!B20 -> -0.003938625 | E6: =IF(B6="Oui",1+C6,1) -> 1.0017876 | F6: =IF(B6="Oui",1+D6,1) -> 0.99606138
A7: Retraites sans impôts | B7: Oui | C7: ='Sans impôts'!B30 -> -0.040852156 | D7: ='Sans impôts'!B31 -> -0.0773946 | E7: =IF(B7="Oui",1+C7,1) -> 0.95914784 | F7: =IF(B7="Oui",1+D7,1) -> 0.9226054
A8: Gel des hautes pensions | B8: Oui | C8: =Gel!B38 -> 0.0013839503 | D8: =Gel!B39 -> -0.0030492103 | E8: =IF(B8="Oui",1+C8,1) -> 1.001384 | F8: =IF(B8="Oui",1+D8,1) -> 0.99695079
A9: Plafond des pensions | B9: Oui | C9: =Plafond!B17 -> 0 | D9: =Plafond!B18 -> -0.03093482 | E9: =IF(B9="Oui",1+C9,1) -> 1 | F9: =IF(B9="Oui",1+D9,1) -> 0.96906518
A11: Effet cumulé, actifs | B11: =PRODUCT(E5:E9)-1 -> -0.031317439
A12: Effet cumulé, retraités | B12: =PRODUCT(F5:F9)-1 -> -0.11793971
A14: Niveaux de vie médians 2024 (€ 2024 par an)
B15: Avant | C15: Après | D15: Par mois avant | E15: Par mois après
A16: Personnes en emploi | B16: 29860 | C16: =B16*(1+B11) -> 28924.861 | D16: =B16/12 -> 2488.3333 | E16: =C16/12 -> 2410.4051
A17: Retraités | B17: 26830 | C17: =B17*(1+B12) -> 23665.678 | D17: =B17/12 -> 2235.8333 | E17: =C17/12 -> 1972.1398
A18: Retraités / en emploi | B18: =B17/B16 -> 0.89852646 | C18: =C17/C16 -> 0.81817774
A20: Série 1996-2024 (Insee, ERFS, € constants 2024, médianes annuelles)
A21: Année | B21: Ensemble | C21: Retraités | D21: En emploi | E21: Retraités / en emploi
A22: 1996 | B22: 20670 | C22: 21280 | D22: 23080 | E22: =C22/D22 -> 0.9220104
A23: 1997 | B23: 20700 | C23: 21010 | D23: 23300 | E23: =C23/D23 -> 0.90171674
A24: 1998 | B24: 21130 | C24: 21350 | D24: 23800 | E24: =C24/D24 -> 0.89705882
A25: 1999 | B25: 21440 | C25: 21850 | D25: 23930 | E25: =C25/D25 -> 0.91307982
A26: 2000 | B26: 21830 | C26: 22030 | D26: 24290 | E26: =C26/D26 -> 0.9069576
A27: 2001 | B27: 22370 | C27: 22420 | D27: 24920 | E27: =C27/D27 -> 0.89967897
A28: 2002 | B28: 22960 | C28: 22690 | D28: 25620 | E28: =C28/D28 -> 0.88563622
A29: 2003 | B29: 22900 | C29: 22610 | D29: 25500 | E29: =C29/D29 -> 0.88666667
A30: 2004 | B30: 22780 | C30: 22580 | D30: 25430 | E30: =C30/D30 -> 0.88792764
A31: 2005 | B31: 23190 | C31: 22830 | D31: 25810 | E31: =C31/D31 -> 0.88454088
A32: 2006 | B32: 23520 | C32: 23670 | D32: 25980 | E32: =C32/D32 -> 0.91108545
A33: 2007 | B33: 24010 | C33: 23970 | D33: 26680 | E33: =C33/D33 -> 0.89842579
... A50: 2024 | B50: 26740 | C50: 26830 | D50: 29860 | E50: =C50/D50 -> 0.89852646

Sheet Rendement
A1: Pensions reçues pour 100 000 € cotisés, selon la génération
A2: Modèle du site calé sur le TRI du COR (cas type non-cadre, carrière complète), trimestre par trimestre. Valeurs actualisées en plus de l'évolution des salaires.
A4: Génération (année de naissance) | B4: 1960
A5: Taux d'actualisation (en plus des salaires) | B5: 0
A6: Décrochage annuel des pensions par rapport aux salaires | B6: 0.01
A7: Compter aussi les impôts affectés aux retraites | B7: Non
I9: Part des ressources hors cotisations (COR) | L9: Part payée par les retraités
A10: Génération | B10: TRI (COR) | C10: Durée de retraite | D10: Espérance de vie à 60 ans | E10: Durée de carrière | I10: Année | J10: Part | L10: Année | M10: Part
A11: 1940 | B11: 0.01985 | C11: 24.71 | D11: 25.52 | E11: 35.3 | I11: 1987 | J11: 0.121 | L11: 1993 | M11: 0
A12: 1945 | B12: 0.01887 | C12: 25.01 | D12: 25.79 | E12: 36.27 | I12: 2004 | J12: 0.1797 | L12: 2018 | M12: 0.05
A13: 1950 | B13: 0.01768 | C13: 25.51 | D13: 25.99 | E13: 38.02 | I13: 2005 | J13: 0.179
A14: 1955 | B14: 0.01243 | C14: 24.18 | D14: 26.1 | E14: 39.46 | I14: 2006 | J14: 0.1795
A15: 1960 | B15: 0.01212 | C15: 24.23 | D15: 26.67 | E15: 39.33 | I15: 2007 | J15: 0.1771
A16: 1965 | B16: 0.01105 | C16: 23.77 | D16: 27.25 | E16: 39.13 | I16: 2008 | J16: 0.1906
A17: 1970 | B17: 0.00882 | C17: 23.6 | D17: 27.78 | E17: 39.05 | I17: 2009 | J17: 0.1811
A18: 1975 | B18: 0.00776 | C18: 23.81 | D18: 28.3 | E18: 38.34 | I18: 2010 | J18: 0.1775
A19: 1980 | B19: 0.00796 | C19: 24.33 | D19: 28.8 | E19: 38.35 | I19: 2011 | J19: 0.1934
A20: 1985 | B20: 0.00786 | C20: 24.73 | D20: 29.29 | E20: 38.04 | I20: 2012 | J20: 0.1974
A21: 1990 | B21: 0.00795 | C21: 25.16 | D21: 29.74 | E21: 37.85 | I21: 2013 | J21: 0.205
A22: 1995 | B22: 0.00824 | C22: 25.58 | D22: 30.17 | E22: 37.87 | I22: 2014 | J22: 0.208
A23: 2000 | B23: 0.00827 | C23: 26.02 | D23: 30.58 | E23: 37.91 | I23: 2015 | J23: 0.2089
I24: 2016 | J24: 0.2081
I25: 2017 | J25: 0.2052
I26: 2018 | J26: 0.2026
I27: 2019 | J27: 0.2005
I28: 2020 | J28: 0.2158
A29: Calendrier et résultat | I29: 2021 | J29: 0.2079
A30: TRI de la génération (COR) | B30: =INDEX(B$11:B$23,MATCH($B$4,$A$11:$A$23,0)) -> 0.01212 | I30: 2022 | J30: 0.2101
A31: Âge de départ | B31: =60+INDEX(D$11:D$23,MATCH($B$4,$A$11:$A$23,0))-INDEX(C$11:C$23,MATCH($B$4,$A$11:$A$23,0)) -> 62.44 | I31: 2023 | J31: 0.2089
A32: Âge de début de carrière | B32: =B31-INDEX(E$11:E$23,MATCH($B$4,$A$11:$A$23,0)) -> 23.11 | I32: 2024 | J32: 0.2089
A33: Âge de fin de retraite | B33: =B31+INDEX(C$11:C$23,MATCH($B$4,$A$11:$A$23,0)) -> 86.67 | I33: 2025 | J33: 0.2104
A34: Calage : pension / cotisation (au TRI du COR) | B34: =SUM(D60:D259)/SUM(I60:I259) -> 2.6757221
A35: Pensions reçues pour 100 000 € cotisés (valeur actualisée) | B35: =100000*B34*SUM(J60:J259)/SUM(E60:E259) -> 146711.47
A57: Grille trimestrielle (pas de 0,25 an ; une ligne compte si l'âge est dans la période)
A59: Cotisation : âge | B59: Compte | C59: Mult. impôts | D59: Poids au TRI | E59: Poids actualisé | G59: Pension : âge | H59: Compte | I59: Poids au TRI | J59: Poids actualisé | L59: Mult. impôts
A60: =$B$32+0.125+0*0.25 -> 23.235 | B60: =IF(A60<$B$31,1,0) -> 1 | C60: =IF($B$7="Oui",1+((IF(($B$4+A60)<=$I$11,$J$11,IF(($B$4+A60)>=$I$33,$J$33,INDEX($J$11:$J$33,MATCH(($B$4+A60),$I$11:$I$33,1))+(INDEX($J$11:$J$33,MATCH(($B$4+A60),$I$11:$I$33,1)+1)-INDEX($J$11:$J$33,MATCH(($B$4+A60),$I$11:$I$33,1)))*(($B$4+A60)-INDEX($I$11:$I$33,MATCH(($B$4+A60),$I$11:$I$33,1)))/(INDEX($I$11:$I$33,MATCH(($B$4+A60),$I$11:$I$33,1)+1)-INDEX($I$11:$I$33,MATCH(($B$4+A60),$I$11:$I$33,1))))))-(IF(($B$4+A60)<=$L$11,$M$11,IF(($B$4+A60)>=$L$12,$M$12,INDEX($M$11:$M$12,MATCH(($B$4+A60),$L$11:$L$12,1))+(INDEX($M$11:$M$12,MATCH(($B$4+A60),$L$11:$L$12,1)+1)-INDEX($M$11:$M$12,MATCH(($B$4+A60),$L$11:$L$12,1)))*(($B$4+A60)-INDEX($L$11:$L$12,MATCH(($B$4+A60),$L$11:$L$12,1)))/(INDEX($L$11:$L$12,MATCH(($B$4+A60),$L$11:$L$12,1)+1)-INDEX($L$11:$L$12,MATCH(($B$4+A60),$L$11:$L$12,1)))))))/(1-(IF(($B$4+A60)<=$I$11,$J$11,IF(($B$4+A60)>=$I$33,$J$33,INDEX($J$11:$J$33,MATCH(($B$4+A60),$I$11:$I$33,1))+(INDEX($J$11:$J$33,MATCH(($B$4+A60),$I$11:$I$33,1)+1)-INDEX($J$11:$J$33,MATCH(($B$4+A60),$I$11:$I$33,1)))*(($B$4+A60)-INDEX($I$11:$I$33,MATCH(($B$4+A60),$I$11:$I$33,1)))/(INDEX($I$11:$I$33,MATCH(($B$4+A60),$I$11:$I$33,1)+1)-INDEX($I$11:$I$33,MATCH(($B$4+A60),$I$11:$I$33,1))))))),1) -> 1 | D60: =B60*(1+$B$30)^(-A60) -> 0.75584774 | E60: =B60*C60*(1+$B$5)^(-A60) -> 1 | G60: =$B$31+0.125+0*0.25 -> 62.565 | H60: =IF(G60<$B$33,1,0) -> 1 | I60: =H60*(1-$B$6)^(G60-$B$31)*(1+$B$30)^(-G60) -> 0.47001735 | J60: =H60*(1-$B$6)^(G60-$B$31)*L60*(1+$B$5)^(-G60) -> 0.9987445 | L60: =IF($B$7="Oui",1-(IF(($B$4+G60)<=$L$11,$M$11,IF(($B$4+G60)>=$L$12,$M$12,INDEX($M$11:$M$12,MATCH(($B$4+G60),$L$11:$L$12,1))+(INDEX($M$11:$M$12,MATCH(($B$4+G60),$L$11:$L$12,1)+1)-INDEX($M$11:$M$12,MATCH(($B$4+G60),$L$11:$L$12,1)))*(($B$4+G60)-INDEX($L$11:$L$12,MATCH(($B$4+G60),$L$11:$L$12,1)))/(INDEX($L$11:$L$12,MATCH(($B$4+G60),$L$11:$L$12,1)+1)-INDEX($L$11:$L$12,MATCH(($B$4+G60),$L$11:$L$12,1)))))),1) -> 1
A61: =$B$32+0.125+1*0.25 -> 23.485 | B61: =IF(A61<$B$31,1,0) -> 1 | C61: =IF($B$7="Oui",1+((IF(($B$4+A61)<=$I$11,$J$11,IF(($B$4+A61)>=$I$33,$J$33,INDEX($J$11:$J$33,MATCH(($B$4+A61),$I$11:$I$33,1))+(INDEX($J$11:$J$33,MATCH(($B$4+A61),$I$11:$I$33,1)+1)-INDEX($J$11:$J$33,MATCH(($B$4+A61),$I$11:$I$33,1)))*(($B$4+A61)-INDEX($I$11:$I$33,MATCH(($B$4+A61),$I$11:$I$33,1)))/(INDEX($I$11:$I$33,MATCH(($B$4+A61),$I$11:$I$33,1)+1)-INDEX($I$11:$I$33,MATCH(($B$4+A61),$I$11:$I$33,1))))))-(IF(($B$4+A61)<=$L$11,$M$11,IF(($B$4+A61)>=$L$12,$M$12,INDEX($M$11:$M$12,MATCH(($B$4+A61),$L$11:$L$12,1))+(INDEX($M$11:$M$12,MATCH(($B$4+A61),$L$11:$L$12,1)+1)-INDEX($M$11:$M$12,MATCH(($B$4+A61),$L$11:$L$12,1)))*(($B$4+A61)-INDEX($L$11:$L$12,MATCH(($B$4+A61),$L$11:$L$12,1)))/(INDEX($L$11:$L$12,MATCH(($B$4+A61),$L$11:$L$12,1)+1)-INDEX($L$11:$L$12,MATCH(($B$4+A61),$L$11:$L$12,1)))))))/(1-(IF(($B$4+A61)<=$I$11,$J$11,IF(($B$4+A61)>=$I$33,$J$33,INDEX($J$11:$J$33,MATCH(($B$4+A61),$I$11:$I$33,1))+(INDEX($J$11:$J$33,MATCH(($B$4+A61),$I$11:$I$33,1)+1)-INDEX($J$11:$J$33,MATCH(($B$4+A61),$I$11:$I$33,1)))*(($B$4+A61)-INDEX($I$11:$I$33,MATCH(($B$4+A61),$I$11:$I$33,1)))/(INDEX($I$11:$I$33,MATCH(($B$4+A61),$I$11:$I$33,1)+1)-INDEX($I$11:$I$33,MATCH(($B$4+A61),$I$11:$I$33,1))))))),1) -> 1 | D61: =B61*(1+$B$30)^(-A61) -> 0.75357472 | E61: =B61*C61*(1+$B$5)^(-A61) -> 1 | G61: =$B$31+0.125+1*0.25 -> 62.815 | H61: =IF(G61<$B$33,1,0) -> 1 | I61: =H61*(1-$B$6)^(G61-$B$31)*(1+$B$30)^(-G61) -> 0.46742796 | J61: =H61*(1-$B$6)^(G61-$B$31)*L61*(1+$B$5)^(-G61) -> 0.99623822 | L61: =IF($B$7="Oui",1-(IF(($B$4+G61)<=$L$11,$M$11,IF(($B$4+G61)>=$L$12,$M$12,INDEX($M$11:$M$12,MATCH(($B$4+G61),$L$11:$L$12,1))+(INDEX($M$11:$M$12,MATCH(($B$4+G61),$L$11:$L$12,1)+1)-INDEX($M$11:$M$12,MATCH(($B$4+G61),$L$11:$L$12,1)))*(($B$4+G61)-INDEX($L$11:$L$12,MATCH(($B$4+G61),$L$11:$L$12,1)))/(INDEX($L$11:$L$12,MATCH(($B$4+G61),$L$11:$L$12,1)+1)-INDEX($L$11:$L$12,MATCH(($B$4+G61),$L$11:$L$12,1)))))),1) -> 1
A62: =$B$32+0.125+2*0.25 -> 23.735 | B62: =IF(A62<$B$31,1,0) -> 1 | C62: =IF($B$7="Oui",1+((IF(($B$4+A62)<=$I$11,$J$11,IF(($B$4+A62)>=$I$33,$J$33,INDEX($J$11:$J$33,MATCH(($B$4+A62),$I$11:$I$33,1))+(INDEX($J$11:$J$33,MATCH(($B$4+A62),$I$11:$I$33,1)+1)-INDEX($J$11:$J$33,MATCH(($B$4+A62),$I$11:$I$33,1)))*(($B$4+A62)-INDEX($I$11:$I$33,MATCH(($B$4+A62),$I$11:$I$33,1)))/(INDEX($I$11:$I$33,MATCH(($B$4+A62),$I$11:$I$33,1)+1)-INDEX($I$11:$I$33,MATCH(($B$4+A62),$I$11:$I$33,1))))))-(IF(($B$4+A62)<=$L$11,$M$11,IF(($B$4+A62)>=$L$12,$M$12,INDEX($M$11:$M$12,MATCH(($B$4+A62),$L$11:$L$12,1))+(INDEX($M$11:$M$12,MATCH(($B$4+A62),$L$11:$L$12,1)+1)-INDEX($M$11:$M$12,MATCH(($B$4+A62),$L$11:$L$12,1)))*(($B$4+A62)-INDEX($L$11:$L$12,MATCH(($B$4+A62),$L$11:$L$12,1)))/(INDEX($L$11:$L$12,MATCH(($B$4+A62),$L$11:$L$12,1)+1)-INDEX($L$11:$L$12,MATCH(($B$4+A62),$L$11:$L$12,1)))))))/(1-(IF(($B$4+A62)<=$I$11,$J$11,IF(($B$4+A62)>=$I$33,$J$33,INDEX($J$11:$J$33,MATCH(($B$4+A62),$I$11:$I$33,1))+(INDEX($J$11:$J$33,MATCH(($B$4+A62),$I$11:$I$33,1)+1)-INDEX($J$11:$J$33,MATCH(($B$4+A62),$I$11:$I$33,1)))*(($B$4+A62)-INDEX($I$11:$I$33,MATCH(($B$4+A62),$I$11:$I$33,1)))/(INDEX($I$11:$I$33,MATCH(($B$4+A62),$I$11:$I$33,1)+1)-INDEX($I$11:$I$33,MATCH(($B$4+A62),$I$11:$I$33,1))))))),1) -> 1 | D62: =B62*(1+$B$30)^(-A62) -> 0.75130853 | E62: =B62*C62*(1+$B$5)^(-A62) -> 1 | G62: =$B$31+0.125+2*0.25 -> 63.065 | H62: =IF(G62<$B$33,1,0) -> 1 | I62: =H62*(1-$B$6)^(G62-$B$31)*(1+$B$30)^(-G62) -> 0.46485284 | J62: =H62*(1-$B$6)^(G62-$B$31)*L62*(1+$B$5)^(-G62) -> 0.99373823 | L62: =IF($B$7="Oui",1-(IF(($B$4+G62)<=$L$11,$M$11,IF(($B$4+G62)>=$L$12,$M$12,INDEX($M$11:$M$12,MATCH(($B$4+G62),$L$11:$L$12,1))+(INDEX($M$11:$M$12,MATCH(($B$4+G62),$L$11:$L$12,1)+1)-INDEX($M$11:$M$12,MATCH(($B$4+G62),$L$11:$L$12,1)))*(($B$4+G62)-INDEX($L$11:$L$12,MATCH(($B$4+G62),$L$11:$L$12,1)))/(INDEX($L$11:$L$12,MATCH(($B$4+G62),$L$11:$L$12,1)+1)-INDEX($L$11:$L$12,MATCH(($B$4+G62),$L$11:$L$12,1)))))),1) -> 1
A63: =$B$32+0.125+3*0.25 -> 23.985 | B63: =IF(A63<$B$31,1,0) -> 1 | C63: =IF($B$7="Oui",1+((IF(($B$4+A63)<=$I$11,$J$11,IF(($B$4+A63)>=$I$33,$J$33,INDEX($J$11:$J$33,MATCH(($B$4+A63),$I$11:$I$33,1))+(INDEX($J$11:$J$33,MATCH(($B$4+A63),$I$11:$I$33,1)+1)-INDEX($J$11:$J$33,MATCH(($B$4+A63),$I$11:$I$33,1)))*(($B$4+A63)-INDEX($I$11:$I$33,MATCH(($B$4+A63),$I$11:$I$33,1)))/(INDEX($I$11:$I$33,MATCH(($B$4+A63),$I$11:$I$33,1)+1)-INDEX($I$11:$I$33,MATCH(($B$4+A63),$I$11:$I$33,1))))))-(IF(($B$4+A63)<=$L$11,$M$11,IF(($B$4+A63)>=$L$12,$M$12,INDEX($M$11:$M$12,MATCH(($B$4+A63),$L$11:$L$12,1))+(INDEX($M$11:$M$12,MATCH(($B$4+A63),$L$11:$L$12,1)+1)-INDEX($M$11:$M$12,MATCH(($B$4+A63),$L$11:$L$12,1)))*(($B$4+A63)-INDEX($L$11:$L$12,MATCH(($B$4+A63),$L$11:$L$12,1)))/(INDEX($L$11:$L$12,MATCH(($B$4+A63),$L$11:$L$12,1)+1)-INDEX($L$11:$L$12,MATCH(($B$4+A63),$L$11:$L$12,1)))))))/(1-(IF(($B$4+A63)<=$I$11,$J$11,IF(($B$4+A63)>=$I$33,$J$33,INDEX($J$11:$J$33,MATCH(($B$4+A63),$I$11:$I$33,1))+(INDEX($J$11:$J$33,MATCH(($B$4+A63),$I$11:$I$33,1)+1)-INDEX($J$11:$J$33,MATCH(($B$4+A63),$I$11:$I$33,1)))*(($B$4+A63)-INDEX($I$11:$I$33,MATCH(($B$4+A63),$I$11:$I$33,1)))/(INDEX($I$11:$I$33,MATCH(($B$4+A63),$I$11:$I$33,1)+1)-INDEX($I$11:$I$33,MATCH(($B$4+A63),$I$11:$I$33,1))))))),1) -> 1 | D63: =B63*(1+$B$30)^(-A63) -> 0.74904915 | E63: =B63*C63*(1+$B$5)^(-A63) -> 1 | G63: =$B$31+0.125+3*0.25 -> 63.315 | H63: =IF(G63<$B$33,1,0) -> 1 | I63: =H63*(1-$B$6)^(G63-$B$31)*(1+$B$30)^(-G63) -> 0.4622919 | J63: =H63*(1-$B$6)^(G63-$B$31)*L63*(1+$B$5)^(-G63) -> 0.99124451 | L63: =IF($B$7="Oui",1-(IF(($B$4+G63)<=$L$11,$M$11,IF(($B$4+G63)>=$L$12,$M$12,INDEX($M$11:$M$12,MATCH(($B$4+G63),$L$11:$L$12,1))+(INDEX($M$11:$M$12,MATCH(($B$4+G63),$L$11:$L$12,1)+1)-INDEX($M$11:$M$12,MATCH(($B$4+G63),$L$11:$L$12,1)))*(($B$4+G63)-INDEX($L$11:$L$12,MATCH(($B$4+G63),$L$11:$L$12,1)))/(INDEX($L$11:$L$12,MATCH(($B$4+G63),$L$11:$L$12,1)+1)-INDEX($L$11:$L$12,MATCH(($B$4+G63),$L$11:$L$12,1)))))),1) -> 1
A64: =$B$32+0.125+4*0.25 -> 24.235 | B64: =IF(A64<$B$31,1,0) -> 1 | C64: =IF($B$7="Oui",1+((IF(($B$4+A64)<=$I$11,$J$11,IF(($B$4+A64)>=$I$33,$J$33,INDEX($J$11:$J$33,MATCH(($B$4+A64),$I$11:$I$33,1))+(INDEX($J$11:$J$33,MATCH(($B$4+A64),$I$11:$I$33,1)+1)-INDEX($J$11:$J$33,MATCH(($B$4+A64),$I$11:$I$33,1)))*(($B$4+A64)-INDEX($I$11:$I$33,MATCH(($B$4+A64),$I$11:$I$33,1)))/(INDEX($I$11:$I$33,MATCH(($B$4+A64),$I$11:$I$33,1)+1)-INDEX($I$11:$I$33,MATCH(($B$4+A64),$I$11:$I$33,1))))))-(IF(($B$4+A64)<=$L$11,$M$11,IF(($B$4+A64)>=$L$12,$M$12,INDEX($M$11:$M$12,MATCH(($B$4+A64),$L$11:$L$12,1))+(INDEX($M$11:$M$12,MATCH(($B$4+A64),$L$11:$L$12,1)+1)-INDEX($M$11:$M$12,MATCH(($B$4+A64),$L$11:$L$12,1)))*(($B$4+A64)-INDEX($L$11:$L$12,MATCH(($B$4+A64),$L$11:$L$12,1)))/(INDEX($L$11:$L$12,MATCH(($B$4+A64),$L$11:$L$12,1)+1)-INDEX($L$11:$L$12,MATCH(($B$4+A64),$L$11:$L$12,1)))))))/(1-(IF(($B$4+A64)<=$I$11,$J$11,IF(($B$4+A64)>=$I$33,$J$33,INDEX($J$11:$J$33,MATCH(($B$4+A64),$I$11:$I$33,1))+(INDEX($J$11:$J$33,MATCH(($B$4+A64),$I$11:$I$33,1)+1)-INDEX($J$11:$J$33,MATCH(($B$4+A64),$I$11:$I$33,1)))*(($B$4+A64)-INDEX($I$11:$I$33,MATCH(($B$4+A64),$I$11:$I$33,1)))/(INDEX($I$11:$I$33,MATCH(($B$4+A64),$I$11:$I$33,1)+1)-INDEX($I$11:$I$33,MATCH(($B$4+A64),$I$11:$I$33,1))))))),1) -> 1 | D64: =B64*(1+$B$30)^(-A64) -> 0.74679657 | E64: =B64*C64*(1+$B$5)^(-A64) -> 1 | G64: =$B$31+0.125+4*0.25 -> 63.565 | H64: =IF(G64<$B$33,1,0) -> 1 | I64: =H64*(1-$B$6)^(G64-$B$31)*(1+$B$30)^(-G64) -> 0.45974507 | J64: =H64*(1-$B$6)^(G64-$B$31)*L64*(1+$B$5)^(-G64) -> 0.98875705 | L64: =IF($B$7="Oui",1-(IF(($B$4+G64)<=$L$11,$M$11,IF(($B$4+G64)>=$L$12,$M$12,INDEX($M$11:$M$12,MATCH(($B$4+G64),$L$11:$L$12,1))+(INDEX($M$11:$M$12,MATCH(($B$4+G64),$L$11:$L$12,1)+1)-INDEX($M$11:$M$12,MATCH(($B$4+G64),$L$11:$L$12,1)))*(($B$4+G64)-INDEX($L$11:$L$12,MATCH(($B$4+G64),$L$11:$L$12,1)))/(INDEX($L$11:$L$12,MATCH(($B$4+G64),$L$11:$L$12,1)+1)-INDEX($L$11:$L$12,MATCH(($B$4+G64),$L$11:$L$12,1)))))),1) -> 1
A65: =$B$32+0.125+5*0.25 -> 24.485 | B65: =IF(A65<$B$31,1,0) -> 1 | C65: =IF($B$7="Oui",1+((IF(($B$4+A65)<=$I$11,$J$11,IF(($B$4+A65)>=$I$33,$J$33,INDEX($J$11:$J$33,MATCH(($B$4+A65),$I$11:$I$33,1))+(INDEX($J$11:$J$33,MATCH(($B$4+A65),$I$11:$I$33,1)+1)-INDEX($J$11:$J$33,MATCH(($B$4+A65),$I$11:$I$33,1)))*(($B$4+A65)-INDEX($I$11:$I$33,MATCH(($B$4+A65),$I$11:$I$33,1)))/(INDEX($I$11:$I$33,MATCH(($B$4+A65),$I$11:$I$33,1)+1)-INDEX($I$11:$I$33,MATCH(($B$4+A65),$I$11:$I$33,1))))))-(IF(($B$4+A65)<=$L$11,$M$11,IF(($B$4+A65)>=$L$12,$M$12,INDEX($M$11:$M$12,MATCH(($B$4+A65),$L$11:$L$12,1))+(INDEX($M$11:$M$12,MATCH(($B$4+A65),$L$11:$L$12,1)+1)-INDEX($M$11:$M$12,MATCH(($B$4+A65),$L$11:$L$12,1)))*(($B$4+A65)-INDEX($L$11:$L$12,MATCH(($B$4+A65),$L$11:$L$12,1)))/(INDEX($L$11:$L$12,MATCH(($B$4+A65),$L$11:$L$12,1)+1)-INDEX($L$11:$L$12,MATCH(($B$4+A65),$L$11:$L$12,1)))))))/(1-(IF(($B$4+A65)<=$I$11,$J$11,IF(($B$4+A65)>=$I$33,$J$33,INDEX($J$11:$J$33,MATCH(($B$4+A65),$I$11:$I$33,1))+(INDEX($J$11:$J$33,MATCH(($B$4+A65),$I$11:$I$33,1)+1)-INDEX($J$11:$J$33,MATCH(($B$4+A65),$I$11:$I$33,1)))*(($B$4+A65)-INDEX($I$11:$I$33,MATCH(($B$4+A65),$I$11:$I$33,1)))/(INDEX($I$11:$I$33,MATCH(($B$4+A65),$I$11:$I$33,1)+1)-INDEX($I$11:$I$33,MATCH(($B$4+A65),$I$11:$I$33,1))))))),1) -> 1 | D65: =B65*(1+$B$30)^(-A65) -> 0.74455076 | E65: =B65*C65*(1+$B$5)^(-A65) -> 1 | G65: =$B$31+0.125+5*0.25 -> 63.815 | H65: =IF(G65<$B$33,1,0) -> 1 | I65: =H65*(1-$B$6)^(G65-$B$31)*(1+$B$30)^(-G65) -> 0.45721227 | J65: =H65*(1-$B$6)^(G65-$B$31)*L65*(1+$B$5)^(-G65) -> 0.98627584 | L65: =IF($B$7="Oui",1-(IF(($B$4+G65)<=$L$11,$M$11,IF(($B$4+G65)>=$L$12,$M$12,INDEX($M$11:$M$12,MATCH(($B$4+G65),$L$11:$L$12,1))+(INDEX($M$11:$M$12,MATCH(($B$4+G65),$L$11:$L$12,1)+1)-INDEX($M$11:$M$12,MATCH(($B$4+G65),$L$11:$L$12,1)))*(($B$4+G65)-INDEX($L$11:$L$12,MATCH(($B$4+G65),$L$11:$L$12,1)))/(INDEX($L$11:$L$12,MATCH(($B$4+G65),$L$11:$L$12,1)+1)-INDEX($L$11:$L$12,MATCH(($B$4+G65),$L$11:$L$12,1)))))),1) -> 1
A66: =$B$32+0.125+6*0.25 -> 24.735 | B66: =IF(A66<$B$31,1,0) -> 1 | C66: =IF($B$7="Oui",1+((IF(($B$4+A66)<=$I$11,$J$11,IF(($B$4+A66)>=$I$33,$J$33,INDEX($J$11:$J$33,MATCH(($B$4+A66),$I$11:$I$33,1))+(INDEX($J$11:$J$33,MATCH(($B$4+A66),$I$11:$I$33,1)+1)-INDEX($J$11:$J$33,MATCH(($B$4+A66),$I$11:$I$33,1)))*(($B$4+A66)-INDEX($I$11:$I$33,MATCH(($B$4+A66),$I$11:$I$33,1)))/(INDEX($I$11:$I$33,MATCH(($B$4+A66),$I$11:$I$33,1)+1)-INDEX($I$11:$I$33,MATCH(($B$4+A66),$I$11:$I$33,1))))))-(IF(($B$4+A66)<=$L$11,$M$11,IF(($B$4+A66)>=$L$12,$M$12,INDEX($M$11:$M$12,MATCH(($B$4+A66),$L$11:$L$12,1))+(INDEX($M$11:$M$12,MATCH(($B$4+A66),$L$11:$L$12,1)+1)-INDEX($M$11:$M$12,MATCH(($B$4+A66),$L$11:$L$12,1)))*(($B$4+A66)-INDEX($L$11:$L$12,MATCH(($B$4+A66),$L$11:$L$12,1)))/(INDEX($L$11:$L$12,MATCH(($B$4+A66),$L$11:$L$12,1)+1)-INDEX($L$11:$L$12,MATCH(($B$4+A66),$L$11:$L$12,1)))))))/(1-(IF(($B$4+A66)<=$I$11,$J$11,IF(($B$4+A66)>=$I$33,$J$33,INDEX($J$11:$J$33,MATCH(($B$4+A66),$I$11:$I$33,1))+(INDEX($J$11:$J$33,MATCH(($B$4+A66),$I$11:$I$33,1)+1)-INDEX($J$11:$J$33,MATCH(($B$4+A66),$I$11:$I$33,1)))*(($B$4+A66)-INDEX($I$11:$I$33,MATCH(($B$4+A66),$I$11:$I$33,1)))/(INDEX($I$11:$I$33,MATCH(($B$4+A66),$I$11:$I$33,1)+1)-INDEX($I$11:$I$33,MATCH(($B$4+A66),$I$11:$I$33,1))))))),1) -> 1 | D66: =B66*(1+$B$30)^(-A66) -> 0.74231171 | E66: =B66*C66*(1+$B$5)^(-A66) -> 1 | G66: =$B$31+0.125+6*0.25 -> 64.065 | H66: =IF(G66<$B$33,1,0) -> 1 | I66: =H66*(1-$B$6)^(G66-$B$31)*(1+$B$30)^(-G66) -> 0.45469343 | J66: =H66*(1-$B$6)^(G66-$B$31)*L66*(1+$B$5)^(-G66) -> 0.98380084 | L66: =IF($B$7="Oui",1-(IF(($B$4+G66)<=$L$11,$M$11,IF(($B$4+G66)>=$L$12,$M$12,INDEX($M$11:$M$12,MATCH(($B$4+G66),$L$11:$L$12,1))+(INDEX($M$11:$M$12,MATCH(($B$4+G66),$L$11:$L$12,1)+1)-INDEX($M$11:$M$12,MATCH(($B$4+G66),$L$11:$L$12,1)))*(($B$4+G66)-INDEX($L$11:$L$12,MATCH(($B$4+G66),$L$11:$L$12,1)))/(INDEX($L$11:$L$12,MATCH(($B$4+G66),$L$11:$L$12,1)+1)-INDEX($L$11:$L$12,MATCH(($B$4+G66),$L$11:$L$12,1)))))),1) -> 1
A67: =$B$32+0.125+7*0.25 -> 24.985 | B67: =IF(A67<$B$31,1,0) -> 1 | C67: =IF($B$7="Oui",1+((IF(($B$4+A67)<=$I$11,$J$11,IF(($B$4+A67)>=$I$33,$J$33,INDEX($J$11:$J$33,MATCH(($B$4+A67),$I$11:$I$33,1))+(INDEX($J$11:$J$33,MATCH(($B$4+A67),$I$11:$I$33,1)+1)-INDEX($J$11:$J$33,MATCH(($B$4+A67),$I$11:$I$33,1)))*(($B$4+A67)-INDEX($I$11:$I$33,MATCH(($B$4+A67),$I$11:$I$33,1)))/(INDEX($I$11:$I$33,MATCH(($B$4+A67),$I$11:$I$33,1)+1)-INDEX($I$11:$I$33,MATCH(($B$4+A67),$I$11:$I$33,1))))))-(IF(($B$4+A67)<=$L$11,$M$11,IF(($B$4+A67)>=$L$12,$M$12,INDEX($M$11:$M$12,MATCH(($B$4+A67),$L$11:$L$12,1))+(INDEX($M$11:$M$12,MATCH(($B$4+A67),$L$11:$L$12,1)+1)-INDEX($M$11:$M$12,MATCH(($B$4+A67),$L$11:$L$12,1)))*(($B$4+A67)-INDEX($L$11:$L$12,MATCH(($B$4+A67),$L$11:$L$12,1)))/(INDEX($L$11:$L$12,MATCH(($B$4+A67),$L$11:$L$12,1)+1)-INDEX($L$11:$L$12,MATCH(($B$4+A67),$L$11:$L$12,1)))))))/(1-(IF(($B$4+A67)<=$I$11,$J$11,IF(($B$4+A67)>=$I$33,$J$33,INDEX($J$11:$J$33,MATCH(($B$4+A67),$I$11:$I$33,1))+(INDEX($J$11:$J$33,MATCH(($B$4+A67),$I$11:$I$33,1)+1)-INDEX($J$11:$J$33,MATCH(($B$4+A67),$I$11:$I$33,1)))*(($B$4+A67)-INDEX($I$11:$I$33,MATCH(($B$4+A67),$I$11:$I$33,1)))/(INDEX($I$11:$I$33,MATCH(($B$4+A67),$I$11:$I$33,1)+1)-INDEX($I$11:$I$33,MATCH(($B$4+A67),$I$11:$I$33,1))))))),1) -> 1 | D67: =B67*(1+$B$30)^(-A67) -> 0.74007939 | E67: =B67*C67*(1+$B$5)^(-A67) -> 1 | G67: =$B$31+0.125+7*0.25 -> 64.315 | H67: =IF(G67<$B$33,1,0) -> 1 | I67: =H67*(1-$B$6)^(G67-$B$31)*(1+$B$30)^(-G67) -> 0.45218846 | J67: =H67*(1-$B$6)^(G67-$B$31)*L67*(1+$B$5)^(-G67) -> 0.98133207 | L67: =IF($B$7="Oui",1-(IF(($B$4+G67)<=$L$11,$M$11,IF(($B$4+G67)>=$L$12,$M$12,INDEX($M$11:$M$12,MATCH(($B$4+G67),$L$11:$L$12,1))+(INDEX($M$11:$M$12,MATCH(($B$4+G67),$L$11:$L$12,1)+1)-INDEX($M$11:$M$12,MATCH(($B$4+G67),$L$11:$L$12,1)))*(($B$4+G67)-INDEX($L$11:$L$12,MATCH(($B$4+G67),$L$11:$L$12,1)))/(INDEX($L$11:$L$12,MATCH(($B$4+G67),$L$11:$L$12,1)+1)-INDEX($L$11:$L$12,MATCH(($B$4+G67),$L$11:$L$12,1)))))),1) -> 1
A68: =$B$32+0.125+8*0.25 -> 25.235 | B68: =IF(A68<$B$31,1,0) -> 1 | C68: =IF($B$7="Oui",1+((IF(($B$4+A68)<=$I$11,$J$11,IF(($B$4+A68)>=$I$33,$J$33,INDEX($J$11:$J$33,MATCH(($B$4+A68),$I$11:$I$33,1))+(INDEX($J$11:$J$33,MATCH(($B$4+A68),$I$11:$I$33,1)+1)-INDEX($J$11:$J$33,MATCH(($B$4+A68),$I$11:$I$33,1)))*(($B$4+A68)-INDEX($I$11:$I$33,MATCH(($B$4+A68),$I$11:$I$33,1)))/(INDEX($I$11:$I$33,MATCH(($B$4+A68),$I$11:$I$33,1)+1)-INDEX($I$11:$I$33,MATCH(($B$4+A68),$I$11:$I$33,1))))))-(IF(($B$4+A68)<=$L$11,$M$11,IF(($B$4+A68)>=$L$12,$M$12,INDEX($M$11:$M$12,MATCH(($B$4+A68),$L$11:$L$12,1))+(INDEX($M$11:$M$12,MATCH(($B$4+A68),$L$11:$L$12,1)+1)-INDEX($M$11:$M$12,MATCH(($B$4+A68),$L$11:$L$12,1)))*(($B$4+A68)-INDEX($L$11:$L$12,MATCH(($B$4+A68),$L$11:$L$12,1)))/(INDEX($L$11:$L$12,MATCH(($B$4+A68),$L$11:$L$12,1)+1)-INDEX($L$11:$L$12,MATCH(($B$4+A68),$L$11:$L$12,1)))))))/(1-(IF(($B$4+A68)<=$I$11,$J$11,IF(($B$4+A68)>=$I$33,$J$33,INDEX($J$11:$J$33,MATCH(($B$4+A68),$I$11:$I$33,1))+(INDEX($J$11:$J$33,MATCH(($B$4+A68),$I$11:$I$33,1)+1)-INDEX($J$11:$J$33,MATCH(($B$4+A68),$I$11:$I$33,1)))*(($B$4+A68)-INDEX($I$11:$I$33,MATCH(($B$4+A68),$I$11:$I$33,1)))/(INDEX($I$11:$I$33,MATCH(($B$4+A68),$I$11:$I$33,1)+1)-INDEX($I$11:$I$33,MATCH(($B$4+A68),$I$11:$I$33,1))))))),1) -> 1 | D68: =B68*(1+$B$30)^(-A68) -> 0.73785378 | E68: =B68*C68*(1+$B$5)^(-A68) -> 1 | G68: =$B$31+0.125+8*0.25 -> 64.565 | H68: =IF(G68<$B$33,1,0) -> 1 | I68: =H68*(1-$B$6)^(G68-$B$31)*(1+$B$30)^(-G68) -> 0.44969729 | J68: =H68*(1-$B$6)^(G68-$B$31)*L68*(1+$B$5)^(-G68) -> 0.97886948 | L68: =IF($B$7="Oui",1-(IF(($B$4+G68)<=$L$11,$M$11,IF(($B$4+G68)>=$L$12,$M$12,INDEX($M$11:$M$12,MATCH(($B$4+G68),$L$11:$L$12,1))+(INDEX($M$11:$M$12,MATCH(($B$4+G68),$L$11:$L$12,1)+1)-INDEX($M$11:$M$12,MATCH(($B$4+G68),$L$11:$L$12,1)))*(($B$4+G68)-INDEX($L$11:$L$12,MATCH(($B$4+G68),$L$11:$L$12,1)))/(INDEX($L$11:$L$12,MATCH(($B$4+G68),$L$11:$L$12,1)+1)-INDEX($L$11:$L$12,MATCH(($B$4+G68),$L$11:$L$12,1)))))),1) -> 1
A69: =$B$32+0.125+9*0.25 -> 25.485 | B69: =IF(A69<$B$31,1,0) -> 1 | C69: =IF($B$7="Oui",1+((IF(($B$4+A69)<=$I$11,$J$11,IF(($B$4+A69)>=$I$33,$J$33,INDEX($J$11:$J$33,MATCH(($B$4+A69),$I$11:$I$33,1))+(INDEX($J$11:$J$33,MATCH(($B$4+A69),$I$11:$I$33,1)+1)-INDEX($J$11:$J$33,MATCH(($B$4+A69),$I$11:$I$33,1)))*(($B$4+A69)-INDEX($I$11:$I$33,MATCH(($B$4+A69),$I$11:$I$33,1)))/(INDEX($I$11:$I$33,MATCH(($B$4+A69),$I$11:$I$33,1)+1)-INDEX($I$11:$I$33,MATCH(($B$4+A69),$I$11:$I$33,1))))))-(IF(($B$4+A69)<=$L$11,$M$11,IF(($B$4+A69)>=$L$12,$M$12,INDEX($M$11:$M$12,MATCH(($B$4+A69),$L$11:$L$12,1))+(INDEX($M$11:$M$12,MATCH(($B$4+A69),$L$11:$L$12,1)+1)-INDEX($M$11:$M$12,MATCH(($B$4+A69),$L$11:$L$12,1)))*(($B$4+A69)-INDEX($L$11:$L$12,MATCH(($B$4+A69),$L$11:$L$12,1)))/(INDEX($L$11:$L$12,MATCH(($B$4+A69),$L$11:$L$12,1)+1)-INDEX($L$11:$L$12,MATCH(($B$4+A69),$L$11:$L$12,1)))))))/(1-(IF(($B$4+A69)<=$I$11,$J$11,IF(($B$4+A69)>=$I$33,$J$33,INDEX($J$11:$J$33,MATCH(($B$4+A69),$I$11:$I$33,1))+(INDEX($J$11:$J$33,MATCH(($B$4+A69),$I$11:$I$33,1)+1)-INDEX($J$11:$J$33,MATCH(($B$4+A69),$I$11:$I$33,1)))*(($B$4+A69)-INDEX($I$11:$I$33,MATCH(($B$4+A69),$I$11:$I$33,1)))/(INDEX($I$11:$I$33,MATCH(($B$4+A69),$I$11:$I$33,1)+1)-INDEX($I$11:$I$33,MATCH(($B$4+A69),$I$11:$I$33,1))))))),1) -> 1 | D69: =B69*(1+$B$30)^(-A69) -> 0.73563487 | E69: =B69*C69*(1+$B$5)^(-A69) -> 1 | G69: =$B$31+0.125+9*0.25 -> 64.815 | H69: =IF(G69<$B$33,1,0) -> 1 | I69: =H69*(1-$B$6)^(G69-$B$31)*(1+$B$30)^(-G69) -> 0.44721984 | J69: =H69*(1-$B$6)^(G69-$B$31)*L69*(1+$B$5)^(-G69) -> 0.97641308 | L69: =IF($B$7="Oui",1-(IF(($B$4+G69)<=$L$11,$M$11,IF(($B$4+G69)>=$L$12,$M$12,INDEX($M$11:$M$12,MATCH(($B$4+G69),$L$11:$L$12,1))+(INDEX($M$11:$M$12,MATCH(($B$4+G69),$L$11:$L$12,1)+1)-INDEX($M$11:$M$12,MATCH(($B$4+G69),$L$11:$L$12,1)))*(($B$4+G69)-INDEX($L$11:$L$12,MATCH(($B$4+G69),$L$11:$L$12,1)))/(INDEX($L$11:$L$12,MATCH(($B$4+G69),$L$11:$L$12,1)+1)-INDEX($L$11:$L$12,MATCH(($B$4+G69),$L$11:$L$12,1)))))),1) -> 1
A70: =$B$32+0.125+10*0.25 -> 25.735 | B70: =IF(A70<$B$31,1,0) -> 1 | C70: =IF($B$7="Oui",1+((IF(($B$4+A70)<=$I$11,$J$11,IF(($B$4+A70)>=$I$33,$J$33,INDEX($J$11:$J$33,MATCH(($B$4+A70),$I$11:$I$33,1))+(INDEX($J$11:$J$33,MATCH(($B$4+A70),$I$11:$I$33,1)+1)-INDEX($J$11:$J$33,MATCH(($B$4+A70),$I$11:$I$33,1)))*(($B$4+A70)-INDEX($I$11:$I$33,MATCH(($B$4+A70),$I$11:$I$33,1)))/(INDEX($I$11:$I$33,MATCH(($B$4+A70),$I$11:$I$33,1)+1)-INDEX($I$11:$I$33,MATCH(($B$4+A70),$I$11:$I$33,1))))))-(IF(($B$4+A70)<=$L$11,$M$11,IF(($B$4+A70)>=$L$12,$M$12,INDEX($M$11:$M$12,MATCH(($B$4+A70),$L$11:$L$12,1))+(INDEX($M$11:$M$12,MATCH(($B$4+A70),$L$11:$L$12,1)+1)-INDEX($M$11:$M$12,MATCH(($B$4+A70),$L$11:$L$12,1)))*(($B$4+A70)-INDEX($L$11:$L$12,MATCH(($B$4+A70),$L$11:$L$12,1)))/(INDEX($L$11:$L$12,MATCH(($B$4+A70),$L$11:$L$12,1)+1)-INDEX($L$11:$L$12,MATCH(($B$4+A70),$L$11:$L$12,1)))))))/(1-(IF(($B$4+A70)<=$I$11,$J$11,IF(($B$4+A70)>=$I$33,$J$33,INDEX($J$11:$J$33,MATCH(($B$4+A70),$I$11:$I$33,1))+(INDEX($J$11:$J$33,MATCH(($B$4+A70),$I$11:$I$33,1)+1)-INDEX($J$11:$J$33,MATCH(($B$4+A70),$I$11:$I$33,1)))*(($B$4+A70)-INDEX($I$11:$I$33,MATCH(($B$4+A70),$I$11:$I$33,1)))/(INDEX($I$11:$I$33,MATCH(($B$4+A70),$I$11:$I$33,1)+1)-INDEX($I$11:$I$33,MATCH(($B$4+A70),$I$11:$I$33,1))))))),1) -> 1 | D70: =B70*(1+$B$30)^(-A70) -> 0.73342263 | E70: =B70*C70*(1+$B$5)^(-A70) -> 1 | G70: =$B$31+0.125+10*0.25 -> 65.065 | H70: =IF(G70<$B$33,1,0) -> 1 | I70: =H70*(1-$B$6)^(G70-$B$31)*(1+$B$30)^(-G70) -> 0.44475605 | J70: =H70*(1-$B$6)^(G70-$B$31)*L70*(1+$B$5)^(-G70) -> 0.97396284 | L70: =IF($B$7="Oui",1-(IF(($B$4+G70)<=$L$11,$M$11,IF(($B$4+G70)>=$L$12,$M$12,INDEX($M$11:$M$12,MATCH(($B$4+G70),$L$11:$L$12,1))+(INDEX($M$11:$M$12,MATCH(($B$4+G70),$L$11:$L$12,1)+1)-INDEX($M$11:$M$12,MATCH(($B$4+G70),$L$11:$L$12,1)))*(($B$4+G70)-INDEX($L$11:$L$12,MATCH(($B$4+G70),$L$11:$L$12,1)))/(INDEX($L$11:$L$12,MATCH(($B$4+G70),$L$11:$L$12,1)+1)-INDEX($L$11:$L$12,MATCH(($B$4+G70),$L$11:$L$12,1)))))),1) -> 1
A71: =$B$32+0.125+11*0.25 -> 25.985 | B71: =IF(A71<$B$31,1,0) -> 1 | C71: =IF($B$7="Oui",1+((IF(($B$4+A71)<=$I$11,$J$11,IF(($B$4+A71)>=$I$33,$J$33,INDEX($J$11:$J$33,MATCH(($B$4+A71),$I$11:$I$33,1))+(INDEX($J$11:$J$33,MATCH(($B$4+A71),$I$11:$I$33,1)+1)-INDEX($J$11:$J$33,MATCH(($B$4+A71),$I$11:$I$33,1)))*(($B$4+A71)-INDEX($I$11:$I$33,MATCH(($B$4+A71),$I$11:$I$33,1)))/(INDEX($I$11:$I$33,MATCH(($B$4+A71),$I$11:$I$33,1)+1)-INDEX($I$11:$I$33,MATCH(($B$4+A71),$I$11:$I$33,1))))))-(IF(($B$4+A71)<=$L$11,$M$11,IF(($B$4+A71)>=$L$12,$M$12,INDEX($M$11:$M$12,MATCH(($B$4+A71),$L$11:$L$12,1))+(INDEX($M$11:$M$12,MATCH(($B$4+A71),$L$11:$L$12,1)+1)-INDEX($M$11:$M$12,MATCH(($B$4+A71),$L$11:$L$12,1)))*(($B$4+A71)-INDEX($L$11:$L$12,MATCH(($B$4+A71),$L$11:$L$12,1)))/(INDEX($L$11:$L$12,MATCH(($B$4+A71),$L$11:$L$12,1)+1)-INDEX($L$11:$L$12,MATCH(($B$4+A71),$L$11:$L$12,1)))))))/(1-(IF(($B$4+A71)<=$I$11,$J$11,IF(($B$4+A71)>=$I$33,$J$33,INDEX($J$11:$J$33,MATCH(($B$4+A71),$I$11:$I$33,1))+(INDEX($J$11:$J$33,MATCH(($B$4+A71),$I$11:$I$33,1)+1)-INDEX($J$11:$J$33,MATCH(($B$4+A71),$I$11:$I$33,1)))*(($B$4+A71)-INDEX($I$11:$I$33,MATCH(($B$4+A71),$I$11:$I$33,1)))/(INDEX($I$11:$I$33,MATCH(($B$4+A71),$I$11:$I$33,1)+1)-INDEX($I$11:$I$33,MATCH(($B$4+A71),$I$11:$I$33,1))))))),1) -> 1 | D71: =B71*(1+$B$30)^(-A71) -> 0.73121704 | E71: =B71*C71*(1+$B$5)^(-A71) -> 1 | G71: =$B$31+0.125+11*0.25 -> 65.315 | H71: =IF(G71<$B$33,1,0) -> 1 | I71: =H71*(1-$B$6)^(G71-$B$31)*(1+$B$30)^(-G71) -> 0.44230583 | J71: =H71*(1-$B$6)^(G71-$B$31)*L71*(1+$B$5)^(-G71) -> 0.97151874 | L71: =IF($B$7="Oui",1-(IF(($B$4+G71)<=$L$11,$M$11,IF(($B$4+G71)>=$L$12,$M$12,INDEX($M$11:$M$12,MATCH(($B$4+G71),$L$11:$L$12,1))+(INDEX($M$11:$M$12,MATCH(($B$4+G71),$L$11:$L$12,1)+1)-INDEX($M$11:$M$12,MATCH(($B$4+G71),$L$11:$L$12,1)))*(($B$4+G71)-INDEX($L$11:$L$12,MATCH(($B$4+G71),$L$11:$L$12,1)))/(INDEX($L$11:$L$12,MATCH(($B$4+G71),$L$11:$L$12,1)+1)-INDEX($L$11:$L$12,MATCH(($B$4+G71),$L$11:$L$12,1)))))),1) -> 1
A72: =$B$32+0.125+12*0.25 -> 26.235 | B72: =IF(A72<$B$31,1,0) -> 1 | C72: =IF($B$7="Oui",1+((IF(($B$4+A72)<=$I$11,$J$11,IF(($B$4+A72)>=$I$33,$J$33,INDEX($J$11:$J$33,MATCH(($B$4+A72),$I$11:$I$33,1))+(INDEX($J$11:$J$33,MATCH(($B$4+A72),$I$11:$I$33,1)+1)-INDEX($J$11:$J$33,MATCH(($B$4+A72),$I$11:$I$33,1)))*(($B$4+A72)-INDEX($I$11:$I$33,MATCH(($B$4+A72),$I$11:$I$33,1)))/(INDEX($I$11:$I$33,MATCH(($B$4+A72),$I$11:$I$33,1)+1)-INDEX($I$11:$I$33,MATCH(($B$4+A72),$I$11:$I$33,1))))))-(IF(($B$4+A72)<=$L$11,$M$11,IF(($B$4+A72)>=$L$12,$M$12,INDEX($M$11:$M$12,MATCH(($B$4+A72),$L$11:$L$12,1))+(INDEX($M$11:$M$12,MATCH(($B$4+A72),$L$11:$L$12,1)+1)-INDEX($M$11:$M$12,MATCH(($B$4+A72),$L$11:$L$12,1)))*(($B$4+A72)-INDEX($L$11:$L$12,MATCH(($B$4+A72),$L$11:$L$12,1)))/(INDEX($L$11:$L$12,MATCH(($B$4+A72),$L$11:$L$12,1)+1)-INDEX($L$11:$L$12,MATCH(($B$4+A72),$L$11:$L$12,1)))))))/(1-(IF(($B$4+A72)<=$I$11,$J$11,IF(($B$4+A72)>=$I$33,$J$33,INDEX($J$11:$J$33,MATCH(($B$4+A72),$I$11:$I$33,1))+(INDEX($J$11:$J$33,MATCH(($B$4+A72),$I$11:$I$33,1)+1)-INDEX($J$11:$J$33,MATCH(($B$4+A72),$I$11:$I$33,1)))*(($B$4+A72)-INDEX($I$11:$I$33,MATCH(($B$4+A72),$I$11:$I$33,1)))/(INDEX($I$11:$I$33,MATCH(($B$4+A72),$I$11:$I$33,1)+1)-INDEX($I$11:$I$33,MATCH(($B$4+A72),$I$11:$I$33,1))))))),1) -> 1 | D72: =B72*(1+$B$30)^(-A72) -> 0.72901808 | E72: =B72*C72*(1+$B$5)^(-A72) -> 1 | G72: =$B$31+0.125+12*0.25 -> 65.565 | H72: =IF(G72<$B$33,1,0) -> 1 | I72: =H72*(1-$B$6)^(G72-$B$31)*(1+$B$30)^(-G72) -> 0.4398691 | J72: =H72*(1-$B$6)^(G72-$B$31)*L72*(1+$B$5)^(-G72) -> 0.96908079 | L72: =IF($B$7="Oui",1-(IF(($B$4+G72)<=$L$11,$M$11,IF(($B$4+G72)>=$L$12,$M$12,INDEX($M$11:$M$12,MATCH(($B$4+G72),$L$11:$L$12,1))+(INDEX($M$11:$M$12,MATCH(($B$4+G72),$L$11:$L$12,1)+1)-INDEX($M$11:$M$12,MATCH(($B$4+G72),$L$11:$L$12,1)))*(($B$4+G72)-INDEX($L$11:$L$12,MATCH(($B$4+G72),$L$11:$L$12,1)))/(INDEX($L$11:$L$12,MATCH(($B$4+G72),$L$11:$L$12,1)+1)-INDEX($L$11:$L$12,MATCH(($B$4+G72),$L$11:$L$12,1)))))),1) -> 1
A73: =$B$32+0.125+13*0.25 -> 26.485 | B73: =IF(A73<$B$31,1,0) -> 1 | C73: =IF($B$7="Oui",1+((IF(($B$4+A73)<=$I$11,$J$11,IF(($B$4+A73)>=$I$33,$J$33,INDEX($J$11:$J$33,MATCH(($B$4+A73),$I$11:$I$33,1))+(INDEX($J$11:$J$33,MATCH(($B$4+A73),$I$11:$I$33,1)+1)-INDEX($J$11:$J$33,MATCH(($B$4+A73),$I$11:$I$33,1)))*(($B$4+A73)-INDEX($I$11:$I$33,MATCH(($B$4+A73),$I$11:$I$33,1)))/(INDEX($I$11:$I$33,MATCH(($B$4+A73),$I$11:$I$33,1)+1)-INDEX($I$11:$I$33,MATCH(($B$4+A73),$I$11:$I$33,1))))))-(IF(($B$4+A73)<=$L$11,$M$11,IF(($B$4+A73)>=$L$12,$M$12,INDEX($M$11:$M$12,MATCH(($B$4+A73),$L$11:$L$12,1))+(INDEX($M$11:$M$12,MATCH(($B$4+A73),$L$11:$L$12,1)+1)-INDEX($M$11:$M$12,MATCH(($B$4+A73),$L$11:$L$12,1)))*(($B$4+A73)-INDEX($L$11:$L$12,MATCH(($B$4+A73),$L$11:$L$12,1)))/(INDEX($L$11:$L$12,MATCH(($B$4+A73),$L$11:$L$12,1)+1)-INDEX($L$11:$L$12,MATCH(($B$4+A73),$L$11:$L$12,1)))))))/(1-(IF(($B$4+A73)<=$I$11,$J$11,IF(($B$4+A73)>=$I$33,$J$33,INDEX($J$11:$J$33,MATCH(($B$4+A73),$I$11:$I$33,1))+(INDEX($J$11:$J$33,MATCH(($B$4+A73),$I$11:$I$33,1)+1)-INDEX($J$11:$J$33,MATCH(($B$4+A73),$I$11:$I$33,1)))*(($B$4+A73)-INDEX($I$11:$I$33,MATCH(($B$4+A73),$I$11:$I$33,1)))/(INDEX($I$11:$I$33,MATCH(($B$4+A73),$I$11:$I$33,1)+1)-INDEX($I$11:$I$33,MATCH(($B$4+A73),$I$11:$I$33,1))))))),1) -> 1 | D73: =B73*(1+$B$30)^(-A73) -> 0.72682574 | E73: =B73*C73*(1+$B$5)^(-A73) -> 1 | G73: =$B$31+0.125+13*0.25 -> 65.815 | H73: =IF(G73<$B$33,1,0) -> 1 | I73: =H73*(1-$B$6)^(G73-$B$31)*(1+$B$30)^(-G73) -> 0.4374458 | J73: =H73*(1-$B$6)^(G73-$B$31)*L73*(1+$B$5)^(-G73) -> 0.96664895 | L73: =IF($B$7="Oui",1-(IF(($B$4+G73)<=$L$11,$M$11,IF(($B$4+G73)>=$L$12,$M$12,INDEX($M$11:$M$12,MATCH(($B$4+G73),$L$11:$L$12,1))+(INDEX($M$11:$M$12,MATCH(($B$4+G73),$L$11:$L$12,1)+1)-INDEX($M$11:$M$12,MATCH(($B$4+G73),$L$11:$L$12,1)))*(($B$4+G73)-INDEX($L$11:$L$12,MATCH(($B$4+G73),$L$11:$L$12,1)))/(INDEX($L$11:$L$12,MATCH(($B$4+G73),$L$11:$L$12,1)+1)-INDEX($L$11:$L$12,MATCH(($B$4+G73),$L$11:$L$12,1)))))),1) -> 1
A74: =$B$32+0.125+14*0.25 -> 26.735 | B74: =IF(A74<$B$31,1,0) -> 1 | C74: =IF($B$7="Oui",1+((IF(($B$4+A74)<=$I$11,$J$11,IF(($B$4+A74)>=$I$33,$J$33,INDEX($J$11:$J$33,MATCH(($B$4+A74),$I$11:$I$33,1))+(INDEX($J$11:$J$33,MATCH(($B$4+A74),$I$11:$I$33,1)+1)-INDEX($J$11:$J$33,MATCH(($B$4+A74),$I$11:$I$33,1)))*(($B$4+A74)-INDEX($I$11:$I$33,MATCH(($B$4+A74),$I$11:$I$33,1)))/(INDEX($I$11:$I$33,MATCH(($B$4+A74),$I$11:$I$33,1)+1)-INDEX($I$11:$I$33,MATCH(($B$4+A74),$I$11:$I$33,1))))))-(IF(($B$4+A74)<=$L$11,$M$11,IF(($B$4+A74)>=$L$12,$M$12,INDEX($M$11:$M$12,MATCH(($B$4+A74),$L$11:$L$12,1))+(INDEX($M$11:$M$12,MATCH(($B$4+A74),$L$11:$L$12,1)+1)-INDEX($M$11:$M$12,MATCH(($B$4+A74),$L$11:$L$12,1)))*(($B$4+A74)-INDEX($L$11:$L$12,MATCH(($B$4+A74),$L$11:$L$12,1)))/(INDEX($L$11:$L$12,MATCH(($B$4+A74),$L$11:$L$12,1)+1)-INDEX($L$11:$L$12,MATCH(($B$4+A74),$L$11:$L$12,1)))))))/(1-(IF(($B$4+A74)<=$I$11,$J$11,IF(($B$4+A74)>=$I$33,$J$33,INDEX($J$11:$J$33,MATCH(($B$4+A74),$I$11:$I$33,1))+(INDEX($J$11:$J$33,MATCH(($B$4+A74),$I$11:$I$33,1)+1)-INDEX($J$11:$J$33,MATCH(($B$4+A74),$I$11:$I$33,1)))*(($B$4+A74)-INDEX($I$11:$I$33,MATCH(($B$4+A74),$I$11:$I$33,1)))/(INDEX($I$11:$I$33,MATCH(($B$4+A74),$I$11:$I$33,1)+1)-INDEX($I$11:$I$33,MATCH(($B$4+A74),$I$11:$I$33,1))))))),1) -> 1 | D74: =B74*(1+$B$30)^(-A74) -> 0.72463999 | E74: =B74*C74*(1+$B$5)^(-A74) -> 1 | G74: =$B$31+0.125+14*0.25 -> 66.065 | H74: =IF(G74<$B$33,1,0) -> 1 | I74: =H74*(1-$B$6)^(G74-$B$31)*(1+$B$30)^(-G74) -> 0.43503585 | J74: =H74*(1-$B$6)^(G74-$B$31)*L74*(1+$B$5)^(-G74) -> 0.96422321 | L74: =IF($B$7="Oui",1-(IF(($B$4+G74)<=$L$11,$M$11,IF(($B$4+G74)>=$L$12,$M$12,INDEX($M$11:$M$12,MATCH(($B$4+G74),$L$11:$L$12,1))+(INDEX($M$11:$M$12,MATCH(($B$4+G74),$L$11:$L$12,1)+1)-INDEX($M$11:$M$12,MATCH(($B$4+G74),$L$11:$L$12,1)))*(($B$4+G74)-INDEX($L$11:$L$12,MATCH(($B$4+G74),$L$11:$L$12,1)))/(INDEX($L$11:$L$12,MATCH(($B$4+G74),$L$11:$L$12,1)+1)-INDEX($L$11:$L$12,MATCH(($B$4+G74),$L$11:$L$12,1)))))),1) -> 1
A75: =$B$32+0.125+15*0.25 -> 26.985 | B75: =IF(A75<$B$31,1,0) -> 1 | C75: =IF($B$7="Oui",1+((IF(($B$4+A75)<=$I$11,$J$11,IF(($B$4+A75)>=$I$33,$J$33,INDEX($J$11:$J$33,MATCH(($B$4+A75),$I$11:$I$33,1))+(INDEX($J$11:$J$33,MATCH(($B$4+A75),$I$11:$I$33,1)+1)-INDEX($J$11:$J$33,MATCH(($B$4+A75),$I$11:$I$33,1)))*(($B$4+A75)-INDEX($I$11:$I$33,MATCH(($B$4+A75),$I$11:$I$33,1)))/(INDEX($I$11:$I$33,MATCH(($B$4+A75),$I$11:$I$33,1)+1)-INDEX($I$11:$I$33,MATCH(($B$4+A75),$I$11:$I$33,1))))))-(IF(($B$4+A75)<=$L$11,$M$11,IF(($B$4+A75)>=$L$12,$M$12,INDEX($M$11:$M$12,MATCH(($B$4+A75),$L$11:$L$12,1))+(INDEX($M$11:$M$12,MATCH(($B$4+A75),$L$11:$L$12,1)+1)-INDEX($M$11:$M$12,MATCH(($B$4+A75),$L$11:$L$12,1)))*(($B$4+A75)-INDEX($L$11:$L$12,MATCH(($B$4+A75),$L$11:$L$12,1)))/(INDEX($L$11:$L$12,MATCH(($B$4+A75),$L$11:$L$12,1)+1)-INDEX($L$11:$L$12,MATCH(($B$4+A75),$L$11:$L$12,1)))))))/(1-(IF(($B$4+A75)<=$I$11,$J$11,IF(($B$4+A75)>=$I$33,$J$33,INDEX($J$11:$J$33,MATCH(($B$4+A75),$I$11:$I$33,1))+(INDEX($J$11:$J$33,MATCH(($B$4+A75),$I$11:$I$33,1)+1)-INDEX($J$11:$J$33,MATCH(($B$4+A75),$I$11:$I$33,1)))*(($B$4+A75)-INDEX($I$11:$I$33,MATCH(($B$4+A75),$I$11:$I$33,1)))/(INDEX($I$11:$I$33,MATCH(($B$4+A75),$I$11:$I$33,1)+1)-INDEX($I$11:$I$33,MATCH(($B$4+A75),$I$11:$I$33,1))))))),1) -> 1 | D75: =B75*(1+$B$30)^(-A75) -> 0.72246081 | E75: =B75*C75*(1+$B$5)^(-A75) -> 1 | G75: =$B$31+0.125+15*0.25 -> 66.315 | H75: =IF(G75<$B$33,1,0) -> 1 | I75: =H75*(1-$B$6)^(G75-$B$31)*(1+$B$30)^(-G75) -> 0.43263918 | J75: =H75*(1-$B$6)^(G75-$B$31)*L75*(1+$B$5)^(-G75) -> 0.96180356 | L75: =IF($B$7="Oui",1-(IF(($B$4+G75)<=$L$11,$M$11,IF(($B$4+G75)>=$L$12,$M$12,INDEX($M$11:$M$12,MATCH(($B$4+G75),$L$11:$L$12,1))+(INDEX($M$11:$M$12,MATCH(($B$4+G75),$L$11:$L$12,1)+1)-INDEX($M$11:$M$12,MATCH(($B$4+G75),$L$11:$L$12,1)))*(($B$4+G75)-INDEX($L$11:$L$12,MATCH(($B$4+G75),$L$11:$L$12,1)))/(INDEX($L$11:$L$12,MATCH(($B$4+G75),$L$11:$L$12,1)+1)-INDEX($L$11:$L$12,MATCH(($B$4+G75),$L$11:$L$12,1)))))),1) -> 1
A76: =$B$32+0.125+16*0.25 -> 27.235 | B76: =IF(A76<$B$31,1,0) -> 1 | C76: =IF($B$7="Oui",1+((IF(($B$4+A76)<=$I$11,$J$11,IF(($B$4+A76)>=$I$33,$J$33,INDEX($J$11:$J$33,MATCH(($B$4+A76),$I$11:$I$33,1))+(INDEX($J$11:$J$33,MATCH(($B$4+A76),$I$11:$I$33,1)+1)-INDEX($J$11:$J$33,MATCH(($B$4+A76),$I$11:$I$33,1)))*(($B$4+A76)-INDEX($I$11:$I$33,MATCH(($B$4+A76),$I$11:$I$33,1)))/(INDEX($I$11:$I$33,MATCH(($B$4+A76),$I$11:$I$33,1)+1)-INDEX($I$11:$I$33,MATCH(($B$4+A76),$I$11:$I$33,1))))))-(IF(($B$4+A76)<=$L$11,$M$11,IF(($B$4+A76)>=$L$12,$M$12,INDEX($M$11:$M$12,MATCH(($B$4+A76),$L$11:$L$12,1))+(INDEX($M$11:$M$12,MATCH(($B$4+A76),$L$11:$L$12,1)+1)-INDEX($M$11:$M$12,MATCH(($B$4+A76),$L$11:$L$12,1)))*(($B$4+A76)-INDEX($L$11:$L$12,MATCH(($B$4+A76),$L$11:$L$12,1)))/(INDEX($L$11:$L$12,MATCH(($B$4+A76),$L$11:$L$12,1)+1)-INDEX($L$11:$L$12,MATCH(($B$4+A76),$L$11:$L$12,1)))))))/(1-(IF(($B$4+A76)<=$I$11,$J$11,IF(($B$4+A76)>=$I$33,$J$33,INDEX($J$11:$J$33,MATCH(($B$4+A76),$I$11:$I$33,1))+(INDEX($J$11:$J$33,MATCH(($B$4+A76),$I$11:$I$33,1)+1)-INDEX($J$11:$J$33,MATCH(($B$4+A76),$I$11:$I$33,1)))*(($B$4+A76)-INDEX($I$11:$I$33,MATCH(($B$4+A76),$I$11:$I$33,1)))/(INDEX($I$11:$I$33,MATCH(($B$4+A76),$I$11:$I$33,1)+1)-INDEX($I$11:$I$33,MATCH(($B$4+A76),$I$11:$I$33,1))))))),1) -> 1 | D76: =B76*(1+$B$30)^(-A76) -> 0.72028819 | E76: =B76*C76*(1+$B$5)^(-A76) -> 1 | G76: =$B$31+0.125+16*0.25 -> 66.565 | H76: =IF(G76<$B$33,1,0) -> 1 | I76: =H76*(1-$B$6)^(G76-$B$31)*(1+$B$30)^(-G76) -> 0.43025571 | J76: =H76*(1-$B$6)^(G76-$B$31)*L76*(1+$B$5)^(-G76) -> 0.95938998 | L76: =IF($B$7="Oui",1-(IF(($B$4+G76)<=$L$11,$M$11,IF(($B$4+G76)>=$L$12,$M$12,INDEX($M$11:$M$12,MATCH(($B$4+G76),$L$11:$L$12,1))+(INDEX($M$11:$M$12,MATCH(($B$4+G76),$L$11:$L$12,1)+1)-INDEX($M$11:$M$12,MATCH(($B$4+G76),$L$11:$L$12,1)))*(($B$4+G76)-INDEX($L$11:$L$12,MATCH(($B$4+G76),$L$11:$L$12,1)))/(INDEX($L$11:$L$12,MATCH(($B$4+G76),$L$11:$L$12,1)+1)-INDEX($L$11:$L$12,MATCH(($B$4+G76),$L$11:$L$12,1)))))),1) -> 1
A77: =$B$32+0.125+17*0.25 -> 27.485 | B77: =IF(A77<$B$31,1,0) -> 1 | C77: =IF($B$7="Oui",1+((IF(($B$4+A77)<=$I$11,$J$11,IF(($B$4+A77)>=$I$33,$J$33,INDEX($J$11:$J$33,MATCH(($B$4+A77),$I$11:$I$33,1))+(INDEX($J$11:$J$33,MATCH(($B$4+A77),$I$11:$I$33,1)+1)-INDEX($J$11:$J$33,MATCH(($B$4+A77),$I$11:$I$33,1)))*(($B$4+A77)-INDEX($I$11:$I$33,MATCH(($B$4+A77),$I$11:$I$33,1)))/(INDEX($I$11:$I$33,MATCH(($B$4+A77),$I$11:$I$33,1)+1)-INDEX($I$11:$I$33,MATCH(($B$4+A77),$I$11:$I$33,1))))))-(IF(($B$4+A77)<=$L$11,$M$11,IF(($B$4+A77)>=$L$12,$M$12,INDEX($M$11:$M$12,MATCH(($B$4+A77),$L$11:$L$12,1))+(INDEX($M$11:$M$12,MATCH(($B$4+A77),$L$11:$L$12,1)+1)-INDEX($M$11:$M$12,MATCH(($B$4+A77),$L$11:$L$12,1)))*(($B$4+A77)-INDEX($L$11:$L$12,MATCH(($B$4+A77),$L$11:$L$12,1)))/(INDEX($L$11:$L$12,MATCH(($B$4+A77),$L$11:$L$12,1)+1)-INDEX($L$11:$L$12,MATCH(($B$4+A77),$L$11:$L$12,1)))))))/(1-(IF(($B$4+A77)<=$I$11,$J$11,IF(($B$4+A77)>=$I$33,$J$33,INDEX($J$11:$J$33,MATCH(($B$4+A77),$I$11:$I$33,1))+(INDEX($J$11:$J$33,MATCH(($B$4+A77),$I$11:$I$33,1)+1)-INDEX($J$11:$J$33,MATCH(($B$4+A77),$I$11:$I$33,1)))*(($B$4+A77)-INDEX($I$11:$I$33,MATCH(($B$4+A77),$I$11:$I$33,1)))/(INDEX($I$11:$I$33,MATCH(($B$4+A77),$I$11:$I$33,1)+1)-INDEX($I$11:$I$33,MATCH(($B$4+A77),$I$11:$I$33,1))))))),1) -> 1 | D77: =B77*(1+$B$30)^(-A77) -> 0.7181221 | E77: =B77*C77*(1+$B$5)^(-A77) -> 1 | G77: =$B$31+0.125+17*0.25 -> 66.815 | H77: =IF(G77<$B$33,1,0) -> 1 | I77: =H77*(1-$B$6)^(G77-$B$31)*(1+$B$30)^(-G77) -> 0.42788537 | J77: =H77*(1-$B$6)^(G77-$B$31)*L77*(1+$B$5)^(-G77) -> 0.95698246 | L77: =IF($B$7="Oui",1-(IF(($B$4+G77)<=$L$11,$M$11,IF(($B$4+G77)>=$L$12,$M$12,INDEX($M$11:$M$12,MATCH(($B$4+G77),$L$11:$L$12,1))+(INDEX($M$11:$M$12,MATCH(($B$4+G77),$L$11:$L$12,1)+1)-INDEX($M$11:$M$12,MATCH(($B$4+G77),$L$11:$L$12,1)))*(($B$4+G77)-INDEX($L$11:$L$12,MATCH(($B$4+G77),$L$11:$L$12,1)))/(INDEX($L$11:$L$12,MATCH(($B$4+G77),$L$11:$L$12,1)+1)-INDEX($L$11:$L$12,MATCH(($B$4+G77),$L$11:$L$12,1)))))),1) -> 1
A78: =$B$32+0.125+18*0.25 -> 27.735 | B78: =IF(A78<$B$31,1,0) -> 1 | C78: =IF($B$7="Oui",1+((IF(($B$4+A78)<=$I$11,$J$11,IF(($B$4+A78)>=$I$33,$J$33,INDEX($J$11:$J$33,MATCH(($B$4+A78),$I$11:$I$33,1))+(INDEX($J$11:$J$33,MATCH(($B$4+A78),$I$11:$I$33,1)+1)-INDEX($J$11:$J$33,MATCH(($B$4+A78),$I$11:$I$33,1)))*(($B$4+A78)-INDEX($I$11:$I$33,MATCH(($B$4+A78),$I$11:$I$33,1)))/(INDEX($I$11:$I$33,MATCH(($B$4+A78),$I$11:$I$33,1)+1)-INDEX($I$11:$I$33,MATCH(($B$4+A78),$I$11:$I$33,1))))))-(IF(($B$4+A78)<=$L$11,$M$11,IF(($B$4+A78)>=$L$12,$M$12,INDEX($M$11:$M$12,MATCH(($B$4+A78),$L$11:$L$12,1))+(INDEX($M$11:$M$12,MATCH(($B$4+A78),$L$11:$L$12,1)+1)-INDEX($M$11:$M$12,MATCH(($B$4+A78),$L$11:$L$12,1)))*(($B$4+A78)-INDEX($L$11:$L$12,MATCH(($B$4+A78),$L$11:$L$12,1)))/(INDEX($L$11:$L$12,MATCH(($B$4+A78),$L$11:$L$12,1)+1)-INDEX($L$11:$L$12,MATCH(($B$4+A78),$L$11:$L$12,1)))))))/(1-(IF(($B$4+A78)<=$I$11,$J$11,IF(($B$4+A78)>=$I$33,$J$33,INDEX($J$11:$J$33,MATCH(($B$4+A78),$I$11:$I$33,1))+(INDEX($J$11:$J$33,MATCH(($B$4+A78),$I$11:$I$33,1)+1)-INDEX($J$11:$J$33,MATCH(($B$4+A78),$I$11:$I$33,1)))*(($B$4+A78)-INDEX($I$11:$I$33,MATCH(($B$4+A78),$I$11:$I$33,1)))/(INDEX($I$11:$I$33,MATCH(($B$4+A78),$I$11:$I$33,1)+1)-INDEX($I$11:$I$33,MATCH(($B$4+A78),$I$11:$I$33,1))))))),1) -> 1 | D78: =B78*(1+$B$30)^(-A78) -> 0.71596252 | E78: =B78*C78*(1+$B$5)^(-A78) -> 1 | G78: =$B$31+0.125+18*0.25 -> 67.065 | H78: =IF(G78<$B$33,1,0) -> 1 | I78: =H78*(1-$B$6)^(G78-$B$31)*(1+$B$30)^(-G78) -> 0.42552809 | J78: =H78*(1-$B$6)^(G78-$B$31)*L78*(1+$B$5)^(-G78) -> 0.95458098 | L78: =IF($B$7="Oui",1-(IF(($B$4+G78)<=$L$11,$M$11,IF(($B$4+G78)>=$L$12,$M$12,INDEX($M$11:$M$12,MATCH(($B$4+G78),$L$11:$L$12,1))+(INDEX($M$11:$M$12,MATCH(($B$4+G78),$L$11:$L$12,1)+1)-INDEX($M$11:$M$12,MATCH(($B$4+G78),$L$11:$L$12,1)))*(($B$4+G78)-INDEX($L$11:$L$12,MATCH(($B$4+G78),$L$11:$L$12,1)))/(INDEX($L$11:$L$12,MATCH(($B$4+G78),$L$11:$L$12,1)+1)-INDEX($L$11:$L$12,MATCH(($B$4+G78),$L$11:$L$12,1)))))),1) -> 1
A79: =$B$32+0.125+19*0.25 -> 27.985 | B79: =IF(A79<$B$31,1,0) -> 1 | C79: =IF($B$7="Oui",1+((IF(($B$4+A79)<=$I$11,$J$11,IF(($B$4+A79)>=$I$33,$J$33,INDEX($J$11:$J$33,MATCH(($B$4+A79),$I$11:$I$33,1))+(INDEX($J$11:$J$33,MATCH(($B$4+A79),$I$11:$I$33,1)+1)-INDEX($J$11:$J$33,MATCH(($B$4+A79),$I$11:$I$33,1)))*(($B$4+A79)-INDEX($I$11:$I$33,MATCH(($B$4+A79),$I$11:$I$33,1)))/(INDEX($I$11:$I$33,MATCH(($B$4+A79),$I$11:$I$33,1)+1)-INDEX($I$11:$I$33,MATCH(($B$4+A79),$I$11:$I$33,1))))))-(IF(($B$4+A79)<=$L$11,$M$11,IF(($B$4+A79)>=$L$12,$M$12,INDEX($M$11:$M$12,MATCH(($B$4+A79),$L$11:$L$12,1))+(INDEX($M$11:$M$12,MATCH(($B$4+A79),$L$11:$L$12,1)+1)-INDEX($M$11:$M$12,MATCH(($B$4+A79),$L$11:$L$12,1)))*(($B$4+A79)-INDEX($L$11:$L$12,MATCH(($B$4+A79),$L$11:$L$12,1)))/(INDEX($L$11:$L$12,MATCH(($B$4+A79),$L$11:$L$12,1)+1)-INDEX($L$11:$L$12,MATCH(($B$4+A79),$L$11:$L$12,1)))))))/(1-(IF(($B$4+A79)<=$I$11,$J$11,IF(($B$4+A79)>=$I$33,$J$33,INDEX($J$11:$J$33,MATCH(($B$4+A79),$I$11:$I$33,1))+(INDEX($J$11:$J$33,MATCH(($B$4+A79),$I$11:$I$33,1)+1)-INDEX($J$11:$J$33,MATCH(($B$4+A79),$I$11:$I$33,1)))*(($B$4+A79)-INDEX($I$11:$I$33,MATCH(($B$4+A79),$I$11:$I$33,1)))/(INDEX($I$11:$I$33,MATCH(($B$4+A79),$I$11:$I$33,1)+1)-INDEX($I$11:$I$33,MATCH(($B$4+A79),$I$11:$I$33,1))))))),1) -> 1 | D79: =B79*(1+$B$30)^(-A79) -> 0.71380944 | E79: =B79*C79*(1+$B$5)^(-A79) -> 1 | G79: =$B$31+0.125+19*0.25 -> 67.315 | H79: =IF(G79<$B$33,1,0) -> 1 | I79: =H79*(1-$B$6)^(G79-$B$31)*(1+$B$30)^(-G79) -> 0.4231838 | J79: =H79*(1-$B$6)^(G79-$B$31)*L79*(1+$B$5)^(-G79) -> 0.95218552 | L79: =IF($B$7="Oui",1-(IF(($B$4+G79)<=$L$11,$M$11,IF(($B$4+G79)>=$L$12,$M$12,INDEX($M$11:$M$12,MATCH(($B$4+G79),$L$11:$L$12,1))+(INDEX($M$11:$M$12,MATCH(($B$4+G79),$L$11:$L$12,1)+1)-INDEX($M$11:$M$12,MATCH(($B$4+G79),$L$11:$L$12,1)))*(($B$4+G79)-INDEX($L$11:$L$12,MATCH(($B$4+G79),$L$11:$L$12,1)))/(INDEX($L$11:$L$12,MATCH(($B$4+G79),$L$11:$L$12,1)+1)-INDEX($L$11:$L$12,MATCH(($B$4+G79),$L$11:$L$12,1)))))),1) -> 1
A80: =$B$32+0.125+20*0.25 -> 28.235 | B80: =IF(A80<$B$31,1,0) -> 1 | C80: =IF($B$7="Oui",1+((IF(($B$4+A80)<=$I$11,$J$11,IF(($B$4+A80)>=$I$33,$J$33,INDEX($J$11:$J$33,MATCH(($B$4+A80),$I$11:$I$33,1))+(INDEX($J$11:$J$33,MATCH(($B$4+A80),$I$11:$I$33,1)+1)-INDEX($J$11:$J$33,MATCH(($B$4+A80),$I$11:$I$33,1)))*(($B$4+A80)-INDEX($I$11:$I$33,MATCH(($B$4+A80),$I$11:$I$33,1)))/(INDEX($I$11:$I$33,MATCH(($B$4+A80),$I$11:$I$33,1)+1)-INDEX($I$11:$I$33,MATCH(($B$4+A80),$I$11:$I$33,1))))))-(IF(($B$4+A80)<=$L$11,$M$11,IF(($B$4+A80)>=$L$12,$M$12,INDEX($M$11:$M$12,MATCH(($B$4+A80),$L$11:$L$12,1))+(INDEX($M$11:$M$12,MATCH(($B$4+A80),$L$11:$L$12,1)+1)-INDEX($M$11:$M$12,MATCH(($B$4+A80),$L$11:$L$12,1)))*(($B$4+A80)-INDEX($L$11:$L$12,MATCH(($B$4+A80),$L$11:$L$12,1)))/(INDEX($L$11:$L$12,MATCH(($B$4+A80),$L$11:$L$12,1)+1)-INDEX($L$11:$L$12,MATCH(($B$4+A80),$L$11:$L$12,1)))))))/(1-(IF(($B$4+A80)<=$I$11,$J$11,IF(($B$4+A80)>=$I$33,$J$33,INDEX($J$11:$J$33,MATCH(($B$4+A80),$I$11:$I$33,1))+(INDEX($J$11:$J$33,MATCH(($B$4+A80),$I$11:$I$33,1)+1)-INDEX($J$11:$J$33,MATCH(($B$4+A80),$I$11:$I$33,1)))*(($B$4+A80)-INDEX($I$11:$I$33,MATCH(($B$4+A80),$I$11:$I$33,1)))/(INDEX($I$11:$I$33,MATCH(($B$4+A80),$I$11:$I$33,1)+1)-INDEX($I$11:$I$33,MATCH(($B$4+A80),$I$11:$I$33,1))))))),1) -> 1 | D80: =B80*(1+$B$30)^(-A80) -> 0.71166284 | E80: =B80*C80*(1+$B$5)^(-A80) -> 1 | G80: =$B$31+0.125+20*0.25 -> 67.565 | H80: =IF(G80<$B$33,1,0) -> 1 | I80: =H80*(1-$B$6)^(G80-$B$31)*(1+$B$30)^(-G80) -> 0.42085242 | J80: =H80*(1-$B$6)^(G80-$B$31)*L80*(1+$B$5)^(-G80) -> 0.94979608 | L80: =IF($B$7="Oui",1-(IF(($B$4+G80)<=$L$11,$M$11,IF(($B$4+G80)>=$L$12,$M$12,INDEX($M$11:$M$12,MATCH(($B$4+G80),$L$11:$L$12,1))+(INDEX($M$11:$M$12,MATCH(($B$4+G80),$L$11:$L$12,1)+1)-INDEX($M$11:$M$12,MATCH(($B$4+G80),$L$11:$L$12,1)))*(($B$4+G80)-INDEX($L$11:$L$12,MATCH(($B$4+G80),$L$11:$L$12,1)))/(INDEX($L$11:$L$12,MATCH(($B$4+G80),$L$11:$L$12,1)+1)-INDEX($L$11:$L$12,MATCH(($B$4+G80),$L$11:$L$12,1)))))),1) -> 1
A81: =$B$32+0.125+21*0.25 -> 28.485 | B81: =IF(A81<$B$31,1,0) -> 1 | C81: =IF($B$7="Oui",1+((IF(($B$4+A81)<=$I$11,$J$11,IF(($B$4+A81)>=$I$33,$J$33,INDEX($J$11:$J$33,MATCH(($B$4+A81),$I$11:$I$33,1))+(INDEX($J$11:$J$33,MATCH(($B$4+A81),$I$11:$I$33,1)+1)-INDEX($J$11:$J$33,MATCH(($B$4+A81),$I$11:$I$33,1)))*(($B$4+A81)-INDEX($I$11:$I$33,MATCH(($B$4+A81),$I$11:$I$33,1)))/(INDEX($I$11:$I$33,MATCH(($B$4+A81),$I$11:$I$33,1)+1)-INDEX($I$11:$I$33,MATCH(($B$4+A81),$I$11:$I$33,1))))))-(IF(($B$4+A81)<=$L$11,$M$11,IF(($B$4+A81)>=$L$12,$M$12,INDEX($M$11:$M$12,MATCH(($B$4+A81),$L$11:$L$12,1))+(INDEX($M$11:$M$12,MATCH(($B$4+A81),$L$11:$L$12,1)+1)-INDEX($M$11:$M$12,MATCH(($B$4+A81),$L$11:$L$12,1)))*(($B$4+A81)-INDEX($L$11:$L$12,MATCH(($B$4+A81),$L$11:$L$12,1)))/(INDEX($L$11:$L$12,MATCH(($B$4+A81),$L$11:$L$12,1)+1)-INDEX($L$11:$L$12,MATCH(($B$4+A81),$L$11:$L$12,1)))))))/(1-(IF(($B$4+A81)<=$I$11,$J$11,IF(($B$4+A81)>=$I$33,$J$33,INDEX($J$11:$J$33,MATCH(($B$4+A81),$I$11:$I$33,1))+(INDEX($J$11:$J$33,MATCH(($B$4+A81),$I$11:$I$33,1)+1)-INDEX($J$11:$J$33,MATCH(($B$4+A81),$I$11:$I$33,1)))*(($B$4+A81)-INDEX($I$11:$I$33,MATCH(($B$4+A81),$I$11:$I$33,1)))/(INDEX($I$11:$I$33,MATCH(($B$4+A81),$I$11:$I$33,1)+1)-INDEX($I$11:$I$33,MATCH(($B$4+A81),$I$11:$I$33,1))))))),1) -> 1 | D81: =B81*(1+$B$30)^(-A81) -> 0.70952269 | E81: =B81*C81*(1+$B$5)^(-A81) -> 1 | G81: =$B$31+0.125+21*0.25 -> 67.815 | H81: =IF(G81<$B$33,1,0) -> 1 | I81: =H81*(1-$B$6)^(G81-$B$31)*(1+$B$30)^(-G81) -> 0.41853389 | J81: =H81*(1-$B$6)^(G81-$B$31)*L81*(1+$B$5)^(-G81) -> 0.94741263 | L81: =IF($B$7="Oui",1-(IF(($B$4+G81)<=$L$11,$M$11,IF(($B$4+G81)>=$L$12,$M$12,INDEX($M$11:$M$12,MATCH(($B$4+G81),$L$11:$L$12,1))+(INDEX($M$11:$M$12,MATCH(($B$4+G81),$L$11:$L$12,1)+1)-INDEX($M$11:$M$12,MATCH(($B$4+G81),$L$11:$L$12,1)))*(($B$4+G81)-INDEX($L$11:$L$12,MATCH(($B$4+G81),$L$11:$L$12,1)))/(INDEX($L$11:$L$12,MATCH(($B$4+G81),$L$11:$L$12,1)+1)-INDEX($L$11:$L$12,MATCH(($B$4+G81),$L$11:$L$12,1)))))),1) -> 1
A82: =$B$32+0.125+22*0.25 -> 28.735 | B82: =IF(A82<$B$31,1,0) -> 1 | C82: =IF($B$7="Oui",1+((IF(($B$4+A82)<=$I$11,$J$11,IF(($B$4+A82)>=$I$33,$J$33,INDEX($J$11:$J$33,MATCH(($B$4+A82),$I$11:$I$33,1))+(INDEX($J$11:$J$33,MATCH(($B$4+A82),$I$11:$I$33,1)+1)-INDEX($J$11:$J$33,MATCH(($B$4+A82),$I$11:$I$33,1)))*(($B$4+A82)-INDEX($I$11:$I$33,MATCH(($B$4+A82),$I$11:$I$33,1)))/(INDEX($I$11:$I$33,MATCH(($B$4+A82),$I$11:$I$33,1)+1)-INDEX($I$11:$I$33,MATCH(($B$4+A82),$I$11:$I$33,1))))))-(IF(($B$4+A82)<=$L$11,$M$11,IF(($B$4+A82)>=$L$12,$M$12,INDEX($M$11:$M$12,MATCH(($B$4+A82),$L$11:$L$12,1))+(INDEX($M$11:$M$12,MATCH(($B$4+A82),$L$11:$L$12,1)+1)-INDEX($M$11:$M$12,MATCH(($B$4+A82),$L$11:$L$12,1)))*(($B$4+A82)-INDEX($L$11:$L$12,MATCH(($B$4+A82),$L$11:$L$12,1)))/(INDEX($L$11:$L$12,MATCH(($B$4+A82),$L$11:$L$12,1)+1)-INDEX($L$11:$L$12,MATCH(($B$4+A82),$L$11:$L$12,1)))))))/(1-(IF(($B$4+A82)<=$I$11,$J$11,IF(($B$4+A82)>=$I$33,$J$33,INDEX($J$11:$J$33,MATCH(($B$4+A82),$I$11:$I$33,1))+(INDEX($J$11:$J$33,MATCH(($B$4+A82),$I$11:$I$33,1)+1)-INDEX($J$11:$J$33,MATCH(($B$4+A82),$I$11:$I$33,1)))*(($B$4+A82)-INDEX($I$11:$I$33,MATCH(($B$4+A82),$I$11:$I$33,1)))/(INDEX($I$11:$I$33,MATCH(($B$4+A82),$I$11:$I$33,1)+1)-INDEX($I$11:$I$33,MATCH(($B$4+A82),$I$11:$I$33,1))))))),1) -> 1 | D82: =B82*(1+$B$30)^(-A82) -> 0.70738897 | E82: =B82*C82*(1+$B$5)^(-A82) -> 1 | G82: =$B$31+0.125+22*0.25 -> 68.065 | H82: =IF(G82<$B$33,1,0) -> 1 | I82: =H82*(1-$B$6)^(G82-$B$31)*(1+$B$30)^(-G82) -> 0.41622813 | J82: =H82*(1-$B$6)^(G82-$B$31)*L82*(1+$B$5)^(-G82) -> 0.94503517 | L82: =IF($B$7="Oui",1-(IF(($B$4+G82)<=$L$11,$M$11,IF(($B$4+G82)>=$L$12,$M$12,INDEX($M$11:$M$12,MATCH(($B$4+G82),$L$11:$L$12,1))+(INDEX($M$11:$M$12,MATCH(($B$4+G82),$L$11:$L$12,1)+1)-INDEX($M$11:$M$12,MATCH(($B$4+G82),$L$11:$L$12,1)))*(($B$4+G82)-INDEX($L$11:$L$12,MATCH(($B$4+G82),$L$11:$L$12,1)))/(INDEX($L$11:$L$12,MATCH(($B$4+G82),$L$11:$L$12,1)+1)-INDEX($L$11:$L$12,MATCH(($B$4+G82),$L$11:$L$12,1)))))),1) -> 1
A83: =$B$32+0.125+23*0.25 -> 28.985 | B83: =IF(A83<$B$31,1,0) -> 1 | C83: =IF($B$7="Oui",1+((IF(($B$4+A83)<=$I$11,$J$11,IF(($B$4+A83)>=$I$33,$J$33,INDEX($J$11:$J$33,MATCH(($B$4+A83),$I$11:$I$33,1))+(INDEX($J$11:$J$33,MATCH(($B$4+A83),$I$11:$I$33,1)+1)-INDEX($J$11:$J$33,MATCH(($B$4+A83),$I$11:$I$33,1)))*(($B$4+A83)-INDEX($I$11:$I$33,MATCH(($B$4+A83),$I$11:$I$33,1)))/(INDEX($I$11:$I$33,MATCH(($B$4+A83),$I$11:$I$33,1)+1)-INDEX($I$11:$I$33,MATCH(($B$4+A83),$I$11:$I$33,1))))))-(IF(($B$4+A83)<=$L$11,$M$11,IF(($B$4+A83)>=$L$12,$M$12,INDEX($M$11:$M$12,MATCH(($B$4+A83),$L$11:$L$12,1))+(INDEX($M$11:$M$12,MATCH(($B$4+A83),$L$11:$L$12,1)+1)-INDEX($M$11:$M$12,MATCH(($B$4+A83),$L$11:$L$12,1)))*(($B$4+A83)-INDEX($L$11:$L$12,MATCH(($B$4+A83),$L$11:$L$12,1)))/(INDEX($L$11:$L$12,MATCH(($B$4+A83),$L$11:$L$12,1)+1)-INDEX($L$11:$L$12,MATCH(($B$4+A83),$L$11:$L$12,1)))))))/(1-(IF(($B$4+A83)<=$I$11,$J$11,IF(($B$4+A83)>=$I$33,$J$33,INDEX($J$11:$J$33,MATCH(($B$4+A83),$I$11:$I$33,1))+(INDEX($J$11:$J$33,MATCH(($B$4+A83),$I$11:$I$33,1)+1)-INDEX($J$11:$J$33,MATCH(($B$4+A83),$I$11:$I$33,1)))*(($B$4+A83)-INDEX($I$11:$I$33,MATCH(($B$4+A83),$I$11:$I$33,1)))/(INDEX($I$11:$I$33,MATCH(($B$4+A83),$I$11:$I$33,1)+1)-INDEX($I$11:$I$33,MATCH(($B$4+A83),$I$11:$I$33,1))))))),1) -> 1 | D83: =B83*(1+$B$30)^(-A83) -> 0.70526167 | E83: =B83*C83*(1+$B$5)^(-A83) -> 1 | G83: =$B$31+0.125+23*0.25 -> 68.315 | H83: =IF(G83<$B$33,1,0) -> 1 | I83: =H83*(1-$B$6)^(G83-$B$31)*(1+$B$30)^(-G83) -> 0.41393507 | J83: =H83*(1-$B$6)^(G83-$B$31)*L83*(1+$B$5)^(-G83) -> 0.94266367 | L83: =IF($B$7="Oui",1-(IF(($B$4+G83)<=$L$11,$M$11,IF(($B$4+G83)>=$L$12,$M$12,INDEX($M$11:$M$12,MATCH(($B$4+G83),$L$11:$L$12,1))+(INDEX($M$11:$M$12,MATCH(($B$4+G83),$L$11:$L$12,1)+1)-INDEX($M$11:$M$12,MATCH(($B$4+G83),$L$11:$L$12,1)))*(($B$4+G83)-INDEX($L$11:$L$12,MATCH(($B$4+G83),$L$11:$L$12,1)))/(INDEX($L$11:$L$12,MATCH(($B$4+G83),$L$11:$L$12,1)+1)-INDEX($L$11:$L$12,MATCH(($B$4+G83),$L$11:$L$12,1)))))),1) -> 1
A84: =$B$32+0.125+24*0.25 -> 29.235 | B84: =IF(A84<$B$31,1,0) -> 1 | C84: =IF($B$7="Oui",1+((IF(($B$4+A84)<=$I$11,$J$11,IF(($B$4+A84)>=$I$33,$J$33,INDEX($J$11:$J$33,MATCH(($B$4+A84),$I$11:$I$33,1))+(INDEX($J$11:$J$33,MATCH(($B$4+A84),$I$11:$I$33,1)+1)-INDEX($J$11:$J$33,MATCH(($B$4+A84),$I$11:$I$33,1)))*(($B$4+A84)-INDEX($I$11:$I$33,MATCH(($B$4+A84),$I$11:$I$33,1)))/(INDEX($I$11:$I$33,MATCH(($B$4+A84),$I$11:$I$33,1)+1)-INDEX($I$11:$I$33,MATCH(($B$4+A84),$I$11:$I$33,1))))))-(IF(($B$4+A84)<=$L$11,$M$11,IF(($B$4+A84)>=$L$12,$M$12,INDEX($M$11:$M$12,MATCH(($B$4+A84),$L$11:$L$12,1))+(INDEX($M$11:$M$12,MATCH(($B$4+A84),$L$11:$L$12,1)+1)-INDEX($M$11:$M$12,MATCH(($B$4+A84),$L$11:$L$12,1)))*(($B$4+A84)-INDEX($L$11:$L$12,MATCH(($B$4+A84),$L$11:$L$12,1)))/(INDEX($L$11:$L$12,MATCH(($B$4+A84),$L$11:$L$12,1)+1)-INDEX($L$11:$L$12,MATCH(($B$4+A84),$L$11:$L$12,1)))))))/(1-(IF(($B$4+A84)<=$I$11,$J$11,IF(($B$4+A84)>=$I$33,$J$33,INDEX($J$11:$J$33,MATCH(($B$4+A84),$I$11:$I$33,1))+(INDEX($J$11:$J$33,MATCH(($B$4+A84),$I$11:$I$33,1)+1)-INDEX($J$11:$J$33,MATCH(($B$4+A84),$I$11:$I$33,1)))*(($B$4+A84)-INDEX($I$11:$I$33,MATCH(($B$4+A84),$I$11:$I$33,1)))/(INDEX($I$11:$I$33,MATCH(($B$4+A84),$I$11:$I$33,1)+1)-INDEX($I$11:$I$33,MATCH(($B$4+A84),$I$11:$I$33,1))))))),1) -> 1 | D84: =B84*(1+$B$30)^(-A84) -> 0.70314077 | E84: =B84*C84*(1+$B$5)^(-A84) -> 1 | G84: =$B$31+0.125+24*0.25 -> 68.565 | H84: =IF(G84<$B$33,1,0) -> 1 | I84: =H84*(1-$B$6)^(G84-$B$31)*(1+$B$30)^(-G84) -> 0.41165464 | J84: =H84*(1-$B$6)^(G84-$B$31)*L84*(1+$B$5)^(-G84) -> 0.94029812 | L84: =IF($B$7="Oui",1-(IF(($B$4+G84)<=$L$11,$M$11,IF(($B$4+G84)>=$L$12,$M$12,INDEX($M$11:$M$12,MATCH(($B$4+G84),$L$11:$L$12,1))+(INDEX($M$11:$M$12,MATCH(($B$4+G84),$L$11:$L$12,1)+1)-INDEX($M$11:$M$12,MATCH(($B$4+G84),$L$11:$L$12,1)))*(($B$4+G84)-INDEX($L$11:$L$12,MATCH(($B$4+G84),$L$11:$L$12,1)))/(INDEX($L$11:$L$12,MATCH(($B$4+G84),$L$11:$L$12,1)+1)-INDEX($L$11:$L$12,MATCH(($B$4+G84),$L$11:$L$12,1)))))),1) -> 1
A85: =$B$32+0.125+25*0.25 -> 29.485 | B85: =IF(A85<$B$31,1,0) -> 1 | C85: =IF($B$7="Oui",1+((IF(($B$4+A85)<=$I$11,$J$11,IF(($B$4+A85)>=$I$33,$J$33,INDEX($J$11:$J$33,MATCH(($B$4+A85),$I$11:$I$33,1))+(INDEX($J$11:$J$33,MATCH(($B$4+A85),$I$11:$I$33,1)+1)-INDEX($J$11:$J$33,MATCH(($B$4+A85),$I$11:$I$33,1)))*(($B$4+A85)-INDEX($I$11:$I$33,MATCH(($B$4+A85),$I$11:$I$33,1)))/(INDEX($I$11:$I$33,MATCH(($B$4+A85),$I$11:$I$33,1)+1)-INDEX($I$11:$I$33,MATCH(($B$4+A85),$I$11:$I$33,1))))))-(IF(($B$4+A85)<=$L$11,$M$11,IF(($B$4+A85)>=$L$12,$M$12,INDEX($M$11:$M$12,MATCH(($B$4+A85),$L$11:$L$12,1))+(INDEX($M$11:$M$12,MATCH(($B$4+A85),$L$11:$L$12,1)+1)-INDEX($M$11:$M$12,MATCH(($B$4+A85),$L$11:$L$12,1)))*(($B$4+A85)-INDEX($L$11:$L$12,MATCH(($B$4+A85),$L$11:$L$12,1)))/(INDEX($L$11:$L$12,MATCH(($B$4+A85),$L$11:$L$12,1)+1)-INDEX($L$11:$L$12,MATCH(($B$4+A85),$L$11:$L$12,1)))))))/(1-(IF(($B$4+A85)<=$I$11,$J$11,IF(($B$4+A85)>=$I$33,$J$33,INDEX($J$11:$J$33,MATCH(($B$4+A85),$I$11:$I$33,1))+(INDEX($J$11:$J$33,MATCH(($B$4+A85),$I$11:$I$33,1)+1)-INDEX($J$11:$J$33,MATCH(($B$4+A85),$I$11:$I$33,1)))*(($B$4+A85)-INDEX($I$11:$I$33,MATCH(($B$4+A85),$I$11:$I$33,1)))/(INDEX($I$11:$I$33,MATCH(($B$4+A85),$I$11:$I$33,1)+1)-INDEX($I$11:$I$33,MATCH(($B$4+A85),$I$11:$I$33,1))))))),1) -> 1 | D85: =B85*(1+$B$30)^(-A85) -> 0.70102625 | E85: =B85*C85*(1+$B$5)^(-A85) -> 1 | G85: =$B$31+0.125+25*0.25 -> 68.815 | H85: =IF(G85<$B$33,1,0) -> 1 | I85: =H85*(1-$B$6)^(G85-$B$31)*(1+$B$30)^(-G85) -> 0.40938678 | J85: =H85*(1-$B$6)^(G85-$B$31)*L85*(1+$B$5)^(-G85) -> 0.93793851 | L85: =IF($B$7="Oui",1-(IF(($B$4+G85)<=$L$11,$M$11,IF(($B$4+G85)>=$L$12,$M$12,INDEX($M$11:$M$12,MATCH(($B$4+G85),$L$11:$L$12,1))+(INDEX($M$11:$M$12,MATCH(($B$4+G85),$L$11:$L$12,1)+1)-INDEX($M$11:$M$12,MATCH(($B$4+G85),$L$11:$L$12,1)))*(($B$4+G85)-INDEX($L$11:$L$12,MATCH(($B$4+G85),$L$11:$L$12,1)))/(INDEX($L$11:$L$12,MATCH(($B$4+G85),$L$11:$L$12,1)+1)-INDEX($L$11:$L$12,MATCH(($B$4+G85),$L$11:$L$12,1)))))),1) -> 1
A86: =$B$32+0.125+26*0.25 -> 29.735 | B86: =IF(A86<$B$31,1,0) -> 1 | C86: =IF($B$7="Oui",1+((IF(($B$4+A86)<=$I$11,$J$11,IF(($B$4+A86)>=$I$33,$J$33,INDEX($J$11:$J$33,MATCH(($B$4+A86),$I$11:$I$33,1))+(INDEX($J$11:$J$33,MATCH(($B$4+A86),$I$11:$I$33,1)+1)-INDEX($J$11:$J$33,MATCH(($B$4+A86),$I$11:$I$33,1)))*(($B$4+A86)-INDEX($I$11:$I$33,MATCH(($B$4+A86),$I$11:$I$33,1)))/(INDEX($I$11:$I$33,MATCH(($B$4+A86),$I$11:$I$33,1)+1)-INDEX($I$11:$I$33,MATCH(($B$4+A86),$I$11:$I$33,1))))))-(IF(($B$4+A86)<=$L$11,$M$11,IF(($B$4+A86)>=$L$12,$M$12,INDEX($M$11:$M$12,MATCH(($B$4+A86),$L$11:$L$12,1))+(INDEX($M$11:$M$12,MATCH(($B$4+A86),$L$11:$L$12,1)+1)-INDEX($M$11:$M$12,MATCH(($B$4+A86),$L$11:$L$12,1)))*(($B$4+A86)-INDEX($L$11:$L$12,MATCH(($B$4+A86),$L$11:$L$12,1)))/(INDEX($L$11:$L$12,MATCH(($B$4+A86),$L$11:$L$12,1)+1)-INDEX($L$11:$L$12,MATCH(($B$4+A86),$L$11:$L$12,1)))))))/(1-(IF(($B$4+A86)<=$I$11,$J$11,IF(($B$4+A86)>=$I$33,$J$33,INDEX($J$11:$J$33,MATCH(($B$4+A86),$I$11:$I$33,1))+(INDEX($J$11:$J$33,MATCH(($B$4+A86),$I$11:$I$33,1)+1)-INDEX($J$11:$J$33,MATCH(($B$4+A86),$I$11:$I$33,1)))*(($B$4+A86)-INDEX($I$11:$I$33,MATCH(($B$4+A86),$I$11:$I$33,1)))/(INDEX($I$11:$I$33,MATCH(($B$4+A86),$I$11:$I$33,1)+1)-INDEX($I$11:$I$33,MATCH(($B$4+A86),$I$11:$I$33,1))))))),1) -> 1 | D86: =B86*(1+$B$30)^(-A86) -> 0.69891808 | E86: =B86*C86*(1+$B$5)^(-A86) -> 1 | G86: =$B$31+0.125+26*0.25 -> 69.065 | H86: =IF(G86<$B$33,1,0) -> 1 | I86: =H86*(1-$B$6)^(G86-$B$31)*(1+$B$30)^(-G86) -> 0.40713141 | J86: =H86*(1-$B$6)^(G86-$B$31)*L86*(1+$B$5)^(-G86) -> 0.93558481 | L86: =IF($B$7="Oui",1-(IF(($B$4+G86)<=$L$11,$M$11,IF(($B$4+G86)>=$L$12,$M$12,INDEX($M$11:$M$12,MATCH(($B$4+G86),$L$11:$L$12,1))+(INDEX($M$11:$M$12,MATCH(($B$4+G86),$L$11:$L$12,1)+1)-INDEX($M$11:$M$12,MATCH(($B$4+G86),$L$11:$L$12,1)))*(($B$4+G86)-INDEX($L$11:$L$12,MATCH(($B$4+G86),$L$11:$L$12,1)))/(INDEX($L$11:$L$12,MATCH(($B$4+G86),$L$11:$L$12,1)+1)-INDEX($L$11:$L$12,MATCH(($B$4+G86),$L$11:$L$12,1)))))),1) -> 1
A87: =$B$32+0.125+27*0.25 -> 29.985 | B87: =IF(A87<$B$31,1,0) -> 1 | C87: =IF($B$7="Oui",1+((IF(($B$4+A87)<=$I$11,$J$11,IF(($B$4+A87)>=$I$33,$J$33,INDEX($J$11:$J$33,MATCH(($B$4+A87),$I$11:$I$33,1))+(INDEX($J$11:$J$33,MATCH(($B$4+A87),$I$11:$I$33,1)+1)-INDEX($J$11:$J$33,MATCH(($B$4+A87),$I$11:$I$33,1)))*(($B$4+A87)-INDEX($I$11:$I$33,MATCH(($B$4+A87),$I$11:$I$33,1)))/(INDEX($I$11:$I$33,MATCH(($B$4+A87),$I$11:$I$33,1)+1)-INDEX($I$11:$I$33,MATCH(($B$4+A87),$I$11:$I$33,1))))))-(IF(($B$4+A87)<=$L$11,$M$11,IF(($B$4+A87)>=$L$12,$M$12,INDEX($M$11:$M$12,MATCH(($B$4+A87),$L$11:$L$12,1))+(INDEX($M$11:$M$12,MATCH(($B$4+A87),$L$11:$L$12,1)+1)-INDEX($M$11:$M$12,MATCH(($B$4+A87),$L$11:$L$12,1)))*(($B$4+A87)-INDEX($L$11:$L$12,MATCH(($B$4+A87),$L$11:$L$12,1)))/(INDEX($L$11:$L$12,MATCH(($B$4+A87),$L$11:$L$12,1)+1)-INDEX($L$11:$L$12,MATCH(($B$4+A87),$L$11:$L$12,1)))))))/(1-(IF(($B$4+A87)<=$I$11,$J$11,IF(($B$4+A87)>=$I$33,$J$33,INDEX($J$11:$J$33,MATCH(($B$4+A87),$I$11:$I$33,1))+(INDEX($J$11:$J$33,MATCH(($B$4+A87),$I$11:$I$33,1)+1)-INDEX($J$11:$J$33,MATCH(($B$4+A87),$I$11:$I$33,1)))*(($B$4+A87)-INDEX($I$11:$I$33,MATCH(($B$4+A87),$I$11:$I$33,1)))/(INDEX($I$11:$I$33,MATCH(($B$4+A87),$I$11:$I$33,1)+1)-INDEX($I$11:$I$33,MATCH(($B$4+A87),$I$11:$I$33,1))))))),1) -> 1 | D87: =B87*(1+$B$30)^(-A87) -> 0.69681626 | E87: =B87*C87*(1+$B$5)^(-A87) -> 1 | G87: =$B$31+0.125+27*0.25 -> 69.315 | H87: =IF(G87<$B$33,1,0) -> 1 | I87: =H87*(1-$B$6)^(G87-$B$31)*(1+$B$30)^(-G87) -> 0.40488847 | J87: =H87*(1-$B$6)^(G87-$B$31)*L87*(1+$B$5)^(-G87) -> 0.93323703 | L87: =IF($B$7="Oui",1-(IF(($B$4+G87)<=$L$11,$M$11,IF(($B$4+G87)>=$L$12,$M$12,INDEX($M$11:$M$12,MATCH(($B$4+G87),$L$11:$L$12,1))+(INDEX($M$11:$M$12,MATCH(($B$4+G87),$L$11:$L$12,1)+1)-INDEX($M$11:$M$12,MATCH(($B$4+G87),$L$11:$L$12,1)))*(($B$4+G87)-INDEX($L$11:$L$12,MATCH(($B$4+G87),$L$11:$L$12,1)))/(INDEX($L$11:$L$12,MATCH(($B$4+G87),$L$11:$L$12,1)+1)-INDEX($L$11:$L$12,MATCH(($B$4+G87),$L$11:$L$12,1)))))),1) -> 1
A88: =$B$32+0.125+28*0.25 -> 30.235 | B88: =IF(A88<$B$31,1,0) -> 1 | C88: =IF($B$7="Oui",1+((IF(($B$4+A88)<=$I$11,$J$11,IF(($B$4+A88)>=$I$33,$J$33,INDEX($J$11:$J$33,MATCH(($B$4+A88),$I$11:$I$33,1))+(INDEX($J$11:$J$33,MATCH(($B$4+A88),$I$11:$I$33,1)+1)-INDEX($J$11:$J$33,MATCH(($B$4+A88),$I$11:$I$33,1)))*(($B$4+A88)-INDEX($I$11:$I$33,MATCH(($B$4+A88),$I$11:$I$33,1)))/(INDEX($I$11:$I$33,MATCH(($B$4+A88),$I$11:$I$33,1)+1)-INDEX($I$11:$I$33,MATCH(($B$4+A88),$I$11:$I$33,1))))))-(IF(($B$4+A88)<=$L$11,$M$11,IF(($B$4+A88)>=$L$12,$M$12,INDEX($M$11:$M$12,MATCH(($B$4+A88),$L$11:$L$12,1))+(INDEX($M$11:$M$12,MATCH(($B$4+A88),$L$11:$L$12,1)+1)-INDEX($M$11:$M$12,MATCH(($B$4+A88),$L$11:$L$12,1)))*(($B$4+A88)-INDEX($L$11:$L$12,MATCH(($B$4+A88),$L$11:$L$12,1)))/(INDEX($L$11:$L$12,MATCH(($B$4+A88),$L$11:$L$12,1)+1)-INDEX($L$11:$L$12,MATCH(($B$4+A88),$L$11:$L$12,1)))))))/(1-(IF(($B$4+A88)<=$I$11,$J$11,IF(($B$4+A88)>=$I$33,$J$33,INDEX($J$11:$J$33,MATCH(($B$4+A88),$I$11:$I$33,1))+(INDEX($J$11:$J$33,MATCH(($B$4+A88),$I$11:$I$33,1)+1)-INDEX($J$11:$J$33,MATCH(($B$4+A88),$I$11:$I$33,1)))*(($B$4+A88)-INDEX($I$11:$I$33,MATCH(($B$4+A88),$I$11:$I$33,1)))/(INDEX($I$11:$I$33,MATCH(($B$4+A88),$I$11:$I$33,1)+1)-INDEX($I$11:$I$33,MATCH(($B$4+A88),$I$11:$I$33,1))))))),1) -> 1 | D88: =B88*(1+$B$30)^(-A88) -> 0.69472076 | E88: =B88*C88*(1+$B$5)^(-A88) -> 1 | G88: =$B$31+0.125+28*0.25 -> 69.565 | H88: =IF(G88<$B$33,1,0) -> 1 | I88: =H88*(1-$B$6)^(G88-$B$31)*(1+$B$30)^(-G88) -> 0.40265788 | J88: =H88*(1-$B$6)^(G88-$B$31)*L88*(1+$B$5)^(-G88) -> 0.93089514 | L88: =IF($B$7="Oui",1-(IF(($B$4+G88)<=$L$11,$M$11,IF(($B$4+G88)>=$L$12,$M$12,INDEX($M$11:$M$12,MATCH(($B$4+G88),$L$11:$L$12,1))+(INDEX($M$11:$M$12,MATCH(($B$4+G88),$L$11:$L$12,1)+1)-INDEX($M$11:$M$12,MATCH(($B$4+G88),$L$11:$L$12,1)))*(($B$4+G88)-INDEX($L$11:$L$12,MATCH(($B$4+G88),$L$11:$L$12,1)))/(INDEX($L$11:$L$12,MATCH(($B$4+G88),$L$11:$L$12,1)+1)-INDEX($L$11:$L$12,MATCH(($B$4+G88),$L$11:$L$12,1)))))),1) -> 1
A89: =$B$32+0.125+29*0.25 -> 30.485 | B89: =IF(A89<$B$31,1,0) -> 1 | C89: =IF($B$7="Oui",1+((IF(($B$4+A89)<=$I$11,$J$11,IF(($B$4+A89)>=$I$33,$J$33,INDEX($J$11:$J$33,MATCH(($B$4+A89),$I$11:$I$33,1))+(INDEX($J$11:$J$33,MATCH(($B$4+A89),$I$11:$I$33,1)+1)-INDEX($J$11:$J$33,MATCH(($B$4+A89),$I$11:$I$33,1)))*(($B$4+A89)-INDEX($I$11:$I$33,MATCH(($B$4+A89),$I$11:$I$33,1)))/(INDEX($I$11:$I$33,MATCH(($B$4+A89),$I$11:$I$33,1)+1)-INDEX($I$11:$I$33,MATCH(($B$4+A89),$I$11:$I$33,1))))))-(IF(($B$4+A89)<=$L$11,$M$11,IF(($B$4+A89)>=$L$12,$M$12,INDEX($M$11:$M$12,MATCH(($B$4+A89),$L$11:$L$12,1))+(INDEX($M$11:$M$12,MATCH(($B$4+A89),$L$11:$L$12,1)+1)-INDEX($M$11:$M$12,MATCH(($B$4+A89),$L$11:$L$12,1)))*(($B$4+A89)-INDEX($L$11:$L$12,MATCH(($B$4+A89),$L$11:$L$12,1)))/(INDEX($L$11:$L$12,MATCH(($B$4+A89),$L$11:$L$12,1)+1)-INDEX($L$11:$L$12,MATCH(($B$4+A89),$L$11:$L$12,1)))))))/(1-(IF(($B$4+A89)<=$I$11,$J$11,IF(($B$4+A89)>=$I$33,$J$33,INDEX($J$11:$J$33,MATCH(($B$4+A89),$I$11:$I$33,1))+(INDEX($J$11:$J$33,MATCH(($B$4+A89),$I$11:$I$33,1)+1)-INDEX($J$11:$J$33,MATCH(($B$4+A89),$I$11:$I$33,1)))*(($B$4+A89)-INDEX($I$11:$I$33,MATCH(($B$4+A89),$I$11:$I$33,1)))/(INDEX($I$11:$I$33,MATCH(($B$4+A89),$I$11:$I$33,1)+1)-INDEX($I$11:$I$33,MATCH(($B$4+A89),$I$11:$I$33,1))))))),1) -> 1 | D89: =B89*(1+$B$30)^(-A89) -> 0.69263155 | E89: =B89*C89*(1+$B$5)^(-A89) -> 1 | G89: =$B$31+0.125+29*0.25 -> 69.815 | H89: =IF(G89<$B$33,1,0) -> 1 | I89: =H89*(1-$B$6)^(G89-$B$31)*(1+$B$30)^(-G89) -> 0.40043959 | J89: =H89*(1-$B$6)^(G89-$B$31)*L89*(1+$B$5)^(-G89) -> 0.92855912 | L89: =IF($B$7="Oui",1-(IF(($B$4+G89)<=$L$11,$M$11,IF(($B$4+G89)>=$L$12,$M$12,INDEX($M$11:$M$12,MATCH(($B$4+G89),$L$11:$L$12,1))+(INDEX($M$11:$M$12,MATCH(($B$4+G89),$L$11:$L$12,1)+1)-INDEX($M$11:$M$12,MATCH(($B$4+G89),$L$11:$L$12,1)))*(($B$4+G89)-INDEX($L$11:$L$12,MATCH(($B$4+G89),$L$11:$L$12,1)))/(INDEX($L$11:$L$12,MATCH(($B$4+G89),$L$11:$L$12,1)+1)-INDEX($L$11:$L$12,MATCH(($B$4+G89),$L$11:$L$12,1)))))),1) -> 1
A90: =$B$32+0.125+30*0.25 -> 30.735 | B90: =IF(A90<$B$31,1,0) -> 1 | C90: =IF($B$7="Oui",1+((IF(($B$4+A90)<=$I$11,$J$11,IF(($B$4+A90)>=$I$33,$J$33,INDEX($J$11:$J$33,MATCH(($B$4+A90),$I$11:$I$33,1))+(INDEX($J$11:$J$33,MATCH(($B$4+A90),$I$11:$I$33,1)+1)-INDEX($J$11:$J$33,MATCH(($B$4+A90),$I$11:$I$33,1)))*(($B$4+A90)-INDEX($I$11:$I$33,MATCH(($B$4+A90),$I$11:$I$33,1)))/(INDEX($I$11:$I$33,MATCH(($B$4+A90),$I$11:$I$33,1)+1)-INDEX($I$11:$I$33,MATCH(($B$4+A90),$I$11:$I$33,1))))))-(IF(($B$4+A90)<=$L$11,$M$11,IF(($B$4+A90)>=$L$12,$M$12,INDEX($M$11:$M$12,MATCH(($B$4+A90),$L$11:$L$12,1))+(INDEX($M$11:$M$12,MATCH(($B$4+A90),$L$11:$L$12,1)+1)-INDEX($M$11:$M$12,MATCH(($B$4+A90),$L$11:$L$12,1)))*(($B$4+A90)-INDEX($L$11:$L$12,MATCH(($B$4+A90),$L$11:$L$12,1)))/(INDEX($L$11:$L$12,MATCH(($B$4+A90),$L$11:$L$12,1)+1)-INDEX($L$11:$L$12,MATCH(($B$4+A90),$L$11:$L$12,1)))))))/(1-(IF(($B$4+A90)<=$I$11,$J$11,IF(($B$4+A90)>=$I$33,$J$33,INDEX($J$11:$J$33,MATCH(($B$4+A90),$I$11:$I$33,1))+(INDEX($J$11:$J$33,MATCH(($B$4+A90),$I$11:$I$33,1)+1)-INDEX($J$11:$J$33,MATCH(($B$4+A90),$I$11:$I$33,1)))*(($B$4+A90)-INDEX($I$11:$I$33,MATCH(($B$4+A90),$I$11:$I$33,1)))/(INDEX($I$11:$I$33,MATCH(($B$4+A90),$I$11:$I$33,1)+1)-INDEX($I$11:$I$33,MATCH(($B$4+A90),$I$11:$I$33,1))))))),1) -> 1 | D90: =B90*(1+$B$30)^(-A90) -> 0.69054863 | E90: =B90*C90*(1+$B$5)^(-A90) -> 1 | G90: =$B$31+0.125+30*0.25 -> 70.065 | H90: =IF(G90<$B$33,1,0) -> 1 | I90: =H90*(1-$B$6)^(G90-$B$31)*(1+$B$30)^(-G90) -> 0.39823351 | J90: =H90*(1-$B$6)^(G90-$B$31)*L90*(1+$B$5)^(-G90) -> 0.92622897 | L90: =IF($B$7="Oui",1-(IF(($B$4+G90)<=$L$11,$M$11,IF(($B$4+G90)>=$L$12,$M$12,INDEX($M$11:$M$12,MATCH(($B$4+G90),$L$11:$L$12,1))+(INDEX($M$11:$M$12,MATCH(($B$4+G90),$L$11:$L$12,1)+1)-INDEX($M$11:$M$12,MATCH(($B$4+G90),$L$11:$L$12,1)))*(($B$4+G90)-INDEX($L$11:$L$12,MATCH(($B$4+G90),$L$11:$L$12,1)))/(INDEX($L$11:$L$12,MATCH(($B$4+G90),$L$11:$L$12,1)+1)-INDEX($L$11:$L$12,MATCH(($B$4+G90),$L$11:$L$12,1)))))),1) -> 1
A91: =$B$32+0.125+31*0.25 -> 30.985 | B91: =IF(A91<$B$31,1,0) -> 1 | C91: =IF($B$7="Oui",1+((IF(($B$4+A91)<=$I$11,$J$11,IF(($B$4+A91)>=$I$33,$J$33,INDEX($J$11:$J$33,MATCH(($B$4+A91),$I$11:$I$33,1))+(INDEX($J$11:$J$33,MATCH(($B$4+A91),$I$11:$I$33,1)+1)-INDEX($J$11:$J$33,MATCH(($B$4+A91),$I$11:$I$33,1)))*(($B$4+A91)-INDEX($I$11:$I$33,MATCH(($B$4+A91),$I$11:$I$33,1)))/(INDEX($I$11:$I$33,MATCH(($B$4+A91),$I$11:$I$33,1)+1)-INDEX($I$11:$I$33,MATCH(($B$4+A91),$I$11:$I$33,1))))))-(IF(($B$4+A91)<=$L$11,$M$11,IF(($B$4+A91)>=$L$12,$M$12,INDEX($M$11:$M$12,MATCH(($B$4+A91),$L$11:$L$12,1))+(INDEX($M$11:$M$12,MATCH(($B$4+A91),$L$11:$L$12,1)+1)-INDEX($M$11:$M$12,MATCH(($B$4+A91),$L$11:$L$12,1)))*(($B$4+A91)-INDEX($L$11:$L$12,MATCH(($B$4+A91),$L$11:$L$12,1)))/(INDEX($L$11:$L$12,MATCH(($B$4+A91),$L$11:$L$12,1)+1)-INDEX($L$11:$L$12,MATCH(($B$4+A91),$L$11:$L$12,1)))))))/(1-(IF(($B$4+A91)<=$I$11,$J$11,IF(($B$4+A91)>=$I$33,$J$33,INDEX($J$11:$J$33,MATCH(($B$4+A91),$I$11:$I$33,1))+(INDEX($J$11:$J$33,MATCH(($B$4+A91),$I$11:$I$33,1)+1)-INDEX($J$11:$J$33,MATCH(($B$4+A91),$I$11:$I$33,1)))*(($B$4+A91)-INDEX($I$11:$I$33,MATCH(($B$4+A91),$I$11:$I$33,1)))/(INDEX($I$11:$I$33,MATCH(($B$4+A91),$I$11:$I$33,1)+1)-INDEX($I$11:$I$33,MATCH(($B$4+A91),$I$11:$I$33,1))))))),1) -> 1 | D91: =B91*(1+$B$30)^(-A91) -> 0.68847198 | E91: =B91*C91*(1+$B$5)^(-A91) -> 1 | G91: =$B$31+0.125+31*0.25 -> 70.315 | H91: =IF(G91<$B$33,1,0) -> 1 | I91: =H91*(1-$B$6)^(G91-$B$31)*(1+$B$30)^(-G91) -> 0.39603959 | J91: =H91*(1-$B$6)^(G91-$B$31)*L91*(1+$B$5)^(-G91) -> 0.92390466 | L91: =IF($B$7="Oui",1-(IF(($B$4+G91)<=$L$11,$M$11,IF(($B$4+G91)>=$L$12,$M$12,INDEX($M$11:$M$12,MATCH(($B$4+G91),$L$11:$L$12,1))+(INDEX($M$11:$M$12,MATCH(($B$4+G91),$L$11:$L$12,1)+1)-INDEX($M$11:$M$12,MATCH(($B$4+G91),$L$11:$L$12,1)))*(($B$4+G91)-INDEX($L$11:$L$12,MATCH(($B$4+G91),$L$11:$L$12,1)))/(INDEX($L$11:$L$12,MATCH(($B$4+G91),$L$11:$L$12,1)+1)-INDEX($L$11:$L$12,MATCH(($B$4+G91),$L$11:$L$12,1)))))),1) -> 1
A92: =$B$32+0.125+32*0.25 -> 31.235 | B92: =IF(A92<$B$31,1,0) -> 1 | C92: =IF($B$7="Oui",1+((IF(($B$4+A92)<=$I$11,$J$11,IF(($B$4+A92)>=$I$33,$J$33,INDEX($J$11:$J$33,MATCH(($B$4+A92),$I$11:$I$33,1))+(INDEX($J$11:$J$33,MATCH(($B$4+A92),$I$11:$I$33,1)+1)-INDEX($J$11:$J$33,MATCH(($B$4+A92),$I$11:$I$33,1)))*(($B$4+A92)-INDEX($I$11:$I$33,MATCH(($B$4+A92),$I$11:$I$33,1)))/(INDEX($I$11:$I$33,MATCH(($B$4+A92),$I$11:$I$33,1)+1)-INDEX($I$11:$I$33,MATCH(($B$4+A92),$I$11:$I$33,1))))))-(IF(($B$4+A92)<=$L$11,$M$11,IF(($B$4+A92)>=$L$12,$M$12,INDEX($M$11:$M$12,MATCH(($B$4+A92),$L$11:$L$12,1))+(INDEX($M$11:$M$12,MATCH(($B$4+A92),$L$11:$L$12,1)+1)-INDEX($M$11:$M$12,MATCH(($B$4+A92),$L$11:$L$12,1)))*(($B$4+A92)-INDEX($L$11:$L$12,MATCH(($B$4+A92),$L$11:$L$12,1)))/(INDEX($L$11:$L$12,MATCH(($B$4+A92),$L$11:$L$12,1)+1)-INDEX($L$11:$L$12,MATCH(($B$4+A92),$L$11:$L$12,1)))))))/(1-(IF(($B$4+A92)<=$I$11,$J$11,IF(($B$4+A92)>=$I$33,$J$33,INDEX($J$11:$J$33,MATCH(($B$4+A92),$I$11:$I$33,1))+(INDEX($J$11:$J$33,MATCH(($B$4+A92),$I$11:$I$33,1)+1)-INDEX($J$11:$J$33,MATCH(($B$4+A92),$I$11:$I$33,1)))*(($B$4+A92)-INDEX($I$11:$I$33,MATCH(($B$4+A92),$I$11:$I$33,1)))/(INDEX($I$11:$I$33,MATCH(($B$4+A92),$I$11:$I$33,1)+1)-INDEX($I$11:$I$33,MATCH(($B$4+A92),$I$11:$I$33,1))))))),1) -> 1 | D92: =B92*(1+$B$30)^(-A92) -> 0.68640157 | E92: =B92*C92*(1+$B$5)^(-A92) -> 1 | G92: =$B$31+0.125+32*0.25 -> 70.565 | H92: =IF(G92<$B$33,1,0) -> 1 | I92: =H92*(1-$B$6)^(G92-$B$31)*(1+$B$30)^(-G92) -> 0.39385775 | J92: =H92*(1-$B$6)^(G92-$B$31)*L92*(1+$B$5)^(-G92) -> 0.92158619 | L92: =IF($B$7="Oui",1-(IF(($B$4+G92)<=$L$11,$M$11,IF(($B$4+G92)>=$L$12,$M$12,INDEX($M$11:$M$12,MATCH(($B$4+G92),$L$11:$L$12,1))+(INDEX($M$11:$M$12,MATCH(($B$4+G92),$L$11:$L$12,1)+1)-INDEX($M$11:$M$12,MATCH(($B$4+G92),$L$11:$L$12,1)))*(($B$4+G92)-INDEX($L$11:$L$12,MATCH(($B$4+G92),$L$11:$L$12,1)))/(INDEX($L$11:$L$12,MATCH(($B$4+G92),$L$11:$L$12,1)+1)-INDEX($L$11:$L$12,MATCH(($B$4+G92),$L$11:$L$12,1)))))),1) -> 1
A93: =$B$32+0.125+33*0.25 -> 31.485 | B93: =IF(A93<$B$31,1,0) -> 1 | C93: =IF($B$7="Oui",1+((IF(($B$4+A93)<=$I$11,$J$11,IF(($B$4+A93)>=$I$33,$J$33,INDEX($J$11:$J$33,MATCH(($B$4+A93),$I$11:$I$33,1))+(INDEX($J$11:$J$33,MATCH(($B$4+A93),$I$11:$I$33,1)+1)-INDEX($J$11:$J$33,MATCH(($B$4+A93),$I$11:$I$33,1)))*(($B$4+A93)-INDEX($I$11:$I$33,MATCH(($B$4+A93),$I$11:$I$33,1)))/(INDEX($I$11:$I$33,MATCH(($B$4+A93),$I$11:$I$33,1)+1)-INDEX($I$11:$I$33,MATCH(($B$4+A93),$I$11:$I$33,1))))))-(IF(($B$4+A93)<=$L$11,$M$11,IF(($B$4+A93)>=$L$12,$M$12,INDEX($M$11:$M$12,MATCH(($B$4+A93),$L$11:$L$12,1))+(INDEX($M$11:$M$12,MATCH(($B$4+A93),$L$11:$L$12,1)+1)-INDEX($M$11:$M$12,MATCH(($B$4+A93),$L$11:$L$12,1)))*(($B$4+A93)-INDEX($L$11:$L$12,MATCH(($B$4+A93),$L$11:$L$12,1)))/(INDEX($L$11:$L$12,MATCH(($B$4+A93),$L$11:$L$12,1)+1)-INDEX($L$11:$L$12,MATCH(($B$4+A93),$L$11:$L$12,1)))))))/(1-(IF(($B$4+A93)<=$I$11,$J$11,IF(($B$4+A93)>=$I$33,$J$33,INDEX($J$11:$J$33,MATCH(($B$4+A93),$I$11:$I$33,1))+(INDEX($J$11:$J$33,MATCH(($B$4+A93),$I$11:$I$33,1)+1)-INDEX($J$11:$J$33,MATCH(($B$4+A93),$I$11:$I$33,1)))*(($B$4+A93)-INDEX($I$11:$I$33,MATCH(($B$4+A93),$I$11:$I$33,1)))/(INDEX($I$11:$I$33,MATCH(($B$4+A93),$I$11:$I$33,1)+1)-INDEX($I$11:$I$33,MATCH(($B$4+A93),$I$11:$I$33,1))))))),1) -> 1 | D93: =B93*(1+$B$30)^(-A93) -> 0.68433738 | E93: =B93*C93*(1+$B$5)^(-A93) -> 1 | G93: =$B$31+0.125+33*0.25 -> 70.815 | H93: =IF(G93<$B$33,1,0) -> 1 | I93: =H93*(1-$B$6)^(G93-$B$31)*(1+$B$30)^(-G93) -> 0.39168793 | J93: =H93*(1-$B$6)^(G93-$B$31)*L93*(1+$B$5)^(-G93) -> 0.91927353 | L93: =IF($B$7="Oui",1-(IF(($B$4+G93)<=$L$11,$M$11,IF(($B$4+G93)>=$L$12,$M$12,INDEX($M$11:$M$12,MATCH(($B$4+G93),$L$11:$L$12,1))+(INDEX($M$11:$M$12,MATCH(($B$4+G93),$L$11:$L$12,1)+1)-INDEX($M$11:$M$12,MATCH(($B$4+G93),$L$11:$L$12,1)))*(($B$4+G93)-INDEX($L$11:$L$12,MATCH(($B$4+G93),$L$11:$L$12,1)))/(INDEX($L$11:$L$12,MATCH(($B$4+G93),$L$11:$L$12,1)+1)-INDEX($L$11:$L$12,MATCH(($B$4+G93),$L$11:$L$12,1)))))),1) -> 1
A94: =$B$32+0.125+34*0.25 -> 31.735 | B94: =IF(A94<$B$31,1,0) -> 1 | C94: =IF($B$7="Oui",1+((IF(($B$4+A94)<=$I$11,$J$11,IF(($B$4+A94)>=$I$33,$J$33,INDEX($J$11:$J$33,MATCH(($B$4+A94),$I$11:$I$33,1))+(INDEX($J$11:$J$33,MATCH(($B$4+A94),$I$11:$I$33,1)+1)-INDEX($J$11:$J$33,MATCH(($B$4+A94),$I$11:$I$33,1)))*(($B$4+A94)-INDEX($I$11:$I$33,MATCH(($B$4+A94),$I$11:$I$33,1)))/(INDEX($I$11:$I$33,MATCH(($B$4+A94),$I$11:$I$33,1)+1)-INDEX($I$11:$I$33,MATCH(($B$4+A94),$I$11:$I$33,1))))))-(IF(($B$4+A94)<=$L$11,$M$11,IF(($B$4+A94)>=$L$12,$M$12,INDEX($M$11:$M$12,MATCH(($B$4+A94),$L$11:$L$12,1))+(INDEX($M$11:$M$12,MATCH(($B$4+A94),$L$11:$L$12,1)+1)-INDEX($M$11:$M$12,MATCH(($B$4+A94),$L$11:$L$12,1)))*(($B$4+A94)-INDEX($L$11:$L$12,MATCH(($B$4+A94),$L$11:$L$12,1)))/(INDEX($L$11:$L$12,MATCH(($B$4+A94),$L$11:$L$12,1)+1)-INDEX($L$11:$L$12,MATCH(($B$4+A94),$L$11:$L$12,1)))))))/(1-(IF(($B$4+A94)<=$I$11,$J$11,IF(($B$4+A94)>=$I$33,$J$33,INDEX($J$11:$J$33,MATCH(($B$4+A94),$I$11:$I$33,1))+(INDEX($J$11:$J$33,MATCH(($B$4+A94),$I$11:$I$33,1)+1)-INDEX($J$11:$J$33,MATCH(($B$4+A94),$I$11:$I$33,1)))*(($B$4+A94)-INDEX($I$11:$I$33,MATCH(($B$4+A94),$I$11:$I$33,1)))/(INDEX($I$11:$I$33,MATCH(($B$4+A94),$I$11:$I$33,1)+1)-INDEX($I$11:$I$33,MATCH(($B$4+A94),$I$11:$I$33,1))))))),1) -> 1 | D94: =B94*(1+$B$30)^(-A94) -> 0.68227941 | E94: =B94*C94*(1+$B$5)^(-A94) -> 1 | G94: =$B$31+0.125+34*0.25 -> 71.065 | H94: =IF(G94<$B$33,1,0) -> 1 | I94: =H94*(1-$B$6)^(G94-$B$31)*(1+$B$30)^(-G94) -> 0.38953007 | J94: =H94*(1-$B$6)^(G94-$B$31)*L94*(1+$B$5)^(-G94) -> 0.91696668 | L94: =IF($B$7="Oui",1-(IF(($B$4+G94)<=$L$11,$M$11,IF(($B$4+G94)>=$L$12,$M$12,INDEX($M$11:$M$12,MATCH(($B$4+G94),$L$11:$L$12,1))+(INDEX($M$11:$M$12,MATCH(($B$4+G94),$L$11:$L$12,1)+1)-INDEX($M$11:$M$12,MATCH(($B$4+G94),$L$11:$L$12,1)))*(($B$4+G94)-INDEX($L$11:$L$12,MATCH(($B$4+G94),$L$11:$L$12,1)))/(INDEX($L$11:$L$12,MATCH(($B$4+G94),$L$11:$L$12,1)+1)-INDEX($L$11:$L$12,MATCH(($B$4+G94),$L$11:$L$12,1)))))),1) -> 1
A95: =$B$32+0.125+35*0.25 -> 31.985 | B95: =IF(A95<$B$31,1,0) -> 1 | C95: =IF($B$7="Oui",1+((IF(($B$4+A95)<=$I$11,$J$11,IF(($B$4+A95)>=$I$33,$J$33,INDEX($J$11:$J$33,MATCH(($B$4+A95),$I$11:$I$33,1))+(INDEX($J$11:$J$33,MATCH(($B$4+A95),$I$11:$I$33,1)+1)-INDEX($J$11:$J$33,MATCH(($B$4+A95),$I$11:$I$33,1)))*(($B$4+A95)-INDEX($I$11:$I$33,MATCH(($B$4+A95),$I$11:$I$33,1)))/(INDEX($I$11:$I$33,MATCH(($B$4+A95),$I$11:$I$33,1)+1)-INDEX($I$11:$I$33,MATCH(($B$4+A95),$I$11:$I$33,1))))))-(IF(($B$4+A95)<=$L$11,$M$11,IF(($B$4+A95)>=$L$12,$M$12,INDEX($M$11:$M$12,MATCH(($B$4+A95),$L$11:$L$12,1))+(INDEX($M$11:$M$12,MATCH(($B$4+A95),$L$11:$L$12,1)+1)-INDEX($M$11:$M$12,MATCH(($B$4+A95),$L$11:$L$12,1)))*(($B$4+A95)-INDEX($L$11:$L$12,MATCH(($B$4+A95),$L$11:$L$12,1)))/(INDEX($L$11:$L$12,MATCH(($B$4+A95),$L$11:$L$12,1)+1)-INDEX($L$11:$L$12,MATCH(($B$4+A95),$L$11:$L$12,1)))))))/(1-(IF(($B$4+A95)<=$I$11,$J$11,IF(($B$4+A95)>=$I$33,$J$33,INDEX($J$11:$J$33,MATCH(($B$4+A95),$I$11:$I$33,1))+(INDEX($J$11:$J$33,MATCH(($B$4+A95),$I$11:$I$33,1)+1)-INDEX($J$11:$J$33,MATCH(($B$4+A95),$I$11:$I$33,1)))*(($B$4+A95)-INDEX($I$11:$I$33,MATCH(($B$4+A95),$I$11:$I$33,1)))/(INDEX($I$11:$I$33,MATCH(($B$4+A95),$I$11:$I$33,1)+1)-INDEX($I$11:$I$33,MATCH(($B$4+A95),$I$11:$I$33,1))))))),1) -> 1 | D95: =B95*(1+$B$30)^(-A95) -> 0.68022762 | E95: =B95*C95*(1+$B$5)^(-A95) -> 1 | G95: =$B$31+0.125+35*0.25 -> 71.315 | H95: =IF(G95<$B$33,1,0) -> 1 | I95: =H95*(1-$B$6)^(G95-$B$31)*(1+$B$30)^(-G95) -> 0.38738409 | J95: =H95*(1-$B$6)^(G95-$B$31)*L95*(1+$B$5)^(-G95) -> 0.91466561 | L95: =IF($B$7="Oui",1-(IF(($B$4+G95)<=$L$11,$M$11,IF(($B$4+G95)>=$L$12,$M$12,INDEX($M$11:$M$12,MATCH(($B$4+G95),$L$11:$L$12,1))+(INDEX($M$11:$M$12,MATCH(($B$4+G95),$L$11:$L$12,1)+1)-INDEX($M$11:$M$12,MATCH(($B$4+G95),$L$11:$L$12,1)))*(($B$4+G95)-INDEX($L$11:$L$12,MATCH(($B$4+G95),$L$11:$L$12,1)))/(INDEX($L$11:$L$12,MATCH(($B$4+G95),$L$11:$L$12,1)+1)-INDEX($L$11:$L$12,MATCH(($B$4+G95),$L$11:$L$12,1)))))),1) -> 1
A96: =$B$32+0.125+36*0.25 -> 32.235 | B96: =IF(A96<$B$31,1,0) -> 1 | C96: =IF($B$7="Oui",1+((IF(($B$4+A96)<=$I$11,$J$11,IF(($B$4+A96)>=$I$33,$J$33,INDEX($J$11:$J$33,MATCH(($B$4+A96),$I$11:$I$33,1))+(INDEX($J$11:$J$33,MATCH(($B$4+A96),$I$11:$I$33,1)+1)-INDEX($J$11:$J$33,MATCH(($B$4+A96),$I$11:$I$33,1)))*(($B$4+A96)-INDEX($I$11:$I$33,MATCH(($B$4+A96),$I$11:$I$33,1)))/(INDEX($I$11:$I$33,MATCH(($B$4+A96),$I$11:$I$33,1)+1)-INDEX($I$11:$I$33,MATCH(($B$4+A96),$I$11:$I$33,1))))))-(IF(($B$4+A96)<=$L$11,$M$11,IF(($B$4+A96)>=$L$12,$M$12,INDEX($M$11:$M$12,MATCH(($B$4+A96),$L$11:$L$12,1))+(INDEX($M$11:$M$12,MATCH(($B$4+A96),$L$11:$L$12,1)+1)-INDEX($M$11:$M$12,MATCH(($B$4+A96),$L$11:$L$12,1)))*(($B$4+A96)-INDEX($L$11:$L$12,MATCH(($B$4+A96),$L$11:$L$12,1)))/(INDEX($L$11:$L$12,MATCH(($B$4+A96),$L$11:$L$12,1)+1)-INDEX($L$11:$L$12,MATCH(($B$4+A96),$L$11:$L$12,1)))))))/(1-(IF(($B$4+A96)<=$I$11,$J$11,IF(($B$4+A96)>=$I$33,$J$33,INDEX($J$11:$J$33,MATCH(($B$4+A96),$I$11:$I$33,1))+(INDEX($J$11:$J$33,MATCH(($B$4+A96),$I$11:$I$33,1)+1)-INDEX($J$11:$J$33,MATCH(($B$4+A96),$I$11:$I$33,1)))*(($B$4+A96)-INDEX($I$11:$I$33,MATCH(($B$4+A96),$I$11:$I$33,1)))/(INDEX($I$11:$I$33,MATCH(($B$4+A96),$I$11:$I$33,1)+1)-INDEX($I$11:$I$33,MATCH(($B$4+A96),$I$11:$I$33,1))))))),1) -> 1 | D96: =B96*(1+$B$30)^(-A96) -> 0.678182 | E96: =B96*C96*(1+$B$5)^(-A96) -> 1 | G96: =$B$31+0.125+36*0.25 -> 71.565 | H96: =IF(G96<$B$33,1,0) -> 1 | I96: =H96*(1-$B$6)^(G96-$B$31)*(1+$B$30)^(-G96) -> 0.38524994 | J96: =H96*(1-$B$6)^(G96-$B$31)*L96*(1+$B$5)^(-G96) -> 0.91237032 | L96: =IF($B$7="Oui",1-(IF(($B$4+G96)<=$L$11,$M$11,IF(($B$4+G96)>=$L$12,$M$12,INDEX($M$11:$M$12,MATCH(($B$4+G96),$L$11:$L$12,1))+(INDEX($M$11:$M$12,MATCH(($B$4+G96),$L$11:$L$12,1)+1)-INDEX($M$11:$M$12,MATCH(($B$4+G96),$L$11:$L$12,1)))*(($B$4+G96)-INDEX($L$11:$L$12,MATCH(($B$4+G96),$L$11:$L$12,1)))/(INDEX($L$11:$L$12,MATCH(($B$4+G96),$L$11:$L$12,1)+1)-INDEX($L$11:$L$12,MATCH(($B$4+G96),$L$11:$L$12,1)))))),1) -> 1
A97: =$B$32+0.125+37*0.25 -> 32.485 | B97: =IF(A97<$B$31,1,0) -> 1 | C97: =IF($B$7="Oui",1+((IF(($B$4+A97)<=$I$11,$J$11,IF(($B$4+A97)>=$I$33,$J$33,INDEX($J$11:$J$33,MATCH(($B$4+A97),$I$11:$I$33,1))+(INDEX($J$11:$J$33,MATCH(($B$4+A97),$I$11:$I$33,1)+1)-INDEX($J$11:$J$33,MATCH(($B$4+A97),$I$11:$I$33,1)))*(($B$4+A97)-INDEX($I$11:$I$33,MATCH(($B$4+A97),$I$11:$I$33,1)))/(INDEX($I$11:$I$33,MATCH(($B$4+A97),$I$11:$I$33,1)+1)-INDEX($I$11:$I$33,MATCH(($B$4+A97),$I$11:$I$33,1))))))-(IF(($B$4+A97)<=$L$11,$M$11,IF(($B$4+A97)>=$L$12,$M$12,INDEX($M$11:$M$12,MATCH(($B$4+A97),$L$11:$L$12,1))+(INDEX($M$11:$M$12,MATCH(($B$4+A97),$L$11:$L$12,1)+1)-INDEX($M$11:$M$12,MATCH(($B$4+A97),$L$11:$L$12,1)))*(($B$4+A97)-INDEX($L$11:$L$12,MATCH(($B$4+A97),$L$11:$L$12,1)))/(INDEX($L$11:$L$12,MATCH(($B$4+A97),$L$11:$L$12,1)+1)-INDEX($L$11:$L$12,MATCH(($B$4+A97),$L$11:$L$12,1)))))))/(1-(IF(($B$4+A97)<=$I$11,$J$11,IF(($B$4+A97)>=$I$33,$J$33,INDEX($J$11:$J$33,MATCH(($B$4+A97),$I$11:$I$33,1))+(INDEX($J$11:$J$33,MATCH(($B$4+A97),$I$11:$I$33,1)+1)-INDEX($J$11:$J$33,MATCH(($B$4+A97),$I$11:$I$33,1)))*(($B$4+A97)-INDEX($I$11:$I$33,MATCH(($B$4+A97),$I$11:$I$33,1)))/(INDEX($I$11:$I$33,MATCH(($B$4+A97),$I$11:$I$33,1)+1)-INDEX($I$11:$I$33,MATCH(($B$4+A97),$I$11:$I$33,1))))))),1) -> 1 | D97: =B97*(1+$B$30)^(-A97) -> 0.67614254 | E97: =B97*C97*(1+$B$5)^(-A97) -> 1 | G97: =$B$31+0.125+37*0.25 -> 71.815 | H97: =IF(G97<$B$33,1,0) -> 1 | I97: =H97*(1-$B$6)^(G97-$B$31)*(1+$B$30)^(-G97) -> 0.38312755 | J97: =H97*(1-$B$6)^(G97-$B$31)*L97*(1+$B$5)^(-G97) -> 0.91008079 | L97: =IF($B$7="Oui",1-(IF(($B$4+G97)<=$L$11,$M$11,IF(($B$4+G97)>=$L$12,$M$12,INDEX($M$11:$M$12,MATCH(($B$4+G97),$L$11:$L$12,1))+(INDEX($M$11:$M$12,MATCH(($B$4+G97),$L$11:$L$12,1)+1)-INDEX($M$11:$M$12,MATCH(($B$4+G97),$L$11:$L$12,1)))*(($B$4+G97)-INDEX($L$11:$L$12,MATCH(($B$4+G97),$L$11:$L$12,1)))/(INDEX($L$11:$L$12,MATCH(($B$4+G97),$L$11:$L$12,1)+1)-INDEX($L$11:$L$12,MATCH(($B$4+G97),$L$11:$L$12,1)))))),1) -> 1
A98: =$B$32+0.125+38*0.25 -> 32.735 | B98: =IF(A98<$B$31,1,0) -> 1 | C98: =IF($B$7="Oui",1+((IF(($B$4+A98)<=$I$11,$J$11,IF(($B$4+A98)>=$I$33,$J$33,INDEX($J$11:$J$33,MATCH(($B$4+A98),$I$11:$I$33,1))+(INDEX($J$11:$J$33,MATCH(($B$4+A98),$I$11:$I$33,1)+1)-INDEX($J$11:$J$33,MATCH(($B$4+A98),$I$11:$I$33,1)))*(($B$4+A98)-INDEX($I$11:$I$33,MATCH(($B$4+A98),$I$11:$I$33,1)))/(INDEX($I$11:$I$33,MATCH(($B$4+A98),$I$11:$I$33,1)+1)-INDEX($I$11:$I$33,MATCH(($B$4+A98),$I$11:$I$33,1))))))-(IF(($B$4+A98)<=$L$11,$M$11,IF(($B$4+A98)>=$L$12,$M$12,INDEX($M$11:$M$12,MATCH(($B$4+A98),$L$11:$L$12,1))+(INDEX($M$11:$M$12,MATCH(($B$4+A98),$L$11:$L$12,1)+1)-INDEX($M$11:$M$12,MATCH(($B$4+A98),$L$11:$L$12,1)))*(($B$4+A98)-INDEX($L$11:$L$12,MATCH(($B$4+A98),$L$11:$L$12,1)))/(INDEX($L$11:$L$12,MATCH(($B$4+A98),$L$11:$L$12,1)+1)-INDEX($L$11:$L$12,MATCH(($B$4+A98),$L$11:$L$12,1)))))))/(1-(IF(($B$4+A98)<=$I$11,$J$11,IF(($B$4+A98)>=$I$33,$J$33,INDEX($J$11:$J$33,MATCH(($B$4+A98),$I$11:$I$33,1))+(INDEX($J$11:$J$33,MATCH(($B$4+A98),$I$11:$I$33,1)+1)-INDEX($J$11:$J$33,MATCH(($B$4+A98),$I$11:$I$33,1)))*(($B$4+A98)-INDEX($I$11:$I$33,MATCH(($B$4+A98),$I$11:$I$33,1)))/(INDEX($I$11:$I$33,MATCH(($B$4+A98),$I$11:$I$33,1)+1)-INDEX($I$11:$I$33,MATCH(($B$4+A98),$I$11:$I$33,1))))))),1) -> 1 | D98: =B98*(1+$B$30)^(-A98) -> 0.6741092 | E98: =B98*C98*(1+$B$5)^(-A98) -> 1 | G98: =$B$31+0.125+38*0.25 -> 72.065 | H98: =IF(G98<$B$33,1,0) -> 1 | I98: =H98*(1-$B$6)^(G98-$B$31)*(1+$B$30)^(-G98) -> 0.38101684 | J98: =H98*(1-$B$6)^(G98-$B$31)*L98*(1+$B$5)^(-G98) -> 0.90779701 | L98: =IF($B$7="Oui",1-(IF(($B$4+G98)<=$L$11,$M$11,IF(($B$4+G98)>=$L$12,$M$12,INDEX($M$11:$M$12,MATCH(($B$4+G98),$L$11:$L$12,1))+(INDEX($M$11:$M$12,MATCH(($B$4+G98),$L$11:$L$12,1)+1)-INDEX($M$11:$M$12,MATCH(($B$4+G98),$L$11:$L$12,1)))*(($B$4+G98)-INDEX($L$11:$L$12,MATCH(($B$4+G98),$L$11:$L$12,1)))/(INDEX($L$11:$L$12,MATCH(($B$4+G98),$L$11:$L$12,1)+1)-INDEX($L$11:$L$12,MATCH(($B$4+G98),$L$11:$L$12,1)))))),1) -> 1
A99: =$B$32+0.125+39*0.25 -> 32.985 | B99: =IF(A99<$B$31,1,0) -> 1 | C99: =IF($B$7="Oui",1+((IF(($B$4+A99)<=$I$11,$J$11,IF(($B$4+A99)>=$I$33,$J$33,INDEX($J$11:$J$33,MATCH(($B$4+A99),$I$11:$I$33,1))+(INDEX($J$11:$J$33,MATCH(($B$4+A99),$I$11:$I$33,1)+1)-INDEX($J$11:$J$33,MATCH(($B$4+A99),$I$11:$I$33,1)))*(($B$4+A99)-INDEX($I$11:$I$33,MATCH(($B$4+A99),$I$11:$I$33,1)))/(INDEX($I$11:$I$33,MATCH(($B$4+A99),$I$11:$I$33,1)+1)-INDEX($I$11:$I$33,MATCH(($B$4+A99),$I$11:$I$33,1))))))-(IF(($B$4+A99)<=$L$11,$M$11,IF(($B$4+A99)>=$L$12,$M$12,INDEX($M$11:$M$12,MATCH(($B$4+A99),$L$11:$L$12,1))+(INDEX($M$11:$M$12,MATCH(($B$4+A99),$L$11:$L$12,1)+1)-INDEX($M$11:$M$12,MATCH(($B$4+A99),$L$11:$L$12,1)))*(($B$4+A99)-INDEX($L$11:$L$12,MATCH(($B$4+A99),$L$11:$L$12,1)))/(INDEX($L$11:$L$12,MATCH(($B$4+A99),$L$11:$L$12,1)+1)-INDEX($L$11:$L$12,MATCH(($B$4+A99),$L$11:$L$12,1)))))))/(1-(IF(($B$4+A99)<=$I$11,$J$11,IF(($B$4+A99)>=$I$33,$J$33,INDEX($J$11:$J$33,MATCH(($B$4+A99),$I$11:$I$33,1))+(INDEX($J$11:$J$33,MATCH(($B$4+A99),$I$11:$I$33,1)+1)-INDEX($J$11:$J$33,MATCH(($B$4+A99),$I$11:$I$33,1)))*(($B$4+A99)-INDEX($I$11:$I$33,MATCH(($B$4+A99),$I$11:$I$33,1)))/(INDEX($I$11:$I$33,MATCH(($B$4+A99),$I$11:$I$33,1)+1)-INDEX($I$11:$I$33,MATCH(($B$4+A99),$I$11:$I$33,1))))))),1) -> 1 | D99: =B99*(1+$B$30)^(-A99) -> 0.67208199 | E99: =B99*C99*(1+$B$5)^(-A99) -> 1 | G99: =$B$31+0.125+39*0.25 -> 72.315 | H99: =IF(G99<$B$33,1,0) -> 1 | I99: =H99*(1-$B$6)^(G99-$B$31)*(1+$B$30)^(-G99) -> 0.37891777 | J99: =H99*(1-$B$6)^(G99-$B$31)*L99*(1+$B$5)^(-G99) -> 0.90551896 | L99: =IF($B$7="Oui",1-(IF(($B$4+G99)<=$L$11,$M$11,IF(($B$4+G99)>=$L$12,$M$12,INDEX($M$11:$M$12,MATCH(($B$4+G99),$L$11:$L$12,1))+(INDEX($M$11:$M$12,MATCH(($B$4+G99),$L$11:$L$12,1)+1)-INDEX($M$11:$M$12,MATCH(($B$4+G99),$L$11:$L$12,1)))*(($B$4+G99)-INDEX($L$11:$L$12,MATCH(($B$4+G99),$L$11:$L$12,1)))/(INDEX($L$11:$L$12,MATCH(($B$4+G99),$L$11:$L$12,1)+1)-INDEX($L$11:$L$12,MATCH(($B$4+G99),$L$11:$L$12,1)))))),1) -> 1
A100: =$B$32+0.125+40*0.25 -> 33.235 | B100: =IF(A100<$B$31,1,0) -> 1 | C100: =IF($B$7="Oui",1+((IF(($B$4+A100)<=$I$11,$J$11,IF(($B$4+A100)>=$I$33,$J$33,INDEX($J$11:$J$33,MATCH(($B$4+A100),$I$11:$I$33,1))+(INDEX($J$11:$J$33,MATCH(($B$4+A100),$I$11:$I$33,1)+1)-INDEX($J$11:$J$33,MATCH(($B$4+A100),$I$11:$I$33,1)))*(($B$4+A100)-INDEX($I$11:$I$33,MATCH(($B$4+A100),$I$11:$I$33,1)))/(INDEX($I$11:$I$33,MATCH(($B$4+A100),$I$11:$I$33,1)+1)-INDEX($I$11:$I$33,MATCH(($B$4+A100),$I$11:$I$33,1))))))-(IF(($B$4+A100)<=$L$11,$M$11,IF(($B$4+A100)>=$L$12,$M$12,INDEX($M$11:$M$12,MATCH(($B$4+A100),$L$11:$L$12,1))+(INDEX($M$11:$M$12,MATCH(($B$4+A100),$L$11:$L$12,1)+1)-INDEX($M$11:$M$12,MATCH(($B$4+A100),$L$11:$L$12,1)))*(($B$4+A100)-INDEX($L$11:$L$12,MATCH(($B$4+A100),$L$11:$L$12,1)))/(INDEX($L$11:$L$12,MATCH(($B$4+A100),$L$11:$L$12,1)+1)-INDEX($L$11:$L$12,MATCH(($B$4+A100),$L$11:$L$12,1)))))))/(1-(IF(($B$4+A100)<=$I$11,$J$11,IF(($B$4+A100)>=$I$33,$J$33,INDEX($J$11:$J$33,MATCH(($B$4+A100),$I$11:$I$33,1))+(INDEX($J$11:$J$33,MATCH(($B$4+A100),$I$11:$I$33,1)+1)-INDEX($J$11:$J$33,MATCH(($B$4+A100),$I$11:$I$33,1)))*(($B$4+A100)-INDEX($I$11:$I$33,MATCH(($B$4+A100),$I$11:$I$33,1)))/(INDEX($I$11:$I$33,MATCH(($B$4+A100),$I$11:$I$33,1)+1)-INDEX($I$11:$I$33,MATCH(($B$4+A100),$I$11:$I$33,1))))))),1) -> 1 | D100: =B100*(1+$B$30)^(-A100) -> 0.67006086 | E100: =B100*C100*(1+$B$5)^(-A100) -> 1 | G100: =$B$31+0.125+40*0.25 -> 72.565 | H100: =IF(G100<$B$33,1,0) -> 1 | I100: =H100*(1-$B$6)^(G100-$B$31)*(1+$B$30)^(-G100) -> 0.37683026 | J100: =H100*(1-$B$6)^(G100-$B$31)*L100*(1+$B$5)^(-G100) -> 0.90324662 | L100: =IF($B$7="Oui",1-(IF(($B$4+G100)<=$L$11,$M$11,IF(($B$4+G100)>=$L$12,$M$12,INDEX($M$11:$M$12,MATCH(($B$4+G100),$L$11:$L$12,1))+(INDEX($M$11:$M$12,MATCH(($B$4+G100),$L$11:$L$12,1)+1)-INDEX($M$11:$M$12,MATCH(($B$4+G100),$L$11:$L$12,1)))*(($B$4+G100)-INDEX($L$11:$L$12,MATCH(($B$4+G100),$L$11:$L$12,1)))/(INDEX($L$11:$L$12,MATCH(($B$4+G100),$L$11:$L$12,1)+1)-INDEX($L$11:$L$12,MATCH(($B$4+G100),$L$11:$L$12,1)))))),1) -> 1
A101: =$B$32+0.125+41*0.25 -> 33.485 | B101: =IF(A101<$B$31,1,0) -> 1 | C101: =IF($B$7="Oui",1+((IF(($B$4+A101)<=$I$11,$J$11,IF(($B$4+A101)>=$I$33,$J$33,INDEX($J$11:$J$33,MATCH(($B$4+A101),$I$11:$I$33,1))+(INDEX($J$11:$J$33,MATCH(($B$4+A101),$I$11:$I$33,1)+1)-INDEX($J$11:$J$33,MATCH(($B$4+A101),$I$11:$I$33,1)))*(($B$4+A101)-INDEX($I$11:$I$33,MATCH(($B$4+A101),$I$11:$I$33,1)))/(INDEX($I$11:$I$33,MATCH(($B$4+A101),$I$11:$I$33,1)+1)-INDEX($I$11:$I$33,MATCH(($B$4+A101),$I$11:$I$33,1))))))-(IF(($B$4+A101)<=$L$11,$M$11,IF(($B$4+A101)>=$L$12,$M$12,INDEX($M$11:$M$12,MATCH(($B$4+A101),$L$11:$L$12,1))+(INDEX($M$11:$M$12,MATCH(($B$4+A101),$L$11:$L$12,1)+1)-INDEX($M$11:$M$12,MATCH(($B$4+A101),$L$11:$L$12,1)))*(($B$4+A101)-INDEX($L$11:$L$12,MATCH(($B$4+A101),$L$11:$L$12,1)))/(INDEX($L$11:$L$12,MATCH(($B$4+A101),$L$11:$L$12,1)+1)-INDEX($L$11:$L$12,MATCH(($B$4+A101),$L$11:$L$12,1)))))))/(1-(IF(($B$4+A101)<=$I$11,$J$11,IF(($B$4+A101)>=$I$33,$J$33,INDEX($J$11:$J$33,MATCH(($B$4+A101),$I$11:$I$33,1))+(INDEX($J$11:$J$33,MATCH(($B$4+A101),$I$11:$I$33,1)+1)-INDEX($J$11:$J$33,MATCH(($B$4+A101),$I$11:$I$33,1)))*(($B$4+A101)-INDEX($I$11:$I$33,MATCH(($B$4+A101),$I$11:$I$33,1)))/(INDEX($I$11:$I$33,MATCH(($B$4+A101),$I$11:$I$33,1)+1)-INDEX($I$11:$I$33,MATCH(($B$4+A101),$I$11:$I$33,1))))))),1) -> 1 | D101: =B101*(1+$B$30)^(-A101) -> 0.66804582 | E101: =B101*C101*(1+$B$5)^(-A101) -> 1 | G101: =$B$31+0.125+41*0.25 -> 72.815 | H101: =IF(G101<$B$33,1,0) -> 1 | I101: =H101*(1-$B$6)^(G101-$B$31)*(1+$B$30)^(-G101) -> 0.37475425 | J101: =H101*(1-$B$6)^(G101-$B$31)*L101*(1+$B$5)^(-G101) -> 0.90097999 | L101: =IF($B$7="Oui",1-(IF(($B$4+G101)<=$L$11,$M$11,IF(($B$4+G101)>=$L$12,$M$12,INDEX($M$11:$M$12,MATCH(($B$4+G101),$L$11:$L$12,1))+(INDEX($M$11:$M$12,MATCH(($B$4+G101),$L$11:$L$12,1)+1)-INDEX($M$11:$M$12,MATCH(($B$4+G101),$L$11:$L$12,1)))*(($B$4+G101)-INDEX($L$11:$L$12,MATCH(($B$4+G101),$L$11:$L$12,1)))/(INDEX($L$11:$L$12,MATCH(($B$4+G101),$L$11:$L$12,1)+1)-INDEX($L$11:$L$12,MATCH(($B$4+G101),$L$11:$L$12,1)))))),1) -> 1
A102: =$B$32+0.125+42*0.25 -> 33.735 | B102: =IF(A102<$B$31,1,0) -> 1 | C102: =IF($B$7="Oui",1+((IF(($B$4+A102)<=$I$11,$J$11,IF(($B$4+A102)>=$I$33,$J$33,INDEX($J$11:$J$33,MATCH(($B$4+A102),$I$11:$I$33,1))+(INDEX($J$11:$J$33,MATCH(($B$4+A102),$I$11:$I$33,1)+1)-INDEX($J$11:$J$33,MATCH(($B$4+A102),$I$11:$I$33,1)))*(($B$4+A102)-INDEX($I$11:$I$33,MATCH(($B$4+A102),$I$11:$I$33,1)))/(INDEX($I$11:$I$33,MATCH(($B$4+A102),$I$11:$I$33,1)+1)-INDEX($I$11:$I$33,MATCH(($B$4+A102),$I$11:$I$33,1))))))-(IF(($B$4+A102)<=$L$11,$M$11,IF(($B$4+A102)>=$L$12,$M$12,INDEX($M$11:$M$12,MATCH(($B$4+A102),$L$11:$L$12,1))+(INDEX($M$11:$M$12,MATCH(($B$4+A102),$L$11:$L$12,1)+1)-INDEX($M$11:$M$12,MATCH(($B$4+A102),$L$11:$L$12,1)))*(($B$4+A102)-INDEX($L$11:$L$12,MATCH(($B$4+A102),$L$11:$L$12,1)))/(INDEX($L$11:$L$12,MATCH(($B$4+A102),$L$11:$L$12,1)+1)-INDEX($L$11:$L$12,MATCH(($B$4+A102),$L$11:$L$12,1)))))))/(1-(IF(($B$4+A102)<=$I$11,$J$11,IF(($B$4+A102)>=$I$33,$J$33,INDEX($J$11:$J$33,MATCH(($B$4+A102),$I$11:$I$33,1))+(INDEX($J$11:$J$33,MATCH(($B$4+A102),$I$11:$I$33,1)+1)-INDEX($J$11:$J$33,MATCH(($B$4+A102),$I$11:$I$33,1)))*(($B$4+A102)-INDEX($I$11:$I$33,MATCH(($B$4+A102),$I$11:$I$33,1)))/(INDEX($I$11:$I$33,MATCH(($B$4+A102),$I$11:$I$33,1)+1)-INDEX($I$11:$I$33,MATCH(($B$4+A102),$I$11:$I$33,1))))))),1) -> 1 | D102: =B102*(1+$B$30)^(-A102) -> 0.66603684 | E102: =B102*C102*(1+$B$5)^(-A102) -> 1 | G102: =$B$31+0.125+42*0.25 -> 73.065 | H102: =IF(G102<$B$33,1,0) -> 1 | I102: =H102*(1-$B$6)^(G102-$B$31)*(1+$B$30)^(-G102) -> 0.37268968 | J102: =H102*(1-$B$6)^(G102-$B$31)*L102*(1+$B$5)^(-G102) -> 0.89871904 | L102: =IF($B$7="Oui",1-(IF(($B$4+G102)<=$L$11,$M$11,IF(($B$4+G102)>=$L$12,$M$12,INDEX($M$11:$M$12,MATCH(($B$4+G102),$L$11:$L$12,1))+(INDEX($M$11:$M$12,MATCH(($B$4+G102),$L$11:$L$12,1)+1)-INDEX($M$11:$M$12,MATCH(($B$4+G102),$L$11:$L$12,1)))*(($B$4+G102)-INDEX($L$11:$L$12,MATCH(($B$4+G102),$L$11:$L$12,1)))/(INDEX($L$11:$L$12,MATCH(($B$4+G102),$L$11:$L$12,1)+1)-INDEX($L$11:$L$12,MATCH(($B$4+G102),$L$11:$L$12,1)))))),1) -> 1
A103: =$B$32+0.125+43*0.25 -> 33.985 | B103: =IF(A103<$B$31,1,0) -> 1 | C103: =IF($B$7="Oui",1+((IF(($B$4+A103)<=$I$11,$J$11,IF(($B$4+A103)>=$I$33,$J$33,INDEX($J$11:$J$33,MATCH(($B$4+A103),$I$11:$I$33,1))+(INDEX($J$11:$J$33,MATCH(($B$4+A103),$I$11:$I$33,1)+1)-INDEX($J$11:$J$33,MATCH(($B$4+A103),$I$11:$I$33,1)))*(($B$4+A103)-INDEX($I$11:$I$33,MATCH(($B$4+A103),$I$11:$I$33,1)))/(INDEX($I$11:$I$33,MATCH(($B$4+A103),$I$11:$I$33,1)+1)-INDEX($I$11:$I$33,MATCH(($B$4+A103),$I$11:$I$33,1))))))-(IF(($B$4+A103)<=$L$11,$M$11,IF(($B$4+A103)>=$L$12,$M$12,INDEX($M$11:$M$12,MATCH(($B$4+A103),$L$11:$L$12,1))+(INDEX($M$11:$M$12,MATCH(($B$4+A103),$L$11:$L$12,1)+1)-INDEX($M$11:$M$12,MATCH(($B$4+A103),$L$11:$L$12,1)))*(($B$4+A103)-INDEX($L$11:$L$12,MATCH(($B$4+A103),$L$11:$L$12,1)))/(INDEX($L$11:$L$12,MATCH(($B$4+A103),$L$11:$L$12,1)+1)-INDEX($L$11:$L$12,MATCH(($B$4+A103),$L$11:$L$12,1)))))))/(1-(IF(($B$4+A103)<=$I$11,$J$11,IF(($B$4+A103)>=$I$33,$J$33,INDEX($J$11:$J$33,MATCH(($B$4+A103),$I$11:$I$33,1))+(INDEX($J$11:$J$33,MATCH(($B$4+A103),$I$11:$I$33,1)+1)-INDEX($J$11:$J$33,MATCH(($B$4+A103),$I$11:$I$33,1)))*(($B$4+A103)-INDEX($I$11:$I$33,MATCH(($B$4+A103),$I$11:$I$33,1)))/(INDEX($I$11:$I$33,MATCH(($B$4+A103),$I$11:$I$33,1)+1)-INDEX($I$11:$I$33,MATCH(($B$4+A103),$I$11:$I$33,1))))))),1) -> 1 | D103: =B103*(1+$B$30)^(-A103) -> 0.6640339 | E103: =B103*C103*(1+$B$5)^(-A103) -> 1 | G103: =$B$31+0.125+43*0.25 -> 73.315 | H103: =IF(G103<$B$33,1,0) -> 1 | I103: =H103*(1-$B$6)^(G103-$B$31)*(1+$B$30)^(-G103) -> 0.37063648 | J103: =H103*(1-$B$6)^(G103-$B$31)*L103*(1+$B$5)^(-G103) -> 0.89646377 | L103: =IF($B$7="Oui",1-(IF(($B$4+G103)<=$L$11,$M$11,IF(($B$4+G103)>=$L$12,$M$12,INDEX($M$11:$M$12,MATCH(($B$4+G103),$L$11:$L$12,1))+(INDEX($M$11:$M$12,MATCH(($B$4+G103),$L$11:$L$12,1)+1)-INDEX($M$11:$M$12,MATCH(($B$4+G103),$L$11:$L$12,1)))*(($B$4+G103)-INDEX($L$11:$L$12,MATCH(($B$4+G103),$L$11:$L$12,1)))/(INDEX($L$11:$L$12,MATCH(($B$4+G103),$L$11:$L$12,1)+1)-INDEX($L$11:$L$12,MATCH(($B$4+G103),$L$11:$L$12,1)))))),1) -> 1
A104: =$B$32+0.125+44*0.25 -> 34.235 | B104: =IF(A104<$B$31,1,0) -> 1 | C104: =IF($B$7="Oui",1+((IF(($B$4+A104)<=$I$11,$J$11,IF(($B$4+A104)>=$I$33,$J$33,INDEX($J$11:$J$33,MATCH(($B$4+A104),$I$11:$I$33,1))+(INDEX($J$11:$J$33,MATCH(($B$4+A104),$I$11:$I$33,1)+1)-INDEX($J$11:$J$33,MATCH(($B$4+A104),$I$11:$I$33,1)))*(($B$4+A104)-INDEX($I$11:$I$33,MATCH(($B$4+A104),$I$11:$I$33,1)))/(INDEX($I$11:$I$33,MATCH(($B$4+A104),$I$11:$I$33,1)+1)-INDEX($I$11:$I$33,MATCH(($B$4+A104),$I$11:$I$33,1))))))-(IF(($B$4+A104)<=$L$11,$M$11,IF(($B$4+A104)>=$L$12,$M$12,INDEX($M$11:$M$12,MATCH(($B$4+A104),$L$11:$L$12,1))+(INDEX($M$11:$M$12,MATCH(($B$4+A104),$L$11:$L$12,1)+1)-INDEX($M$11:$M$12,MATCH(($B$4+A104),$L$11:$L$12,1)))*(($B$4+A104)-INDEX($L$11:$L$12,MATCH(($B$4+A104),$L$11:$L$12,1)))/(INDEX($L$11:$L$12,MATCH(($B$4+A104),$L$11:$L$12,1)+1)-INDEX($L$11:$L$12,MATCH(($B$4+A104),$L$11:$L$12,1)))))))/(1-(IF(($B$4+A104)<=$I$11,$J$11,IF(($B$4+A104)>=$I$33,$J$33,INDEX($J$11:$J$33,MATCH(($B$4+A104),$I$11:$I$33,1))+(INDEX($J$11:$J$33,MATCH(($B$4+A104),$I$11:$I$33,1)+1)-INDEX($J$11:$J$33,MATCH(($B$4+A104),$I$11:$I$33,1)))*(($B$4+A104)-INDEX($I$11:$I$33,MATCH(($B$4+A104),$I$11:$I$33,1)))/(INDEX($I$11:$I$33,MATCH(($B$4+A104),$I$11:$I$33,1)+1)-INDEX($I$11:$I$33,MATCH(($B$4+A104),$I$11:$I$33,1))))))),1) -> 1 | D104: =B104*(1+$B$30)^(-A104) -> 0.66203698 | E104: =B104*C104*(1+$B$5)^(-A104) -> 1 | G104: =$B$31+0.125+44*0.25 -> 73.565 | H104: =IF(G104<$B$33,1,0) -> 1 | I104: =H104*(1-$B$6)^(G104-$B$31)*(1+$B$30)^(-G104) -> 0.36859459 | J104: =H104*(1-$B$6)^(G104-$B$31)*L104*(1+$B$5)^(-G104) -> 0.89421415 | L104: =IF($B$7="Oui",1-(IF(($B$4+G104)<=$L$11,$M$11,IF(($B$4+G104)>=$L$12,$M$12,INDEX($M$11:$M$12,MATCH(($B$4+G104),$L$11:$L$12,1))+(INDEX($M$11:$M$12,MATCH(($B$4+G104),$L$11:$L$12,1)+1)-INDEX($M$11:$M$12,MATCH(($B$4+G104),$L$11:$L$12,1)))*(($B$4+G104)-INDEX($L$11:$L$12,MATCH(($B$4+G104),$L$11:$L$12,1)))/(INDEX($L$11:$L$12,MATCH(($B$4+G104),$L$11:$L$12,1)+1)-INDEX($L$11:$L$12,MATCH(($B$4+G104),$L$11:$L$12,1)))))),1) -> 1
A105: =$B$32+0.125+45*0.25 -> 34.485 | B105: =IF(A105<$B$31,1,0) -> 1 | C105: =IF($B$7="Oui",1+((IF(($B$4+A105)<=$I$11,$J$11,IF(($B$4+A105)>=$I$33,$J$33,INDEX($J$11:$J$33,MATCH(($B$4+A105),$I$11:$I$33,1))+(INDEX($J$11:$J$33,MATCH(($B$4+A105),$I$11:$I$33,1)+1)-INDEX($J$11:$J$33,MATCH(($B$4+A105),$I$11:$I$33,1)))*(($B$4+A105)-INDEX($I$11:$I$33,MATCH(($B$4+A105),$I$11:$I$33,1)))/(INDEX($I$11:$I$33,MATCH(($B$4+A105),$I$11:$I$33,1)+1)-INDEX($I$11:$I$33,MATCH(($B$4+A105),$I$11:$I$33,1))))))-(IF(($B$4+A105)<=$L$11,$M$11,IF(($B$4+A105)>=$L$12,$M$12,INDEX($M$11:$M$12,MATCH(($B$4+A105),$L$11:$L$12,1))+(INDEX($M$11:$M$12,MATCH(($B$4+A105),$L$11:$L$12,1)+1)-INDEX($M$11:$M$12,MATCH(($B$4+A105),$L$11:$L$12,1)))*(($B$4+A105)-INDEX($L$11:$L$12,MATCH(($B$4+A105),$L$11:$L$12,1)))/(INDEX($L$11:$L$12,MATCH(($B$4+A105),$L$11:$L$12,1)+1)-INDEX($L$11:$L$12,MATCH(($B$4+A105),$L$11:$L$12,1)))))))/(1-(IF(($B$4+A105)<=$I$11,$J$11,IF(($B$4+A105)>=$I$33,$J$33,INDEX($J$11:$J$33,MATCH(($B$4+A105),$I$11:$I$33,1))+(INDEX($J$11:$J$33,MATCH(($B$4+A105),$I$11:$I$33,1)+1)-INDEX($J$11:$J$33,MATCH(($B$4+A105),$I$11:$I$33,1)))*(($B$4+A105)-INDEX($I$11:$I$33,MATCH(($B$4+A105),$I$11:$I$33,1)))/(INDEX($I$11:$I$33,MATCH(($B$4+A105),$I$11:$I$33,1)+1)-INDEX($I$11:$I$33,MATCH(($B$4+A105),$I$11:$I$33,1))))))),1) -> 1 | D105: =B105*(1+$B$30)^(-A105) -> 0.66004606 | E105: =B105*C105*(1+$B$5)^(-A105) -> 1 | G105: =$B$31+0.125+45*0.25 -> 73.815 | H105: =IF(G105<$B$33,1,0) -> 1 | I105: =H105*(1-$B$6)^(G105-$B$31)*(1+$B$30)^(-G105) -> 0.36656395 | J105: =H105*(1-$B$6)^(G105-$B$31)*L105*(1+$B$5)^(-G105) -> 0.89197019 | L105: =IF($B$7="Oui",1-(IF(($B$4+G105)<=$L$11,$M$11,IF(($B$4+G105)>=$L$12,$M$12,INDEX($M$11:$M$12,MATCH(($B$4+G105),$L$11:$L$12,1))+(INDEX($M$11:$M$12,MATCH(($B$4+G105),$L$11:$L$12,1)+1)-INDEX($M$11:$M$12,MATCH(($B$4+G105),$L$11:$L$12,1)))*(($B$4+G105)-INDEX($L$11:$L$12,MATCH(($B$4+G105),$L$11:$L$12,1)))/(INDEX($L$11:$L$12,MATCH(($B$4+G105),$L$11:$L$12,1)+1)-INDEX($L$11:$L$12,MATCH(($B$4+G105),$L$11:$L$12,1)))))),1) -> 1
A106: =$B$32+0.125+46*0.25 -> 34.735 | B106: =IF(A106<$B$31,1,0) -> 1 | C106: =IF($B$7="Oui",1+((IF(($B$4+A106)<=$I$11,$J$11,IF(($B$4+A106)>=$I$33,$J$33,INDEX($J$11:$J$33,MATCH(($B$4+A106),$I$11:$I$33,1))+(INDEX($J$11:$J$33,MATCH(($B$4+A106),$I$11:$I$33,1)+1)-INDEX($J$11:$J$33,MATCH(($B$4+A106),$I$11:$I$33,1)))*(($B$4+A106)-INDEX($I$11:$I$33,MATCH(($B$4+A106),$I$11:$I$33,1)))/(INDEX($I$11:$I$33,MATCH(($B$4+A106),$I$11:$I$33,1)+1)-INDEX($I$11:$I$33,MATCH(($B$4+A106),$I$11:$I$33,1))))))-(IF(($B$4+A106)<=$L$11,$M$11,IF(($B$4+A106)>=$L$12,$M$12,INDEX($M$11:$M$12,MATCH(($B$4+A106),$L$11:$L$12,1))+(INDEX($M$11:$M$12,MATCH(($B$4+A106),$L$11:$L$12,1)+1)-INDEX($M$11:$M$12,MATCH(($B$4+A106),$L$11:$L$12,1)))*(($B$4+A106)-INDEX($L$11:$L$12,MATCH(($B$4+A106),$L$11:$L$12,1)))/(INDEX($L$11:$L$12,MATCH(($B$4+A106),$L$11:$L$12,1)+1)-INDEX($L$11:$L$12,MATCH(($B$4+A106),$L$11:$L$12,1)))))))/(1-(IF(($B$4+A106)<=$I$11,$J$11,IF(($B$4+A106)>=$I$33,$J$33,INDEX($J$11:$J$33,MATCH(($B$4+A106),$I$11:$I$33,1))+(INDEX($J$11:$J$33,MATCH(($B$4+A106),$I$11:$I$33,1)+1)-INDEX($J$11:$J$33,MATCH(($B$4+A106),$I$11:$I$33,1)))*(($B$4+A106)-INDEX($I$11:$I$33,MATCH(($B$4+A106),$I$11:$I$33,1)))/(INDEX($I$11:$I$33,MATCH(($B$4+A106),$I$11:$I$33,1)+1)-INDEX($I$11:$I$33,MATCH(($B$4+A106),$I$11:$I$33,1))))))),1) -> 1 | D106: =B106*(1+$B$30)^(-A106) -> 0.65806114 | E106: =B106*C106*(1+$B$5)^(-A106) -> 1 | G106: =$B$31+0.125+46*0.25 -> 74.065 | H106: =IF(G106<$B$33,1,0) -> 1 | I106: =H106*(1-$B$6)^(G106-$B$31)*(1+$B$30)^(-G106) -> 0.3645445 | J106: =H106*(1-$B$6)^(G106-$B$31)*L106*(1+$B$5)^(-G106) -> 0.88973185 | L106: =IF($B$7="Oui",1-(IF(($B$4+G106)<=$L$11,$M$11,IF(($B$4+G106)>=$L$12,$M$12,INDEX($M$11:$M$12,MATCH(($B$4+G106),$L$11:$L$12,1))+(INDEX($M$11:$M$12,MATCH(($B$4+G106),$L$11:$L$12,1)+1)-INDEX($M$11:$M$12,MATCH(($B$4+G106),$L$11:$L$12,1)))*(($B$4+G106)-INDEX($L$11:$L$12,MATCH(($B$4+G106),$L$11:$L$12,1)))/(INDEX($L$11:$L$12,MATCH(($B$4+G106),$L$11:$L$12,1)+1)-INDEX($L$11:$L$12,MATCH(($B$4+G106),$L$11:$L$12,1)))))),1) -> 1
A107: =$B$32+0.125+47*0.25 -> 34.985 | B107: =IF(A107<$B$31,1,0) -> 1 | C107: =IF($B$7="Oui",1+((IF(($B$4+A107)<=$I$11,$J$11,IF(($B$4+A107)>=$I$33,$J$33,INDEX($J$11:$J$33,MATCH(($B$4+A107),$I$11:$I$33,1))+(INDEX($J$11:$J$33,MATCH(($B$4+A107),$I$11:$I$33,1)+1)-INDEX($J$11:$J$33,MATCH(($B$4+A107),$I$11:$I$33,1)))*(($B$4+A107)-INDEX($I$11:$I$33,MATCH(($B$4+A107),$I$11:$I$33,1)))/(INDEX($I$11:$I$33,MATCH(($B$4+A107),$I$11:$I$33,1)+1)-INDEX($I$11:$I$33,MATCH(($B$4+A107),$I$11:$I$33,1))))))-(IF(($B$4+A107)<=$L$11,$M$11,IF(($B$4+A107)>=$L$12,$M$12,INDEX($M$11:$M$12,MATCH(($B$4+A107),$L$11:$L$12,1))+(INDEX($M$11:$M$12,MATCH(($B$4+A107),$L$11:$L$12,1)+1)-INDEX($M$11:$M$12,MATCH(($B$4+A107),$L$11:$L$12,1)))*(($B$4+A107)-INDEX($L$11:$L$12,MATCH(($B$4+A107),$L$11:$L$12,1)))/(INDEX($L$11:$L$12,MATCH(($B$4+A107),$L$11:$L$12,1)+1)-INDEX($L$11:$L$12,MATCH(($B$4+A107),$L$11:$L$12,1)))))))/(1-(IF(($B$4+A107)<=$I$11,$J$11,IF(($B$4+A107)>=$I$33,$J$33,INDEX($J$11:$J$33,MATCH(($B$4+A107),$I$11:$I$33,1))+(INDEX($J$11:$J$33,MATCH(($B$4+A107),$I$11:$I$33,1)+1)-INDEX($J$11:$J$33,MATCH(($B$4+A107),$I$11:$I$33,1)))*(($B$4+A107)-INDEX($I$11:$I$33,MATCH(($B$4+A107),$I$11:$I$33,1)))/(INDEX($I$11:$I$33,MATCH(($B$4+A107),$I$11:$I$33,1)+1)-INDEX($I$11:$I$33,MATCH(($B$4+A107),$I$11:$I$33,1))))))),1) -> 1 | D107: =B107*(1+$B$30)^(-A107) -> 0.65608218 | E107: =B107*C107*(1+$B$5)^(-A107) -> 1 | G107: =$B$31+0.125+47*0.25 -> 74.315 | H107: =IF(G107<$B$33,1,0) -> 1 | I107: =H107*(1-$B$6)^(G107-$B$31)*(1+$B$30)^(-G107) -> 0.36253618 | J107: =H107*(1-$B$6)^(G107-$B$31)*L107*(1+$B$5)^(-G107) -> 0.88749913 | L107: =IF($B$7="Oui",1-(IF(($B$4+G107)<=$L$11,$M$11,IF(($B$4+G107)>=$L$12,$M$12,INDEX($M$11:$M$12,MATCH(($B$4+G107),$L$11:$L$12,1))+(INDEX($M$11:$M$12,MATCH(($B$4+G107),$L$11:$L$12,1)+1)-INDEX($M$11:$M$12,MATCH(($B$4+G107),$L$11:$L$12,1)))*(($B$4+G107)-INDEX($L$11:$L$12,MATCH(($B$4+G107),$L$11:$L$12,1)))/(INDEX($L$11:$L$12,MATCH(($B$4+G107),$L$11:$L$12,1)+1)-INDEX($L$11:$L$12,MATCH(($B$4+G107),$L$11:$L$12,1)))))),1) -> 1
A108: =$B$32+0.125+48*0.25 -> 35.235 | B108: =IF(A108<$B$31,1,0) -> 1 | C108: =IF($B$7="Oui",1+((IF(($B$4+A108)<=$I$11,$J$11,IF(($B$4+A108)>=$I$33,$J$33,INDEX($J$11:$J$33,MATCH(($B$4+A108),$I$11:$I$33,1))+(INDEX($J$11:$J$33,MATCH(($B$4+A108),$I$11:$I$33,1)+1)-INDEX($J$11:$J$33,MATCH(($B$4+A108),$I$11:$I$33,1)))*(($B$4+A108)-INDEX($I$11:$I$33,MATCH(($B$4+A108),$I$11:$I$33,1)))/(INDEX($I$11:$I$33,MATCH(($B$4+A108),$I$11:$I$33,1)+1)-INDEX($I$11:$I$33,MATCH(($B$4+A108),$I$11:$I$33,1))))))-(IF(($B$4+A108)<=$L$11,$M$11,IF(($B$4+A108)>=$L$12,$M$12,INDEX($M$11:$M$12,MATCH(($B$4+A108),$L$11:$L$12,1))+(INDEX($M$11:$M$12,MATCH(($B$4+A108),$L$11:$L$12,1)+1)-INDEX($M$11:$M$12,MATCH(($B$4+A108),$L$11:$L$12,1)))*(($B$4+A108)-INDEX($L$11:$L$12,MATCH(($B$4+A108),$L$11:$L$12,1)))/(INDEX($L$11:$L$12,MATCH(($B$4+A108),$L$11:$L$12,1)+1)-INDEX($L$11:$L$12,MATCH(($B$4+A108),$L$11:$L$12,1)))))))/(1-(IF(($B$4+A108)<=$I$11,$J$11,IF(($B$4+A108)>=$I$33,$J$33,INDEX($J$11:$J$33,MATCH(($B$4+A108),$I$11:$I$33,1))+(INDEX($J$11:$J$33,MATCH(($B$4+A108),$I$11:$I$33,1)+1)-INDEX($J$11:$J$33,MATCH(($B$4+A108),$I$11:$I$33,1)))*(($B$4+A108)-INDEX($I$11:$I$33,MATCH(($B$4+A108),$I$11:$I$33,1)))/(INDEX($I$11:$I$33,MATCH(($B$4+A108),$I$11:$I$33,1)+1)-INDEX($I$11:$I$33,MATCH(($B$4+A108),$I$11:$I$33,1))))))),1) -> 1 | D108: =B108*(1+$B$30)^(-A108) -> 0.65410917 | E108: =B108*C108*(1+$B$5)^(-A108) -> 1 | G108: =$B$31+0.125+48*0.25 -> 74.565 | H108: =IF(G108<$B$33,1,0) -> 1 | I108: =H108*(1-$B$6)^(G108-$B$31)*(1+$B$30)^(-G108) -> 0.36053891 | J108: =H108*(1-$B$6)^(G108-$B$31)*L108*(1+$B$5)^(-G108) -> 0.88527201 | L108: =IF($B$7="Oui",1-(IF(($B$4+G108)<=$L$11,$M$11,IF(($B$4+G108)>=$L$12,$M$12,INDEX($M$11:$M$12,MATCH(($B$4+G108),$L$11:$L$12,1))+(INDEX($M$11:$M$12,MATCH(($B$4+G108),$L$11:$L$12,1)+1)-INDEX($M$11:$M$12,MATCH(($B$4+G108),$L$11:$L$12,1)))*(($B$4+G108)-INDEX($L$11:$L$12,MATCH(($B$4+G108),$L$11:$L$12,1)))/(INDEX($L$11:$L$12,MATCH(($B$4+G108),$L$11:$L$12,1)+1)-INDEX($L$11:$L$12,MATCH(($B$4+G108),$L$11:$L$12,1)))))),1) -> 1
A109: =$B$32+0.125+49*0.25 -> 35.485 | B109: =IF(A109<$B$31,1,0) -> 1 | C109: =IF($B$7="Oui",1+((IF(($B$4+A109)<=$I$11,$J$11,IF(($B$4+A109)>=$I$33,$J$33,INDEX($J$11:$J$33,MATCH(($B$4+A109),$I$11:$I$33,1))+(INDEX($J$11:$J$33,MATCH(($B$4+A109),$I$11:$I$33,1)+1)-INDEX($J$11:$J$33,MATCH(($B$4+A109),$I$11:$I$33,1)))*(($B$4+A109)-INDEX($I$11:$I$33,MATCH(($B$4+A109),$I$11:$I$33,1)))/(INDEX($I$11:$I$33,MATCH(($B$4+A109),$I$11:$I$33,1)+1)-INDEX($I$11:$I$33,MATCH(($B$4+A109),$I$11:$I$33,1))))))-(IF(($B$4+A109)<=$L$11,$M$11,IF(($B$4+A109)>=$L$12,$M$12,INDEX($M$11:$M$12,MATCH(($B$4+A109),$L$11:$L$12,1))+(INDEX($M$11:$M$12,MATCH(($B$4+A109),$L$11:$L$12,1)+1)-INDEX($M$11:$M$12,MATCH(($B$4+A109),$L$11:$L$12,1)))*(($B$4+A109)-INDEX($L$11:$L$12,MATCH(($B$4+A109),$L$11:$L$12,1)))/(INDEX($L$11:$L$12,MATCH(($B$4+A109),$L$11:$L$12,1)+1)-INDEX($L$11:$L$12,MATCH(($B$4+A109),$L$11:$L$12,1)))))))/(1-(IF(($B$4+A109)<=$I$11,$J$11,IF(($B$4+A109)>=$I$33,$J$33,INDEX($J$11:$J$33,MATCH(($B$4+A109),$I$11:$I$33,1))+(INDEX($J$11:$J$33,MATCH(($B$4+A109),$I$11:$I$33,1)+1)-INDEX($J$11:$J$33,MATCH(($B$4+A109),$I$11:$I$33,1)))*(($B$4+A109)-INDEX($I$11:$I$33,MATCH(($B$4+A109),$I$11:$I$33,1)))/(INDEX($I$11:$I$33,MATCH(($B$4+A109),$I$11:$I$33,1)+1)-INDEX($I$11:$I$33,MATCH(($B$4+A109),$I$11:$I$33,1))))))),1) -> 1 | D109: =B109*(1+$B$30)^(-A109) -> 0.6521421 | E109: =B109*C109*(1+$B$5)^(-A109) -> 1 | G109: =$B$31+0.125+49*0.25 -> 74.815 | H109: =IF(G109<$B$33,1,0) -> 1 | I109: =H109*(1-$B$6)^(G109-$B$31)*(1+$B$30)^(-G109) -> 0.35855266 | J109: =H109*(1-$B$6)^(G109-$B$31)*L109*(1+$B$5)^(-G109) -> 0.88305048 | L109: =IF($B$7="Oui",1-(IF(($B$4+G109)<=$L$11,$M$11,IF(($B$4+G109)>=$L$12,$M$12,INDEX($M$11:$M$12,MATCH(($B$4+G109),$L$11:$L$12,1))+(INDEX($M$11:$M$12,MATCH(($B$4+G109),$L$11:$L$12,1)+1)-INDEX($M$11:$M$12,MATCH(($B$4+G109),$L$11:$L$12,1)))*(($B$4+G109)-INDEX($L$11:$L$12,MATCH(($B$4+G109),$L$11:$L$12,1)))/(INDEX($L$11:$L$12,MATCH(($B$4+G109),$L$11:$L$12,1)+1)-INDEX($L$11:$L$12,MATCH(($B$4+G109),$L$11:$L$12,1)))))),1) -> 1
A110: =$B$32+0.125+50*0.25 -> 35.735 | B110: =IF(A110<$B$31,1,0) -> 1 | C110: =IF($B$7="Oui",1+((IF(($B$4+A110)<=$I$11,$J$11,IF(($B$4+A110)>=$I$33,$J$33,INDEX($J$11:$J$33,MATCH(($B$4+A110),$I$11:$I$33,1))+(INDEX($J$11:$J$33,MATCH(($B$4+A110),$I$11:$I$33,1)+1)-INDEX($J$11:$J$33,MATCH(($B$4+A110),$I$11:$I$33,1)))*(($B$4+A110)-INDEX($I$11:$I$33,MATCH(($B$4+A110),$I$11:$I$33,1)))/(INDEX($I$11:$I$33,MATCH(($B$4+A110),$I$11:$I$33,1)+1)-INDEX($I$11:$I$33,MATCH(($B$4+A110),$I$11:$I$33,1))))))-(IF(($B$4+A110)<=$L$11,$M$11,IF(($B$4+A110)>=$L$12,$M$12,INDEX($M$11:$M$12,MATCH(($B$4+A110),$L$11:$L$12,1))+(INDEX($M$11:$M$12,MATCH(($B$4+A110),$L$11:$L$12,1)+1)-INDEX($M$11:$M$12,MATCH(($B$4+A110),$L$11:$L$12,1)))*(($B$4+A110)-INDEX($L$11:$L$12,MATCH(($B$4+A110),$L$11:$L$12,1)))/(INDEX($L$11:$L$12,MATCH(($B$4+A110),$L$11:$L$12,1)+1)-INDEX($L$11:$L$12,MATCH(($B$4+A110),$L$11:$L$12,1)))))))/(1-(IF(($B$4+A110)<=$I$11,$J$11,IF(($B$4+A110)>=$I$33,$J$33,INDEX($J$11:$J$33,MATCH(($B$4+A110),$I$11:$I$33,1))+(INDEX($J$11:$J$33,MATCH(($B$4+A110),$I$11:$I$33,1)+1)-INDEX($J$11:$J$33,MATCH(($B$4+A110),$I$11:$I$33,1)))*(($B$4+A110)-INDEX($I$11:$I$33,MATCH(($B$4+A110),$I$11:$I$33,1)))/(INDEX($I$11:$I$33,MATCH(($B$4+A110),$I$11:$I$33,1)+1)-INDEX($I$11:$I$33,MATCH(($B$4+A110),$I$11:$I$33,1))))))),1) -> 1 | D110: =B110*(1+$B$30)^(-A110) -> 0.65018094 | E110: =B110*C110*(1+$B$5)^(-A110) -> 1 | G110: =$B$31+0.125+50*0.25 -> 75.065 | H110: =IF(G110<$B$33,1,0) -> 1 | I110: =H110*(1-$B$6)^(G110-$B$31)*(1+$B$30)^(-G110) -> 0.35657734 | J110: =H110*(1-$B$6)^(G110-$B$31)*L110*(1+$B$5)^(-G110) -> 0.88083453 | L110: =IF($B$7="Oui",1-(IF(($B$4+G110)<=$L$11,$M$11,IF(($B$4+G110)>=$L$12,$M$12,INDEX($M$11:$M$12,MATCH(($B$4+G110),$L$11:$L$12,1))+(INDEX($M$11:$M$12,MATCH(($B$4+G110),$L$11:$L$12,1)+1)-INDEX($M$11:$M$12,MATCH(($B$4+G110),$L$11:$L$12,1)))*(($B$4+G110)-INDEX($L$11:$L$12,MATCH(($B$4+G110),$L$11:$L$12,1)))/(INDEX($L$11:$L$12,MATCH(($B$4+G110),$L$11:$L$12,1)+1)-INDEX($L$11:$L$12,MATCH(($B$4+G110),$L$11:$L$12,1)))))),1) -> 1
A111: =$B$32+0.125+51*0.25 -> 35.985 | B111: =IF(A111<$B$31,1,0) -> 1 | C111: =IF($B$7="Oui",1+((IF(($B$4+A111)<=$I$11,$J$11,IF(($B$4+A111)>=$I$33,$J$33,INDEX($J$11:$J$33,MATCH(($B$4+A111),$I$11:$I$33,1))+(INDEX($J$11:$J$33,MATCH(($B$4+A111),$I$11:$I$33,1)+1)-INDEX($J$11:$J$33,MATCH(($B$4+A111),$I$11:$I$33,1)))*(($B$4+A111)-INDEX($I$11:$I$33,MATCH(($B$4+A111),$I$11:$I$33,1)))/(INDEX($I$11:$I$33,MATCH(($B$4+A111),$I$11:$I$33,1)+1)-INDEX($I$11:$I$33,MATCH(($B$4+A111),$I$11:$I$33,1))))))-(IF(($B$4+A111)<=$L$11,$M$11,IF(($B$4+A111)>=$L$12,$M$12,INDEX($M$11:$M$12,MATCH(($B$4+A111),$L$11:$L$12,1))+(INDEX($M$11:$M$12,MATCH(($B$4+A111),$L$11:$L$12,1)+1)-INDEX($M$11:$M$12,MATCH(($B$4+A111),$L$11:$L$12,1)))*(($B$4+A111)-INDEX($L$11:$L$12,MATCH(($B$4+A111),$L$11:$L$12,1)))/(INDEX($L$11:$L$12,MATCH(($B$4+A111),$L$11:$L$12,1)+1)-INDEX($L$11:$L$12,MATCH(($B$4+A111),$L$11:$L$12,1)))))))/(1-(IF(($B$4+A111)<=$I$11,$J$11,IF(($B$4+A111)>=$I$33,$J$33,INDEX($J$11:$J$33,MATCH(($B$4+A111),$I$11:$I$33,1))+(INDEX($J$11:$J$33,MATCH(($B$4+A111),$I$11:$I$33,1)+1)-INDEX($J$11:$J$33,MATCH(($B$4+A111),$I$11:$I$33,1)))*(($B$4+A111)-INDEX($I$11:$I$33,MATCH(($B$4+A111),$I$11:$I$33,1)))/(INDEX($I$11:$I$33,MATCH(($B$4+A111),$I$11:$I$33,1)+1)-INDEX($I$11:$I$33,MATCH(($B$4+A111),$I$11:$I$33,1))))))),1) -> 1 | D111: =B111*(1+$B$30)^(-A111) -> 0.64822568 | E111: =B111*C111*(1+$B$5)^(-A111) -> 1 | G111: =$B$31+0.125+51*0.25 -> 75.315 | H111: =IF(G111<$B$33,1,0) -> 1 | I111: =H111*(1-$B$6)^(G111-$B$31)*(1+$B$30)^(-G111) -> 0.35461291 | J111: =H111*(1-$B$6)^(G111-$B$31)*L111*(1+$B$5)^(-G111) -> 0.87862414 | L111: =IF($B$7="Oui",1-(IF(($B$4+G111)<=$L$11,$M$11,IF(($B$4+G111)>=$L$12,$M$12,INDEX($M$11:$M$12,MATCH(($B$4+G111),$L$11:$L$12,1))+(INDEX($M$11:$M$12,MATCH(($B$4+G111),$L$11:$L$12,1)+1)-INDEX($M$11:$M$12,MATCH(($B$4+G111),$L$11:$L$12,1)))*(($B$4+G111)-INDEX($L$11:$L$12,MATCH(($B$4+G111),$L$11:$L$12,1)))/(INDEX($L$11:$L$12,MATCH(($B$4+G111),$L$11:$L$12,1)+1)-INDEX($L$11:$L$12,MATCH(($B$4+G111),$L$11:$L$12,1)))))),1) -> 1
A112: =$B$32+0.125+52*0.25 -> 36.235 | B112: =IF(A112<$B$31,1,0) -> 1 | C112: =IF($B$7="Oui",1+((IF(($B$4+A112)<=$I$11,$J$11,IF(($B$4+A112)>=$I$33,$J$33,INDEX($J$11:$J$33,MATCH(($B$4+A112),$I$11:$I$33,1))+(INDEX($J$11:$J$33,MATCH(($B$4+A112),$I$11:$I$33,1)+1)-INDEX($J$11:$J$33,MATCH(($B$4+A112),$I$11:$I$33,1)))*(($B$4+A112)-INDEX($I$11:$I$33,MATCH(($B$4+A112),$I$11:$I$33,1)))/(INDEX($I$11:$I$33,MATCH(($B$4+A112),$I$11:$I$33,1)+1)-INDEX($I$11:$I$33,MATCH(($B$4+A112),$I$11:$I$33,1))))))-(IF(($B$4+A112)<=$L$11,$M$11,IF(($B$4+A112)>=$L$12,$M$12,INDEX($M$11:$M$12,MATCH(($B$4+A112),$L$11:$L$12,1))+(INDEX($M$11:$M$12,MATCH(($B$4+A112),$L$11:$L$12,1)+1)-INDEX($M$11:$M$12,MATCH(($B$4+A112),$L$11:$L$12,1)))*(($B$4+A112)-INDEX($L$11:$L$12,MATCH(($B$4+A112),$L$11:$L$12,1)))/(INDEX($L$11:$L$12,MATCH(($B$4+A112),$L$11:$L$12,1)+1)-INDEX($L$11:$L$12,MATCH(($B$4+A112),$L$11:$L$12,1)))))))/(1-(IF(($B$4+A112)<=$I$11,$J$11,IF(($B$4+A112)>=$I$33,$J$33,INDEX($J$11:$J$33,MATCH(($B$4+A112),$I$11:$I$33,1))+(INDEX($J$11:$J$33,MATCH(($B$4+A112),$I$11:$I$33,1)+1)-INDEX($J$11:$J$33,MATCH(($B$4+A112),$I$11:$I$33,1)))*(($B$4+A112)-INDEX($I$11:$I$33,MATCH(($B$4+A112),$I$11:$I$33,1)))/(INDEX($I$11:$I$33,MATCH(($B$4+A112),$I$11:$I$33,1)+1)-INDEX($I$11:$I$33,MATCH(($B$4+A112),$I$11:$I$33,1))))))),1) -> 1 | D112: =B112*(1+$B$30)^(-A112) -> 0.6462763 | E112: =B112*C112*(1+$B$5)^(-A112) -> 1 | G112: =$B$31+0.125+52*0.25 -> 75.565 | H112: =IF(G112<$B$33,1,0) -> 1 | I112: =H112*(1-$B$6)^(G112-$B$31)*(1+$B$30)^(-G112) -> 0.35265929 | J112: =H112*(1-$B$6)^(G112-$B$31)*L112*(1+$B$5)^(-G112) -> 0.87641929 | L112: =IF($B$7="Oui",1-(IF(($B$4+G112)<=$L$11,$M$11,IF(($B$4+G112)>=$L$12,$M$12,INDEX($M$11:$M$12,MATCH(($B$4+G112),$L$11:$L$12,1))+(INDEX($M$11:$M$12,MATCH(($B$4+G112),$L$11:$L$12,1)+1)-INDEX($M$11:$M$12,MATCH(($B$4+G112),$L$11:$L$12,1)))*(($B$4+G112)-INDEX($L$11:$L$12,MATCH(($B$4+G112),$L$11:$L$12,1)))/(INDEX($L$11:$L$12,MATCH(($B$4+G112),$L$11:$L$12,1)+1)-INDEX($L$11:$L$12,MATCH(($B$4+G112),$L$11:$L$12,1)))))),1) -> 1
A113: =$B$32+0.125+53*0.25 -> 36.485 | B113: =IF(A113<$B$31,1,0) -> 1 | C113: =IF($B$7="Oui",1+((IF(($B$4+A113)<=$I$11,$J$11,IF(($B$4+A113)>=$I$33,$J$33,INDEX($J$11:$J$33,MATCH(($B$4+A113),$I$11:$I$33,1))+(INDEX($J$11:$J$33,MATCH(($B$4+A113),$I$11:$I$33,1)+1)-INDEX($J$11:$J$33,MATCH(($B$4+A113),$I$11:$I$33,1)))*(($B$4+A113)-INDEX($I$11:$I$33,MATCH(($B$4+A113),$I$11:$I$33,1)))/(INDEX($I$11:$I$33,MATCH(($B$4+A113),$I$11:$I$33,1)+1)-INDEX($I$11:$I$33,MATCH(($B$4+A113),$I$11:$I$33,1))))))-(IF(($B$4+A113)<=$L$11,$M$11,IF(($B$4+A113)>=$L$12,$M$12,INDEX($M$11:$M$12,MATCH(($B$4+A113),$L$11:$L$12,1))+(INDEX($M$11:$M$12,MATCH(($B$4+A113),$L$11:$L$12,1)+1)-INDEX($M$11:$M$12,MATCH(($B$4+A113),$L$11:$L$12,1)))*(($B$4+A113)-INDEX($L$11:$L$12,MATCH(($B$4+A113),$L$11:$L$12,1)))/(INDEX($L$11:$L$12,MATCH(($B$4+A113),$L$11:$L$12,1)+1)-INDEX($L$11:$L$12,MATCH(($B$4+A113),$L$11:$L$12,1)))))))/(1-(IF(($B$4+A113)<=$I$11,$J$11,IF(($B$4+A113)>=$I$33,$J$33,INDEX($J$11:$J$33,MATCH(($B$4+A113),$I$11:$I$33,1))+(INDEX($J$11:$J$33,MATCH(($B$4+A113),$I$11:$I$33,1)+1)-INDEX($J$11:$J$33,MATCH(($B$4+A113),$I$11:$I$33,1)))*(($B$4+A113)-INDEX($I$11:$I$33,MATCH(($B$4+A113),$I$11:$I$33,1)))/(INDEX($I$11:$I$33,MATCH(($B$4+A113),$I$11:$I$33,1)+1)-INDEX($I$11:$I$33,MATCH(($B$4+A113),$I$11:$I$33,1))))))),1) -> 1 | D113: =B113*(1+$B$30)^(-A113) -> 0.64433279 | E113: =B113*C113*(1+$B$5)^(-A113) -> 1 | G113: =$B$31+0.125+53*0.25 -> 75.815 | H113: =IF(G113<$B$33,1,0) -> 1 | I113: =H113*(1-$B$6)^(G113-$B$31)*(1+$B$30)^(-G113) -> 0.35071645 | J113: =H113*(1-$B$6)^(G113-$B$31)*L113*(1+$B$5)^(-G113) -> 0.87421998 | L113: =IF($B$7="Oui",1-(IF(($B$4+G113)<=$L$11,$M$11,IF(($B$4+G113)>=$L$12,$M$12,INDEX($M$11:$M$12,MATCH(($B$4+G113),$L$11:$L$12,1))+(INDEX($M$11:$M$12,MATCH(($B$4+G113),$L$11:$L$12,1)+1)-INDEX($M$11:$M$12,MATCH(($B$4+G113),$L$11:$L$12,1)))*(($B$4+G113)-INDEX($L$11:$L$12,MATCH(($B$4+G113),$L$11:$L$12,1)))/(INDEX($L$11:$L$12,MATCH(($B$4+G113),$L$11:$L$12,1)+1)-INDEX($L$11:$L$12,MATCH(($B$4+G113),$L$11:$L$12,1)))))),1) -> 1
A114: =$B$32+0.125+54*0.25 -> 36.735 | B114: =IF(A114<$B$31,1,0) -> 1 | C114: =IF($B$7="Oui",1+((IF(($B$4+A114)<=$I$11,$J$11,IF(($B$4+A114)>=$I$33,$J$33,INDEX($J$11:$J$33,MATCH(($B$4+A114),$I$11:$I$33,1))+(INDEX($J$11:$J$33,MATCH(($B$4+A114),$I$11:$I$33,1)+1)-INDEX($J$11:$J$33,MATCH(($B$4+A114),$I$11:$I$33,1)))*(($B$4+A114)-INDEX($I$11:$I$33,MATCH(($B$4+A114),$I$11:$I$33,1)))/(INDEX($I$11:$I$33,MATCH(($B$4+A114),$I$11:$I$33,1)+1)-INDEX($I$11:$I$33,MATCH(($B$4+A114),$I$11:$I$33,1))))))-(IF(($B$4+A114)<=$L$11,$M$11,IF(($B$4+A114)>=$L$12,$M$12,INDEX($M$11:$M$12,MATCH(($B$4+A114),$L$11:$L$12,1))+(INDEX($M$11:$M$12,MATCH(($B$4+A114),$L$11:$L$12,1)+1)-INDEX($M$11:$M$12,MATCH(($B$4+A114),$L$11:$L$12,1)))*(($B$4+A114)-INDEX($L$11:$L$12,MATCH(($B$4+A114),$L$11:$L$12,1)))/(INDEX($L$11:$L$12,MATCH(($B$4+A114),$L$11:$L$12,1)+1)-INDEX($L$11:$L$12,MATCH(($B$4+A114),$L$11:$L$12,1)))))))/(1-(IF(($B$4+A114)<=$I$11,$J$11,IF(($B$4+A114)>=$I$33,$J$33,INDEX($J$11:$J$33,MATCH(($B$4+A114),$I$11:$I$33,1))+(INDEX($J$11:$J$33,MATCH(($B$4+A114),$I$11:$I$33,1)+1)-INDEX($J$11:$J$33,MATCH(($B$4+A114),$I$11:$I$33,1)))*(($B$4+A114)-INDEX($I$11:$I$33,MATCH(($B$4+A114),$I$11:$I$33,1)))/(INDEX($I$11:$I$33,MATCH(($B$4+A114),$I$11:$I$33,1)+1)-INDEX($I$11:$I$33,MATCH(($B$4+A114),$I$11:$I$33,1))))))),1) -> 1 | D114: =B114*(1+$B$30)^(-A114) -> 0.64239511 | E114: =B114*C114*(1+$B$5)^(-A114) -> 1 | G114: =$B$31+0.125+54*0.25 -> 76.065 | H114: =IF(G114<$B$33,1,0) -> 1 | I114: =H114*(1-$B$6)^(G114-$B$31)*(1+$B$30)^(-G114) -> 0.3487843 | J114: =H114*(1-$B$6)^(G114-$B$31)*L114*(1+$B$5)^(-G114) -> 0.87202619 | L114: =IF($B$7="Oui",1-(IF(($B$4+G114)<=$L$11,$M$11,IF(($B$4+G114)>=$L$12,$M$12,INDEX($M$11:$M$12,MATCH(($B$4+G114),$L$11:$L$12,1))+(INDEX($M$11:$M$12,MATCH(($B$4+G114),$L$11:$L$12,1)+1)-INDEX($M$11:$M$12,MATCH(($B$4+G114),$L$11:$L$12,1)))*(($B$4+G114)-INDEX($L$11:$L$12,MATCH(($B$4+G114),$L$11:$L$12,1)))/(INDEX($L$11:$L$12,MATCH(($B$4+G114),$L$11:$L$12,1)+1)-INDEX($L$11:$L$12,MATCH(($B$4+G114),$L$11:$L$12,1)))))),1) -> 1
A115: =$B$32+0.125+55*0.25 -> 36.985 | B115: =IF(A115<$B$31,1,0) -> 1 | C115: =IF($B$7="Oui",1+((IF(($B$4+A115)<=$I$11,$J$11,IF(($B$4+A115)>=$I$33,$J$33,INDEX($J$11:$J$33,MATCH(($B$4+A115),$I$11:$I$33,1))+(INDEX($J$11:$J$33,MATCH(($B$4+A115),$I$11:$I$33,1)+1)-INDEX($J$11:$J$33,MATCH(($B$4+A115),$I$11:$I$33,1)))*(($B$4+A115)-INDEX($I$11:$I$33,MATCH(($B$4+A115),$I$11:$I$33,1)))/(INDEX($I$11:$I$33,MATCH(($B$4+A115),$I$11:$I$33,1)+1)-INDEX($I$11:$I$33,MATCH(($B$4+A115),$I$11:$I$33,1))))))-(IF(($B$4+A115)<=$L$11,$M$11,IF(($B$4+A115)>=$L$12,$M$12,INDEX($M$11:$M$12,MATCH(($B$4+A115),$L$11:$L$12,1))+(INDEX($M$11:$M$12,MATCH(($B$4+A115),$L$11:$L$12,1)+1)-INDEX($M$11:$M$12,MATCH(($B$4+A115),$L$11:$L$12,1)))*(($B$4+A115)-INDEX($L$11:$L$12,MATCH(($B$4+A115),$L$11:$L$12,1)))/(INDEX($L$11:$L$12,MATCH(($B$4+A115),$L$11:$L$12,1)+1)-INDEX($L$11:$L$12,MATCH(($B$4+A115),$L$11:$L$12,1)))))))/(1-(IF(($B$4+A115)<=$I$11,$J$11,IF(($B$4+A115)>=$I$33,$J$33,INDEX($J$11:$J$33,MATCH(($B$4+A115),$I$11:$I$33,1))+(INDEX($J$11:$J$33,MATCH(($B$4+A115),$I$11:$I$33,1)+1)-INDEX($J$11:$J$33,MATCH(($B$4+A115),$I$11:$I$33,1)))*(($B$4+A115)-INDEX($I$11:$I$33,MATCH(($B$4+A115),$I$11:$I$33,1)))/(INDEX($I$11:$I$33,MATCH(($B$4+A115),$I$11:$I$33,1)+1)-INDEX($I$11:$I$33,MATCH(($B$4+A115),$I$11:$I$33,1))))))),1) -> 1 | D115: =B115*(1+$B$30)^(-A115) -> 0.64046327 | E115: =B115*C115*(1+$B$5)^(-A115) -> 1 | G115: =$B$31+0.125+55*0.25 -> 76.315 | H115: =IF(G115<$B$33,1,0) -> 1 | I115: =H115*(1-$B$6)^(G115-$B$31)*(1+$B$30)^(-G115) -> 0.3468628 | J115: =H115*(1-$B$6)^(G115-$B$31)*L115*(1+$B$5)^(-G115) -> 0.8698379 | L115: =IF($B$7="Oui",1-(IF(($B$4+G115)<=$L$11,$M$11,IF(($B$4+G115)>=$L$12,$M$12,INDEX($M$11:$M$12,MATCH(($B$4+G115),$L$11:$L$12,1))+(INDEX($M$11:$M$12,MATCH(($B$4+G115),$L$11:$L$12,1)+1)-INDEX($M$11:$M$12,MATCH(($B$4+G115),$L$11:$L$12,1)))*(($B$4+G115)-INDEX($L$11:$L$12,MATCH(($B$4+G115),$L$11:$L$12,1)))/(INDEX($L$11:$L$12,MATCH(($B$4+G115),$L$11:$L$12,1)+1)-INDEX($L$11:$L$12,MATCH(($B$4+G115),$L$11:$L$12,1)))))),1) -> 1
A116: =$B$32+0.125+56*0.25 -> 37.235 | B116: =IF(A116<$B$31,1,0) -> 1 | C116: =IF($B$7="Oui",1+((IF(($B$4+A116)<=$I$11,$J$11,IF(($B$4+A116)>=$I$33,$J$33,INDEX($J$11:$J$33,MATCH(($B$4+A116),$I$11:$I$33,1))+(INDEX($J$11:$J$33,MATCH(($B$4+A116),$I$11:$I$33,1)+1)-INDEX($J$11:$J$33,MATCH(($B$4+A116),$I$11:$I$33,1)))*(($B$4+A116)-INDEX($I$11:$I$33,MATCH(($B$4+A116),$I$11:$I$33,1)))/(INDEX($I$11:$I$33,MATCH(($B$4+A116),$I$11:$I$33,1)+1)-INDEX($I$11:$I$33,MATCH(($B$4+A116),$I$11:$I$33,1))))))-(IF(($B$4+A116)<=$L$11,$M$11,IF(($B$4+A116)>=$L$12,$M$12,INDEX($M$11:$M$12,MATCH(($B$4+A116),$L$11:$L$12,1))+(INDEX($M$11:$M$12,MATCH(($B$4+A116),$L$11:$L$12,1)+1)-INDEX($M$11:$M$12,MATCH(($B$4+A116),$L$11:$L$12,1)))*(($B$4+A116)-INDEX($L$11:$L$12,MATCH(($B$4+A116),$L$11:$L$12,1)))/(INDEX($L$11:$L$12,MATCH(($B$4+A116),$L$11:$L$12,1)+1)-INDEX($L$11:$L$12,MATCH(($B$4+A116),$L$11:$L$12,1)))))))/(1-(IF(($B$4+A116)<=$I$11,$J$11,IF(($B$4+A116)>=$I$33,$J$33,INDEX($J$11:$J$33,MATCH(($B$4+A116),$I$11:$I$33,1))+(INDEX($J$11:$J$33,MATCH(($B$4+A116),$I$11:$I$33,1)+1)-INDEX($J$11:$J$33,MATCH(($B$4+A116),$I$11:$I$33,1)))*(($B$4+A116)-INDEX($I$11:$I$33,MATCH(($B$4+A116),$I$11:$I$33,1)))/(INDEX($I$11:$I$33,MATCH(($B$4+A116),$I$11:$I$33,1)+1)-INDEX($I$11:$I$33,MATCH(($B$4+A116),$I$11:$I$33,1))))))),1) -> 1 | D116: =B116*(1+$B$30)^(-A116) -> 0.63853723 | E116: =B116*C116*(1+$B$5)^(-A116) -> 1 | G116: =$B$31+0.125+56*0.25 -> 76.565 | H116: =IF(G116<$B$33,1,0) -> 1 | I116: =H116*(1-$B$6)^(G116-$B$31)*(1+$B$30)^(-G116) -> 0.34495188 | J116: =H116*(1-$B$6)^(G116-$B$31)*L116*(1+$B$5)^(-G116) -> 0.8676551 | L116: =IF($B$7="Oui",1-(IF(($B$4+G116)<=$L$11,$M$11,IF(($B$4+G116)>=$L$12,$M$12,INDEX($M$11:$M$12,MATCH(($B$4+G116),$L$11:$L$12,1))+(INDEX($M$11:$M$12,MATCH(($B$4+G116),$L$11:$L$12,1)+1)-INDEX($M$11:$M$12,MATCH(($B$4+G116),$L$11:$L$12,1)))*(($B$4+G116)-INDEX($L$11:$L$12,MATCH(($B$4+G116),$L$11:$L$12,1)))/(INDEX($L$11:$L$12,MATCH(($B$4+G116),$L$11:$L$12,1)+1)-INDEX($L$11:$L$12,MATCH(($B$4+G116),$L$11:$L$12,1)))))),1) -> 1
A117: =$B$32+0.125+57*0.25 -> 37.485 | B117: =IF(A117<$B$31,1,0) -> 1 | C117: =IF($B$7="Oui",1+((IF(($B$4+A117)<=$I$11,$J$11,IF(($B$4+A117)>=$I$33,$J$33,INDEX($J$11:$J$33,MATCH(($B$4+A117),$I$11:$I$33,1))+(INDEX($J$11:$J$33,MATCH(($B$4+A117),$I$11:$I$33,1)+1)-INDEX($J$11:$J$33,MATCH(($B$4+A117),$I$11:$I$33,1)))*(($B$4+A117)-INDEX($I$11:$I$33,MATCH(($B$4+A117),$I$11:$I$33,1)))/(INDEX($I$11:$I$33,MATCH(($B$4+A117),$I$11:$I$33,1)+1)-INDEX($I$11:$I$33,MATCH(($B$4+A117),$I$11:$I$33,1))))))-(IF(($B$4+A117)<=$L$11,$M$11,IF(($B$4+A117)>=$L$12,$M$12,INDEX($M$11:$M$12,MATCH(($B$4+A117),$L$11:$L$12,1))+(INDEX($M$11:$M$12,MATCH(($B$4+A117),$L$11:$L$12,1)+1)-INDEX($M$11:$M$12,MATCH(($B$4+A117),$L$11:$L$12,1)))*(($B$4+A117)-INDEX($L$11:$L$12,MATCH(($B$4+A117),$L$11:$L$12,1)))/(INDEX($L$11:$L$12,MATCH(($B$4+A117),$L$11:$L$12,1)+1)-INDEX($L$11:$L$12,MATCH(($B$4+A117),$L$11:$L$12,1)))))))/(1-(IF(($B$4+A117)<=$I$11,$J$11,IF(($B$4+A117)>=$I$33,$J$33,INDEX($J$11:$J$33,MATCH(($B$4+A117),$I$11:$I$33,1))+(INDEX($J$11:$J$33,MATCH(($B$4+A117),$I$11:$I$33,1)+1)-INDEX($J$11:$J$33,MATCH(($B$4+A117),$I$11:$I$33,1)))*(($B$4+A117)-INDEX($I$11:$I$33,MATCH(($B$4+A117),$I$11:$I$33,1)))/(INDEX($I$11:$I$33,MATCH(($B$4+A117),$I$11:$I$33,1)+1)-INDEX($I$11:$I$33,MATCH(($B$4+A117),$I$11:$I$33,1))))))),1) -> 1 | D117: =B117*(1+$B$30)^(-A117) -> 0.63661699 | E117: =B117*C117*(1+$B$5)^(-A117) -> 1 | G117: =$B$31+0.125+57*0.25 -> 76.815 | H117: =IF(G117<$B$33,1,0) -> 1 | I117: =H117*(1-$B$6)^(G117-$B$31)*(1+$B$30)^(-G117) -> 0.3430515 | J117: =H117*(1-$B$6)^(G117-$B$31)*L117*(1+$B$5)^(-G117) -> 0.86547778 | L117: =IF($B$7="Oui",1-(IF(($B$4+G117)<=$L$11,$M$11,IF(($B$4+G117)>=$L$12,$M$12,INDEX($M$11:$M$12,MATCH(($B$4+G117),$L$11:$L$12,1))+(INDEX($M$11:$M$12,MATCH(($B$4+G117),$L$11:$L$12,1)+1)-INDEX($M$11:$M$12,MATCH(($B$4+G117),$L$11:$L$12,1)))*(($B$4+G117)-INDEX($L$11:$L$12,MATCH(($B$4+G117),$L$11:$L$12,1)))/(INDEX($L$11:$L$12,MATCH(($B$4+G117),$L$11:$L$12,1)+1)-INDEX($L$11:$L$12,MATCH(($B$4+G117),$L$11:$L$12,1)))))),1) -> 1
A118: =$B$32+0.125+58*0.25 -> 37.735 | B118: =IF(A118<$B$31,1,0) -> 1 | C118: =IF($B$7="Oui",1+((IF(($B$4+A118)<=$I$11,$J$11,IF(($B$4+A118)>=$I$33,$J$33,INDEX($J$11:$J$33,MATCH(($B$4+A118),$I$11:$I$33,1))+(INDEX($J$11:$J$33,MATCH(($B$4+A118),$I$11:$I$33,1)+1)-INDEX($J$11:$J$33,MATCH(($B$4+A118),$I$11:$I$33,1)))*(($B$4+A118)-INDEX($I$11:$I$33,MATCH(($B$4+A118),$I$11:$I$33,1)))/(INDEX($I$11:$I$33,MATCH(($B$4+A118),$I$11:$I$33,1)+1)-INDEX($I$11:$I$33,MATCH(($B$4+A118),$I$11:$I$33,1))))))-(IF(($B$4+A118)<=$L$11,$M$11,IF(($B$4+A118)>=$L$12,$M$12,INDEX($M$11:$M$12,MATCH(($B$4+A118),$L$11:$L$12,1))+(INDEX($M$11:$M$12,MATCH(($B$4+A118),$L$11:$L$12,1)+1)-INDEX($M$11:$M$12,MATCH(($B$4+A118),$L$11:$L$12,1)))*(($B$4+A118)-INDEX($L$11:$L$12,MATCH(($B$4+A118),$L$11:$L$12,1)))/(INDEX($L$11:$L$12,MATCH(($B$4+A118),$L$11:$L$12,1)+1)-INDEX($L$11:$L$12,MATCH(($B$4+A118),$L$11:$L$12,1)))))))/(1-(IF(($B$4+A118)<=$I$11,$J$11,IF(($B$4+A118)>=$I$33,$J$33,INDEX($J$11:$J$33,MATCH(($B$4+A118),$I$11:$I$33,1))+(INDEX($J$11:$J$33,MATCH(($B$4+A118),$I$11:$I$33,1)+1)-INDEX($J$11:$J$33,MATCH(($B$4+A118),$I$11:$I$33,1)))*(($B$4+A118)-INDEX($I$11:$I$33,MATCH(($B$4+A118),$I$11:$I$33,1)))/(INDEX($I$11:$I$33,MATCH(($B$4+A118),$I$11:$I$33,1)+1)-INDEX($I$11:$I$33,MATCH(($B$4+A118),$I$11:$I$33,1))))))),1) -> 1 | D118: =B118*(1+$B$30)^(-A118) -> 0.63470252 | E118: =B118*C118*(1+$B$5)^(-A118) -> 1 | G118: =$B$31+0.125+58*0.25 -> 77.065 | H118: =IF(G118<$B$33,1,0) -> 1 | I118: =H118*(1-$B$6)^(G118-$B$31)*(1+$B$30)^(-G118) -> 0.34116158 | J118: =H118*(1-$B$6)^(G118-$B$31)*L118*(1+$B$5)^(-G118) -> 0.86330592 | L118: =IF($B$7="Oui",1-(IF(($B$4+G118)<=$L$11,$M$11,IF(($B$4+G118)>=$L$12,$M$12,INDEX($M$11:$M$12,MATCH(($B$4+G118),$L$11:$L$12,1))+(INDEX($M$11:$M$12,MATCH(($B$4+G118),$L$11:$L$12,1)+1)-INDEX($M$11:$M$12,MATCH(($B$4+G118),$L$11:$L$12,1)))*(($B$4+G118)-INDEX($L$11:$L$12,MATCH(($B$4+G118),$L$11:$L$12,1)))/(INDEX($L$11:$L$12,MATCH(($B$4+G118),$L$11:$L$12,1)+1)-INDEX($L$11:$L$12,MATCH(($B$4+G118),$L$11:$L$12,1)))))),1) -> 1
A119: =$B$32+0.125+59*0.25 -> 37.985 | B119: =IF(A119<$B$31,1,0) -> 1 | C119: =IF($B$7="Oui",1+((IF(($B$4+A119)<=$I$11,$J$11,IF(($B$4+A119)>=$I$33,$J$33,INDEX($J$11:$J$33,MATCH(($B$4+A119),$I$11:$I$33,1))+(INDEX($J$11:$J$33,MATCH(($B$4+A119),$I$11:$I$33,1)+1)-INDEX($J$11:$J$33,MATCH(($B$4+A119),$I$11:$I$33,1)))*(($B$4+A119)-INDEX($I$11:$I$33,MATCH(($B$4+A119),$I$11:$I$33,1)))/(INDEX($I$11:$I$33,MATCH(($B$4+A119),$I$11:$I$33,1)+1)-INDEX($I$11:$I$33,MATCH(($B$4+A119),$I$11:$I$33,1))))))-(IF(($B$4+A119)<=$L$11,$M$11,IF(($B$4+A119)>=$L$12,$M$12,INDEX($M$11:$M$12,MATCH(($B$4+A119),$L$11:$L$12,1))+(INDEX($M$11:$M$12,MATCH(($B$4+A119),$L$11:$L$12,1)+1)-INDEX($M$11:$M$12,MATCH(($B$4+A119),$L$11:$L$12,1)))*(($B$4+A119)-INDEX($L$11:$L$12,MATCH(($B$4+A119),$L$11:$L$12,1)))/(INDEX($L$11:$L$12,MATCH(($B$4+A119),$L$11:$L$12,1)+1)-INDEX($L$11:$L$12,MATCH(($B$4+A119),$L$11:$L$12,1)))))))/(1-(IF(($B$4+A119)<=$I$11,$J$11,IF(($B$4+A119)>=$I$33,$J$33,INDEX($J$11:$J$33,MATCH(($B$4+A119),$I$11:$I$33,1))+(INDEX($J$11:$J$33,MATCH(($B$4+A119),$I$11:$I$33,1)+1)-INDEX($J$11:$J$33,MATCH(($B$4+A119),$I$11:$I$33,1)))*(($B$4+A119)-INDEX($I$11:$I$33,MATCH(($B$4+A119),$I$11:$I$33,1)))/(INDEX($I$11:$I$33,MATCH(($B$4+A119),$I$11:$I$33,1)+1)-INDEX($I$11:$I$33,MATCH(($B$4+A119),$I$11:$I$33,1))))))),1) -> 1 | D119: =B119*(1+$B$30)^(-A119) -> 0.63279381 | E119: =B119*C119*(1+$B$5)^(-A119) -> 1 | G119: =$B$31+0.125+59*0.25 -> 77.315 | H119: =IF(G119<$B$33,1,0) -> 1 | I119: =H119*(1-$B$6)^(G119-$B$31)*(1+$B$30)^(-G119) -> 0.33928207 | J119: =H119*(1-$B$6)^(G119-$B$31)*L119*(1+$B$5)^(-G119) -> 0.86113952 | L119: =IF($B$7="Oui",1-(IF(($B$4+G119)<=$L$11,$M$11,IF(($B$4+G119)>=$L$12,$M$12,INDEX($M$11:$M$12,MATCH(($B$4+G119),$L$11:$L$12,1))+(INDEX($M$11:$M$12,MATCH(($B$4+G119),$L$11:$L$12,1)+1)-INDEX($M$11:$M$12,MATCH(($B$4+G119),$L$11:$L$12,1)))*(($B$4+G119)-INDEX($L$11:$L$12,MATCH(($B$4+G119),$L$11:$L$12,1)))/(INDEX($L$11:$L$12,MATCH(($B$4+G119),$L$11:$L$12,1)+1)-INDEX($L$11:$L$12,MATCH(($B$4+G119),$L$11:$L$12,1)))))),1) -> 1
A120: =$B$32+0.125+60*0.25 -> 38.235 | B120: =IF(A120<$B$31,1,0) -> 1 | C120: =IF($B$7="Oui",1+((IF(($B$4+A120)<=$I$11,$J$11,IF(($B$4+A120)>=$I$33,$J$33,INDEX($J$11:$J$33,MATCH(($B$4+A120),$I$11:$I$33,1))+(INDEX($J$11:$J$33,MATCH(($B$4+A120),$I$11:$I$33,1)+1)-INDEX($J$11:$J$33,MATCH(($B$4+A120),$I$11:$I$33,1)))*(($B$4+A120)-INDEX($I$11:$I$33,MATCH(($B$4+A120),$I$11:$I$33,1)))/(INDEX($I$11:$I$33,MATCH(($B$4+A120),$I$11:$I$33,1)+1)-INDEX($I$11:$I$33,MATCH(($B$4+A120),$I$11:$I$33,1))))))-(IF(($B$4+A120)<=$L$11,$M$11,IF(($B$4+A120)>=$L$12,$M$12,INDEX($M$11:$M$12,MATCH(($B$4+A120),$L$11:$L$12,1))+(INDEX($M$11:$M$12,MATCH(($B$4+A120),$L$11:$L$12,1)+1)-INDEX($M$11:$M$12,MATCH(($B$4+A120),$L$11:$L$12,1)))*(($B$4+A120)-INDEX($L$11:$L$12,MATCH(($B$4+A120),$L$11:$L$12,1)))/(INDEX($L$11:$L$12,MATCH(($B$4+A120),$L$11:$L$12,1)+1)-INDEX($L$11:$L$12,MATCH(($B$4+A120),$L$11:$L$12,1)))))))/(1-(IF(($B$4+A120)<=$I$11,$J$11,IF(($B$4+A120)>=$I$33,$J$33,INDEX($J$11:$J$33,MATCH(($B$4+A120),$I$11:$I$33,1))+(INDEX($J$11:$J$33,MATCH(($B$4+A120),$I$11:$I$33,1)+1)-INDEX($J$11:$J$33,MATCH(($B$4+A120),$I$11:$I$33,1)))*(($B$4+A120)-INDEX($I$11:$I$33,MATCH(($B$4+A120),$I$11:$I$33,1)))/(INDEX($I$11:$I$33,MATCH(($B$4+A120),$I$11:$I$33,1)+1)-INDEX($I$11:$I$33,MATCH(($B$4+A120),$I$11:$I$33,1))))))),1) -> 1 | D120: =B120*(1+$B$30)^(-A120) -> 0.63089084 | E120: =B120*C120*(1+$B$5)^(-A120) -> 1 | G120: =$B$31+0.125+60*0.25 -> 77.565 | H120: =IF(G120<$B$33,1,0) -> 1 | I120: =H120*(1-$B$6)^(G120-$B$31)*(1+$B$30)^(-G120) -> 0.33741292 | J120: =H120*(1-$B$6)^(G120-$B$31)*L120*(1+$B$5)^(-G120) -> 0.85897855 | L120: =IF($B$7="Oui",1-(IF(($B$4+G120)<=$L$11,$M$11,IF(($B$4+G120)>=$L$12,$M$12,INDEX($M$11:$M$12,MATCH(($B$4+G120),$L$11:$L$12,1))+(INDEX($M$11:$M$12,MATCH(($B$4+G120),$L$11:$L$12,1)+1)-INDEX($M$11:$M$12,MATCH(($B$4+G120),$L$11:$L$12,1)))*(($B$4+G120)-INDEX($L$11:$L$12,MATCH(($B$4+G120),$L$11:$L$12,1)))/(INDEX($L$11:$L$12,MATCH(($B$4+G120),$L$11:$L$12,1)+1)-INDEX($L$11:$L$12,MATCH(($B$4+G120),$L$11:$L$12,1)))))),1) -> 1
A121: =$B$32+0.125+61*0.25 -> 38.485 | B121: =IF(A121<$B$31,1,0) -> 1 | C121: =IF($B$7="Oui",1+((IF(($B$4+A121)<=$I$11,$J$11,IF(($B$4+A121)>=$I$33,$J$33,INDEX($J$11:$J$33,MATCH(($B$4+A121),$I$11:$I$33,1))+(INDEX($J$11:$J$33,MATCH(($B$4+A121),$I$11:$I$33,1)+1)-INDEX($J$11:$J$33,MATCH(($B$4+A121),$I$11:$I$33,1)))*(($B$4+A121)-INDEX($I$11:$I$33,MATCH(($B$4+A121),$I$11:$I$33,1)))/(INDEX($I$11:$I$33,MATCH(($B$4+A121),$I$11:$I$33,1)+1)-INDEX($I$11:$I$33,MATCH(($B$4+A121),$I$11:$I$33,1))))))-(IF(($B$4+A121)<=$L$11,$M$11,IF(($B$4+A121)>=$L$12,$M$12,INDEX($M$11:$M$12,MATCH(($B$4+A121),$L$11:$L$12,1))+(INDEX($M$11:$M$12,MATCH(($B$4+A121),$L$11:$L$12,1)+1)-INDEX($M$11:$M$12,MATCH(($B$4+A121),$L$11:$L$12,1)))*(($B$4+A121)-INDEX($L$11:$L$12,MATCH(($B$4+A121),$L$11:$L$12,1)))/(INDEX($L$11:$L$12,MATCH(($B$4+A121),$L$11:$L$12,1)+1)-INDEX($L$11:$L$12,MATCH(($B$4+A121),$L$11:$L$12,1)))))))/(1-(IF(($B$4+A121)<=$I$11,$J$11,IF(($B$4+A121)>=$I$33,$J$33,INDEX($J$11:$J$33,MATCH(($B$4+A121),$I$11:$I$33,1))+(INDEX($J$11:$J$33,MATCH(($B$4+A121),$I$11:$I$33,1)+1)-INDEX($J$11:$J$33,MATCH(($B$4+A121),$I$11:$I$33,1)))*(($B$4+A121)-INDEX($I$11:$I$33,MATCH(($B$4+A121),$I$11:$I$33,1)))/(INDEX($I$11:$I$33,MATCH(($B$4+A121),$I$11:$I$33,1)+1)-INDEX($I$11:$I$33,MATCH(($B$4+A121),$I$11:$I$33,1))))))),1) -> 1 | D121: =B121*(1+$B$30)^(-A121) -> 0.62899359 | E121: =B121*C121*(1+$B$5)^(-A121) -> 1 | G121: =$B$31+0.125+61*0.25 -> 77.815 | H121: =IF(G121<$B$33,1,0) -> 1 | I121: =H121*(1-$B$6)^(G121-$B$31)*(1+$B$30)^(-G121) -> 0.33555407 | J121: =H121*(1-$B$6)^(G121-$B$31)*L121*(1+$B$5)^(-G121) -> 0.856823 | L121: =IF($B$7="Oui",1-(IF(($B$4+G121)<=$L$11,$M$11,IF(($B$4+G121)>=$L$12,$M$12,INDEX($M$11:$M$12,MATCH(($B$4+G121),$L$11:$L$12,1))+(INDEX($M$11:$M$12,MATCH(($B$4+G121),$L$11:$L$12,1)+1)-INDEX($M$11:$M$12,MATCH(($B$4+G121),$L$11:$L$12,1)))*(($B$4+G121)-INDEX($L$11:$L$12,MATCH(($B$4+G121),$L$11:$L$12,1)))/(INDEX($L$11:$L$12,MATCH(($B$4+G121),$L$11:$L$12,1)+1)-INDEX($L$11:$L$12,MATCH(($B$4+G121),$L$11:$L$12,1)))))),1) -> 1
A122: =$B$32+0.125+62*0.25 -> 38.735 | B122: =IF(A122<$B$31,1,0) -> 1 | C122: =IF($B$7="Oui",1+((IF(($B$4+A122)<=$I$11,$J$11,IF(($B$4+A122)>=$I$33,$J$33,INDEX($J$11:$J$33,MATCH(($B$4+A122),$I$11:$I$33,1))+(INDEX($J$11:$J$33,MATCH(($B$4+A122),$I$11:$I$33,1)+1)-INDEX($J$11:$J$33,MATCH(($B$4+A122),$I$11:$I$33,1)))*(($B$4+A122)-INDEX($I$11:$I$33,MATCH(($B$4+A122),$I$11:$I$33,1)))/(INDEX($I$11:$I$33,MATCH(($B$4+A122),$I$11:$I$33,1)+1)-INDEX($I$11:$I$33,MATCH(($B$4+A122),$I$11:$I$33,1))))))-(IF(($B$4+A122)<=$L$11,$M$11,IF(($B$4+A122)>=$L$12,$M$12,INDEX($M$11:$M$12,MATCH(($B$4+A122),$L$11:$L$12,1))+(INDEX($M$11:$M$12,MATCH(($B$4+A122),$L$11:$L$12,1)+1)-INDEX($M$11:$M$12,MATCH(($B$4+A122),$L$11:$L$12,1)))*(($B$4+A122)-INDEX($L$11:$L$12,MATCH(($B$4+A122),$L$11:$L$12,1)))/(INDEX($L$11:$L$12,MATCH(($B$4+A122),$L$11:$L$12,1)+1)-INDEX($L$11:$L$12,MATCH(($B$4+A122),$L$11:$L$12,1)))))))/(1-(IF(($B$4+A122)<=$I$11,$J$11,IF(($B$4+A122)>=$I$33,$J$33,INDEX($J$11:$J$33,MATCH(($B$4+A122),$I$11:$I$33,1))+(INDEX($J$11:$J$33,MATCH(($B$4+A122),$I$11:$I$33,1)+1)-INDEX($J$11:$J$33,MATCH(($B$4+A122),$I$11:$I$33,1)))*(($B$4+A122)-INDEX($I$11:$I$33,MATCH(($B$4+A122),$I$11:$I$33,1)))/(INDEX($I$11:$I$33,MATCH(($B$4+A122),$I$11:$I$33,1)+1)-INDEX($I$11:$I$33,MATCH(($B$4+A122),$I$11:$I$33,1))))))),1) -> 1 | D122: =B122*(1+$B$30)^(-A122) -> 0.62710204 | E122: =B122*C122*(1+$B$5)^(-A122) -> 1 | G122: =$B$31+0.125+62*0.25 -> 78.065 | H122: =IF(G122<$B$33,1,0) -> 1 | I122: =H122*(1-$B$6)^(G122-$B$31)*(1+$B$30)^(-G122) -> 0.33370545 | J122: =H122*(1-$B$6)^(G122-$B$31)*L122*(1+$B$5)^(-G122) -> 0.85467286 | L122: =IF($B$7="Oui",1-(IF(($B$4+G122)<=$L$11,$M$11,IF(($B$4+G122)>=$L$12,$M$12,INDEX($M$11:$M$12,MATCH(($B$4+G122),$L$11:$L$12,1))+(INDEX($M$11:$M$12,MATCH(($B$4+G122),$L$11:$L$12,1)+1)-INDEX($M$11:$M$12,MATCH(($B$4+G122),$L$11:$L$12,1)))*(($B$4+G122)-INDEX($L$11:$L$12,MATCH(($B$4+G122),$L$11:$L$12,1)))/(INDEX($L$11:$L$12,MATCH(($B$4+G122),$L$11:$L$12,1)+1)-INDEX($L$11:$L$12,MATCH(($B$4+G122),$L$11:$L$12,1)))))),1) -> 1
A123: =$B$32+0.125+63*0.25 -> 38.985 | B123: =IF(A123<$B$31,1,0) -> 1 | C123: =IF($B$7="Oui",1+((IF(($B$4+A123)<=$I$11,$J$11,IF(($B$4+A123)>=$I$33,$J$33,INDEX($J$11:$J$33,MATCH(($B$4+A123),$I$11:$I$33,1))+(INDEX($J$11:$J$33,MATCH(($B$4+A123),$I$11:$I$33,1)+1)-INDEX($J$11:$J$33,MATCH(($B$4+A123),$I$11:$I$33,1)))*(($B$4+A123)-INDEX($I$11:$I$33,MATCH(($B$4+A123),$I$11:$I$33,1)))/(INDEX($I$11:$I$33,MATCH(($B$4+A123),$I$11:$I$33,1)+1)-INDEX($I$11:$I$33,MATCH(($B$4+A123),$I$11:$I$33,1))))))-(IF(($B$4+A123)<=$L$11,$M$11,IF(($B$4+A123)>=$L$12,$M$12,INDEX($M$11:$M$12,MATCH(($B$4+A123),$L$11:$L$12,1))+(INDEX($M$11:$M$12,MATCH(($B$4+A123),$L$11:$L$12,1)+1)-INDEX($M$11:$M$12,MATCH(($B$4+A123),$L$11:$L$12,1)))*(($B$4+A123)-INDEX($L$11:$L$12,MATCH(($B$4+A123),$L$11:$L$12,1)))/(INDEX($L$11:$L$12,MATCH(($B$4+A123),$L$11:$L$12,1)+1)-INDEX($L$11:$L$12,MATCH(($B$4+A123),$L$11:$L$12,1)))))))/(1-(IF(($B$4+A123)<=$I$11,$J$11,IF(($B$4+A123)>=$I$33,$J$33,INDEX($J$11:$J$33,MATCH(($B$4+A123),$I$11:$I$33,1))+(INDEX($J$11:$J$33,MATCH(($B$4+A123),$I$11:$I$33,1)+1)-INDEX($J$11:$J$33,MATCH(($B$4+A123),$I$11:$I$33,1)))*(($B$4+A123)-INDEX($I$11:$I$33,MATCH(($B$4+A123),$I$11:$I$33,1)))/(INDEX($I$11:$I$33,MATCH(($B$4+A123),$I$11:$I$33,1)+1)-INDEX($I$11:$I$33,MATCH(($B$4+A123),$I$11:$I$33,1))))))),1) -> 1 | D123: =B123*(1+$B$30)^(-A123) -> 0.62521619 | E123: =B123*C123*(1+$B$5)^(-A123) -> 1 | G123: =$B$31+0.125+63*0.25 -> 78.315 | H123: =IF(G123<$B$33,1,0) -> 1 | I123: =H123*(1-$B$6)^(G123-$B$31)*(1+$B$30)^(-G123) -> 0.33186702 | J123: =H123*(1-$B$6)^(G123-$B$31)*L123*(1+$B$5)^(-G123) -> 0.85252812 | L123: =IF($B$7="Oui",1-(IF(($B$4+G123)<=$L$11,$M$11,IF(($B$4+G123)>=$L$12,$M$12,INDEX($M$11:$M$12,MATCH(($B$4+G123),$L$11:$L$12,1))+(INDEX($M$11:$M$12,MATCH(($B$4+G123),$L$11:$L$12,1)+1)-INDEX($M$11:$M$12,MATCH(($B$4+G123),$L$11:$L$12,1)))*(($B$4+G123)-INDEX($L$11:$L$12,MATCH(($B$4+G123),$L$11:$L$12,1)))/(INDEX($L$11:$L$12,MATCH(($B$4+G123),$L$11:$L$12,1)+1)-INDEX($L$11:$L$12,MATCH(($B$4+G123),$L$11:$L$12,1)))))),1) -> 1
A124: =$B$32+0.125+64*0.25 -> 39.235 | B124: =IF(A124<$B$31,1,0) -> 1 | C124: =IF($B$7="Oui",1+((IF(($B$4+A124)<=$I$11,$J$11,IF(($B$4+A124)>=$I$33,$J$33,INDEX($J$11:$J$33,MATCH(($B$4+A124),$I$11:$I$33,1))+(INDEX($J$11:$J$33,MATCH(($B$4+A124),$I$11:$I$33,1)+1)-INDEX($J$11:$J$33,MATCH(($B$4+A124),$I$11:$I$33,1)))*(($B$4+A124)-INDEX($I$11:$I$33,MATCH(($B$4+A124),$I$11:$I$33,1)))/(INDEX($I$11:$I$33,MATCH(($B$4+A124),$I$11:$I$33,1)+1)-INDEX($I$11:$I$33,MATCH(($B$4+A124),$I$11:$I$33,1))))))-(IF(($B$4+A124)<=$L$11,$M$11,IF(($B$4+A124)>=$L$12,$M$12,INDEX($M$11:$M$12,MATCH(($B$4+A124),$L$11:$L$12,1))+(INDEX($M$11:$M$12,MATCH(($B$4+A124),$L$11:$L$12,1)+1)-INDEX($M$11:$M$12,MATCH(($B$4+A124),$L$11:$L$12,1)))*(($B$4+A124)-INDEX($L$11:$L$12,MATCH(($B$4+A124),$L$11:$L$12,1)))/(INDEX($L$11:$L$12,MATCH(($B$4+A124),$L$11:$L$12,1)+1)-INDEX($L$11:$L$12,MATCH(($B$4+A124),$L$11:$L$12,1)))))))/(1-(IF(($B$4+A124)<=$I$11,$J$11,IF(($B$4+A124)>=$I$33,$J$33,INDEX($J$11:$J$33,MATCH(($B$4+A124),$I$11:$I$33,1))+(INDEX($J$11:$J$33,MATCH(($B$4+A124),$I$11:$I$33,1)+1)-INDEX($J$11:$J$33,MATCH(($B$4+A124),$I$11:$I$33,1)))*(($B$4+A124)-INDEX($I$11:$I$33,MATCH(($B$4+A124),$I$11:$I$33,1)))/(INDEX($I$11:$I$33,MATCH(($B$4+A124),$I$11:$I$33,1)+1)-INDEX($I$11:$I$33,MATCH(($B$4+A124),$I$11:$I$33,1))))))),1) -> 1 | D124: =B124*(1+$B$30)^(-A124) -> 0.623336 | E124: =B124*C124*(1+$B$5)^(-A124) -> 1 | G124: =$B$31+0.125+64*0.25 -> 78.565 | H124: =IF(G124<$B$33,1,0) -> 1 | I124: =H124*(1-$B$6)^(G124-$B$31)*(1+$B$30)^(-G124) -> 0.33003872 | J124: =H124*(1-$B$6)^(G124-$B$31)*L124*(1+$B$5)^(-G124) -> 0.85038876 | L124: =IF($B$7="Oui",1-(IF(($B$4+G124)<=$L$11,$M$11,IF(($B$4+G124)>=$L$12,$M$12,INDEX($M$11:$M$12,MATCH(($B$4+G124),$L$11:$L$12,1))+(INDEX($M$11:$M$12,MATCH(($B$4+G124),$L$11:$L$12,1)+1)-INDEX($M$11:$M$12,MATCH(($B$4+G124),$L$11:$L$12,1)))*(($B$4+G124)-INDEX($L$11:$L$12,MATCH(($B$4+G124),$L$11:$L$12,1)))/(INDEX($L$11:$L$12,MATCH(($B$4+G124),$L$11:$L$12,1)+1)-INDEX($L$11:$L$12,MATCH(($B$4+G124),$L$11:$L$12,1)))))),1) -> 1
...

Sheet Sources
A1: Sources
A3: Donnée | B3: Source | C3: Lien
A4: Financement et dépenses des retraites | B4: COR, rapport annuel juin 2026, tableau 2.2 | C4: https://www.cor-retraites.fr/sites/default/files/2026-06/RA_2026_def.pdf
A5: CSG, barème des retraités | B5: Code de la sécurité sociale, art. L136-8 ; seuils 2025 : service-public.gouv.fr | C5: https://www.service-public.gouv.fr/particuliers/vosdroits/F2971
A6: Recettes de CSG d'activité | B6: CCSS, rapport de mai 2026, tableau 1 (recettes 2025) ; valeur du point : calcul du simulateur | C6: https://www.securite-sociale.fr/files/live/sites/SSFR/files/medias/CCSS/2026/CCSS%20mai%202026_assembl%C3%A9_V2.pdf
A7: TVA : rendement et effet sur les prix | B7: DG Trésor, Trésor-Éco n° 371, septembre 2025, tableaux 1 et 2 | C7: https://www.tresor.economie.gouv.fr/Articles/2025/09/25/analyse-de-la-composition-des-recettes-de-tva
A8: Distribution des pensions | B8: Drees, échantillon interrégimes de retraités (EIR) 2020, tableau 5 | C8: https://data.drees.solidarites-sante.gouv.fr/explore/dataset/4178_distribution-des-pensions-mensuelles/information/
A9: Retraités | B9: Drees, effectifs de retraités fin 2024 (17,3 millions de retraités de droit direct, dont 16,4 en France) | C9: https://drees.solidarites-sante.gouv.fr/communique-de-presse-jeux-de-donnees/jeux-de-donnees/effectifs-de-retraites-et-montants-des
A10: Sous-indexation, taux d'annuité | B10: IPP, Perspectives budgétaires 2027, chapitre 3 : sous-indexation des retraites (Aubert, Tô, Tochev, 2026) | C10: https://www.ipp.eu/wp-content/uploads/2026/07/Chapitre_Desindexation_retraite___Rapport_Perspectives_Budgetaires_2027-4.pdf
A11: Décès | B11: Insee Première n° 2087, Bilan démographique 2025 | C11: https://www.insee.fr/fr/statistiques/8719824
A12: Épargne des ménages | B12: Insee Première n° 1815, 2020 (enquête Budget de famille 2017) | C12: https://www.insee.fr/fr/statistiques/4764600
A13: Niveaux de vie | B13: Insee, niveau de vie selon le statut d'activité (ERFS), euros constants 2024 | C13: https://www.insee.fr/fr/statistiques/2415628
A14: Composition des revenus | B14: COR, rapport annuel juin 2026, figure 3.8 : pensions 77,8 % du revenu des ménages retraités, revenus d'activité 84,1 % de celui des ménages actifs
A15: Rendement par génération | B15: COR, rapport annuel de juin 2026 | C15: https://www.cor-retraites.fr/sites/default/files/2026-06/RA_2026_def.pdf
A16: Impôts affectés aux retraites | B16: COR, « L'état du financement du système de retraite », séance du 17 octobre 2019 ; COR 2026, figure 2.11 | C16: https://www.cor-retraites.fr/sites/default/files/2019-11/Doc_2_%C3%A9tat_financement_0.pdf
A17: Emploi, salaires | B17: Insee, Emploi, chômage, revenus du travail, édition 2025 : 30,4 millions de personnes en emploi fin 2024 ; Insee, Comptes de la Nation 2024, tableau 6.205 (salaires et traitements bruts, total branches) | C17: https://www.insee.fr/fr/statistiques/8574681?sommaire=8574832
